Workbook
Name Печать: #REF!
Name Опрессовка: 'ТЕХ.ЛИСТ.ОБ'!$B$1:$N$1

Sheet ТЕХ.ЛИСТ.ОБ
A1: {=(БД.ОП[Название])} -> Резка | B1: =IFERROR(__xludf.DUMMYFUNCTION("IF(A1="""","""",IFERROR(TRANSPOSE(query(БД.ОБ,""SELECT P WHERE D='""&A1&""'"")),""""))"),"")
A2: Резка | B2: =IFERROR(__xludf.DUMMYFUNCTION("IF(A2="""","""",IFERROR(TRANSPOSE(query(БД.ОБ,""SELECT P WHERE D='""&A2&""'"")),""""))"),"")
A3: Резка линейных материалов | B3: =IFERROR(__xludf.DUMMYFUNCTION("IF(A3="""","""",IFERROR(TRANSPOSE(query(БД.ОБ,""SELECT P WHERE D='""&A3&""'"")),""""))"),"")
A4: Резка линейных материалов | B4: =IFERROR(__xludf.DUMMYFUNCTION("IF(A4="""","""",IFERROR(TRANSPOSE(query(БД.ОБ,""SELECT P WHERE D='""&A4&""'"")),""""))"),"")
A5: Резка с разделкой | B5: =IFERROR(__xludf.DUMMYFUNCTION("IF(A5="""","""",IFERROR(TRANSPOSE(query(БД.ОБ,""SELECT P WHERE D='""&A5&""'"")),""""))"),"")
A6: Резка с разделкой | B6: =IFERROR(__xludf.DUMMYFUNCTION("IF(A6="""","""",IFERROR(TRANSPOSE(query(БД.ОБ,""SELECT P WHERE D='""&A6&""'"")),""""))"),"")
A7: Резка с разделкой | B7: =IFERROR(__xludf.DUMMYFUNCTION("IF(A7="""","""",IFERROR(TRANSPOSE(query(БД.ОБ,""SELECT P WHERE D='""&A7&""'"")),""""))"),"")
A8: Резка с разделкой | B8: =IFERROR(__xludf.DUMMYFUNCTION("IF(A8="""","""",IFERROR(TRANSPOSE(query(БД.ОБ,""SELECT P WHERE D='""&A8&""'"")),""""))"),"")
A9: Резка с разделкой+ маркировка | B9: =IFERROR(__xludf.DUMMYFUNCTION("IF(A9="""","""",IFERROR(TRANSPOSE(query(БД.ОБ,""SELECT P WHERE D='""&A9&""'"")),""""))"),"")
A10: Резка с разделкой+ маркировка | B10: =IFERROR(__xludf.DUMMYFUNCTION("IF(A10="""","""",IFERROR(TRANSPOSE(query(БД.ОБ,""SELECT P WHERE D='""&A10&""'"")),""""))"),"")
A11: Резка с разделкой+ маркировка | B11: =IFERROR(__xludf.DUMMYFUNCTION("IF(A11="""","""",IFERROR(TRANSPOSE(query(БД.ОБ,""SELECT P WHERE D='""&A11&""'"")),""""))"),"")
A12: Резка с разделкой+ маркировка | B12: =IFERROR(__xludf.DUMMYFUNCTION("IF(A12="""","""",IFERROR(TRANSPOSE(query(БД.ОБ,""SELECT P WHERE D='""&A12&""'"")),""""))"),"")
A13: Автомат резка + опрессовка | B13: =IFERROR(__xludf.DUMMYFUNCTION("IF(A13="""","""",IFERROR(TRANSPOSE(query(БД.ОБ,""SELECT P WHERE D='""&A13&""'"")),""""))"),"")
A14: Автомат резка + опрессовка + лужение | B14: =IFERROR(__xludf.DUMMYFUNCTION("IF(A14="""","""",IFERROR(TRANSPOSE(query(БД.ОБ,""SELECT P WHERE D='""&A14&""'"")),""""))"),"")
A15: Автомат резка + опрессовка | B15: =IFERROR(__xludf.DUMMYFUNCTION("IF(A15="""","""",IFERROR(TRANSPOSE(query(БД.ОБ,""SELECT P WHERE D='""&A15&""'"")),""""))"),"")
A16: Резка линейных материалов | B16: =IFERROR(__xludf.DUMMYFUNCTION("IF(A16="""","""",IFERROR(TRANSPOSE(query(БД.ОБ,""SELECT P WHERE D='""&A16&""'"")),""""))"),"")
A17: Резка линейных материалов | B17: =IFERROR(__xludf.DUMMYFUNCTION("IF(A17="""","""",IFERROR(TRANSPOSE(query(БД.ОБ,""SELECT P WHERE D='""&A17&""'"")),""""))"),"")
A18: Резка линейных материалов | B18: =IFERROR(__xludf.DUMMYFUNCTION("IF(A18="""","""",IFERROR(TRANSPOSE(query(БД.ОБ,""SELECT P WHERE D='""&A18&""'"")),""""))"),"")
A19: Разделка | B19: =IFERROR(__xludf.DUMMYFUNCTION("IF(A19="""","""",IFERROR(TRANSPOSE(query(БД.ОБ,""SELECT P WHERE D='""&A19&""'"")),""""))"),"")
A20: Разделка | B20: =IFERROR(__xludf.DUMMYFUNCTION("IF(A20="""","""",IFERROR(TRANSPOSE(query(БД.ОБ,""SELECT P WHERE D='""&A20&""'"")),""""))"),"")
A21: Разделка | B21: =IFERROR(__xludf.DUMMYFUNCTION("IF(A21="""","""",IFERROR(TRANSPOSE(query(БД.ОБ,""SELECT P WHERE D='""&A21&""'"")),""""))"),"")
A22: Разделка | B22: =IFERROR(__xludf.DUMMYFUNCTION("IF(A22="""","""",IFERROR(TRANSPOSE(query(БД.ОБ,""SELECT P WHERE D='""&A22&""'"")),""""))"),"")
A23: Разделка | B23: =IFERROR(__xludf.DUMMYFUNCTION("IF(A23="""","""",IFERROR(TRANSPOSE(query(БД.ОБ,""SELECT P WHERE D='""&A23&""'"")),""""))"),"")
A24: Разделка | B24: =IFERROR(__xludf.DUMMYFUNCTION("IF(A24="""","""",IFERROR(TRANSPOSE(query(БД.ОБ,""SELECT P WHERE D='""&A24&""'"")),""""))"),"")
A25: Разделка | B25: =IFERROR(__xludf.DUMMYFUNCTION("IF(A25="""","""",IFERROR(TRANSPOSE(query(БД.ОБ,""SELECT P WHERE D='""&A25&""'"")),""""))"),"")
A26: Разделка | B26: =IFERROR(__xludf.DUMMYFUNCTION("IF(A26="""","""",IFERROR(TRANSPOSE(query(БД.ОБ,""SELECT P WHERE D='""&A26&""'"")),""""))"),"")
A27: Разделка | B27: =IFERROR(__xludf.DUMMYFUNCTION("IF(A27="""","""",IFERROR(TRANSPOSE(query(БД.ОБ,""SELECT P WHERE D='""&A27&""'"")),""""))"),"")
A28: Разделка | B28: =IFERROR(__xludf.DUMMYFUNCTION("IF(A28="""","""",IFERROR(TRANSPOSE(query(БД.ОБ,""SELECT P WHERE D='""&A28&""'"")),""""))"),"")
A29: Разделка | B29: =IFERROR(__xludf.DUMMYFUNCTION("IF(A29="""","""",IFERROR(TRANSPOSE(query(БД.ОБ,""SELECT P WHERE D='""&A29&""'"")),""""))"),"")
A30: Разделка | B30: =IFERROR(__xludf.DUMMYFUNCTION("IF(A30="""","""",IFERROR(TRANSPOSE(query(БД.ОБ,""SELECT P WHERE D='""&A30&""'"")),""""))"),"")
A31: Разделка | B31: =IFERROR(__xludf.DUMMYFUNCTION("IF(A31="""","""",IFERROR(TRANSPOSE(query(БД.ОБ,""SELECT P WHERE D='""&A31&""'"")),""""))"),"")
A32: Разделка | B32: =IFERROR(__xludf.DUMMYFUNCTION("IF(A32="""","""",IFERROR(TRANSPOSE(query(БД.ОБ,""SELECT P WHERE D='""&A32&""'"")),""""))"),"")
A33: Разделка | B33: =IFERROR(__xludf.DUMMYFUNCTION("IF(A33="""","""",IFERROR(TRANSPOSE(query(БД.ОБ,""SELECT P WHERE D='""&A33&""'"")),""""))"),"")
A34: Опрессовка терминалов | B34: =IFERROR(__xludf.DUMMYFUNCTION("IF(A34="""","""",IFERROR(TRANSPOSE(query(БД.ОБ,""SELECT P WHERE D='""&A34&""'"")),""""))"),"")
A35: Опрессовка терминалов | B35: =IFERROR(__xludf.DUMMYFUNCTION("IF(A35="""","""",IFERROR(TRANSPOSE(query(БД.ОБ,""SELECT P WHERE D='""&A35&""'"")),""""))"),"")
A36: Опрессовка терминалов | B36: =IFERROR(__xludf.DUMMYFUNCTION("IF(A36="""","""",IFERROR(TRANSPOSE(query(БД.ОБ,""SELECT P WHERE D='""&A36&""'"")),""""))"),"")
A37: Опрессовка терминалов | B37: =IFERROR(__xludf.DUMMYFUNCTION("IF(A37="""","""",IFERROR(TRANSPOSE(query(БД.ОБ,""SELECT P WHERE D='""&A37&""'"")),""""))"),"")
A38: Опрессовка терминалов | B38: =IFERROR(__xludf.DUMMYFUNCTION("IF(A38="""","""",IFERROR(TRANSPOSE(query(БД.ОБ,""SELECT P WHERE D='""&A38&""'"")),""""))"),"")
A39: Опрессовка наконечников | B39: =IFERROR(__xludf.DUMMYFUNCTION("IF(A39="""","""",IFERROR(TRANSPOSE(query(БД.ОБ,""SELECT P WHERE D='""&A39&""'"")),""""))"),"")
A40: Опрессовка наконечников | B40: =IFERROR(__xludf.DUMMYFUNCTION("IF(A40="""","""",IFERROR(TRANSPOSE(query(БД.ОБ,""SELECT P WHERE D='""&A40&""'"")),""""))"),"")
A41: Опрессовка наконечников | B41: =IFERROR(__xludf.DUMMYFUNCTION("IF(A41="""","""",IFERROR(TRANSPOSE(query(БД.ОБ,""SELECT P WHERE D='""&A41&""'"")),""""))"),"")
A42: Опрессовка | B42: =IFERROR(__xludf.DUMMYFUNCTION("IF(A42="""","""",IFERROR(TRANSPOSE(query(БД.ОБ,""SELECT P WHERE D='""&A42&""'"")),""""))"),"")
A43: Опрессовка | B43: =IFERROR(__xludf.DUMMYFUNCTION("IF(A43="""","""",IFERROR(TRANSPOSE(query(БД.ОБ,""SELECT P WHERE D='""&A43&""'"")),""""))"),"")
A44: Опрессовка | B44: =IFERROR(__xludf.DUMMYFUNCTION("IF(A44="""","""",IFERROR(TRANSPOSE(query(БД.ОБ,""SELECT P WHERE D='""&A44&""'"")),""""))"),"")
A45: Опрессовка | B45: =IFERROR(__xludf.DUMMYFUNCTION("IF(A45="""","""",IFERROR(TRANSPOSE(query(БД.ОБ,""SELECT P WHERE D='""&A45&""'"")),""""))"),"")
A46: Опрессовка | B46: =IFERROR(__xludf.DUMMYFUNCTION("IF(A46="""","""",IFERROR(TRANSPOSE(query(БД.ОБ,""SELECT P WHERE D='""&A46&""'"")),""""))"),"")
A47: Опрессовка | B47: =IFERROR(__xludf.DUMMYFUNCTION("IF(A47="""","""",IFERROR(TRANSPOSE(query(БД.ОБ,""SELECT P WHERE D='""&A47&""'"")),""""))"),"")
A48: Ленточный обжим | B48: =IFERROR(__xludf.DUMMYFUNCTION("IF(A48="""","""",IFERROR(TRANSPOSE(query(БД.ОБ,""SELECT P WHERE D='""&A48&""'"")),""""))"),"")
A49: Пайка | B49: =IFERROR(__xludf.DUMMYFUNCTION("IF(A49="""","""",IFERROR(TRANSPOSE(query(БД.ОБ,""SELECT P WHERE D='""&A49&""'"")),""""))"),"")
A50: Пайка | B50: =IFERROR(__xludf.DUMMYFUNCTION("IF(A50="""","""",IFERROR(TRANSPOSE(query(БД.ОБ,""SELECT P WHERE D='""&A50&""'"")),""""))"),"")
A51: Пайка | B51: =IFERROR(__xludf.DUMMYFUNCTION("IF(A51="""","""",IFERROR(TRANSPOSE(query(БД.ОБ,""SELECT P WHERE D='""&A51&""'"")),""""))"),"")
A52: Пайка | B52: =IFERROR(__xludf.DUMMYFUNCTION("IF(A52="""","""",IFERROR(TRANSPOSE(query(БД.ОБ,""SELECT P WHERE D='""&A52&""'"")),""""))"),"")
A53: Пайка | B53: =IFERROR(__xludf.DUMMYFUNCTION("IF(A53="""","""",IFERROR(TRANSPOSE(query(БД.ОБ,""SELECT P WHERE D='""&A53&""'"")),""""))"),"")
A54: Пайка | B54: =IFERROR(__xludf.DUMMYFUNCTION("IF(A54="""","""",IFERROR(TRANSPOSE(query(БД.ОБ,""SELECT P WHERE D='""&A54&""'"")),""""))"),"")
A55: Пайка | B55: =IFERROR(__xludf.DUMMYFUNCTION("IF(A55="""","""",IFERROR(TRANSPOSE(query(БД.ОБ,""SELECT P WHERE D='""&A55&""'"")),""""))"),"")
A56: Пайка | B56: =IFERROR(__xludf.DUMMYFUNCTION("IF(A56="""","""",IFERROR(TRANSPOSE(query(БД.ОБ,""SELECT P WHERE D='""&A56&""'"")),""""))"),"")
A57: Пайка | B57: =IFERROR(__xludf.DUMMYFUNCTION("IF(A57="""","""",IFERROR(TRANSPOSE(query(БД.ОБ,""SELECT P WHERE D='""&A57&""'"")),""""))"),"")
A58: Пайка | B58: =IFERROR(__xludf.DUMMYFUNCTION("IF(A58="""","""",IFERROR(TRANSPOSE(query(БД.ОБ,""SELECT P WHERE D='""&A58&""'"")),""""))"),"")
A59: Пайка | B59: =IFERROR(__xludf.DUMMYFUNCTION("IF(A59="""","""",IFERROR(TRANSPOSE(query(БД.ОБ,""SELECT P WHERE D='""&A59&""'"")),""""))"),"")
A60: Пайка | B60: =IFERROR(__xludf.DUMMYFUNCTION("IF(A60="""","""",IFERROR(TRANSPOSE(query(БД.ОБ,""SELECT P WHERE D='""&A60&""'"")),""""))"),"")
A61: Пайка | B61: =IFERROR(__xludf.DUMMYFUNCTION("IF(A61="""","""",IFERROR(TRANSPOSE(query(БД.ОБ,""SELECT P WHERE D='""&A61&""'"")),""""))"),"")
A62: Пайка | B62: =IFERROR(__xludf.DUMMYFUNCTION("IF(A62="""","""",IFERROR(TRANSPOSE(query(БД.ОБ,""SELECT P WHERE D='""&A62&""'"")),""""))"),"")
A63: Пайка | B63: =IFERROR(__xludf.DUMMYFUNCTION("IF(A63="""","""",IFERROR(TRANSPOSE(query(БД.ОБ,""SELECT P WHERE D='""&A63&""'"")),""""))"),"")
A64: Пайка | B64: =IFERROR(__xludf.DUMMYFUNCTION("IF(A64="""","""",IFERROR(TRANSPOSE(query(БД.ОБ,""SELECT P WHERE D='""&A64&""'"")),""""))"),"")
A65: Пайка | B65: =IFERROR(__xludf.DUMMYFUNCTION("IF(A65="""","""",IFERROR(TRANSPOSE(query(БД.ОБ,""SELECT P WHERE D='""&A65&""'"")),""""))"),"")
A66: Пайка | B66: =IFERROR(__xludf.DUMMYFUNCTION("IF(A66="""","""",IFERROR(TRANSPOSE(query(БД.ОБ,""SELECT P WHERE D='""&A66&""'"")),""""))"),"")
A67: Пайка | B67: =IFERROR(__xludf.DUMMYFUNCTION("IF(A67="""","""",IFERROR(TRANSPOSE(query(БД.ОБ,""SELECT P WHERE D='""&A67&""'"")),""""))"),"")
A68: Пайка | B68: =IFERROR(__xludf.DUMMYFUNCTION("IF(A68="""","""",IFERROR(TRANSPOSE(query(БД.ОБ,""SELECT P WHERE D='""&A68&""'"")),""""))"),"")
A69: Пайка | B69: =IFERROR(__xludf.DUMMYFUNCTION("IF(A69="""","""",IFERROR(TRANSPOSE(query(БД.ОБ,""SELECT P WHERE D='""&A69&""'"")),""""))"),"")
A70: Лужение | B70: =IFERROR(__xludf.DUMMYFUNCTION("IF(A70="""","""",IFERROR(TRANSPOSE(query(БД.ОБ,""SELECT P WHERE D='""&A70&""'"")),""""))"),"")
A71: Монтаж терминалов | B71: =IFERROR(__xludf.DUMMYFUNCTION("IF(A71="""","""",IFERROR(TRANSPOSE(query(БД.ОБ,""SELECT P WHERE D='""&A71&""'"")),""""))"),"")
A72: Монтаж терминалов | B72: =IFERROR(__xludf.DUMMYFUNCTION("IF(A72="""","""",IFERROR(TRANSPOSE(query(БД.ОБ,""SELECT P WHERE D='""&A72&""'"")),""""))"),"")
A73: Монтаж терминалов | B73: =IFERROR(__xludf.DUMMYFUNCTION("IF(A73="""","""",IFERROR(TRANSPOSE(query(БД.ОБ,""SELECT P WHERE D='""&A73&""'"")),""""))"),"")
A74: Монтаж терминалов | B74: =IFERROR(__xludf.DUMMYFUNCTION("IF(A74="""","""",IFERROR(TRANSPOSE(query(БД.ОБ,""SELECT P WHERE D='""&A74&""'"")),""""))"),"")
A75: Монтаж терминалов | B75: =IFERROR(__xludf.DUMMYFUNCTION("IF(A75="""","""",IFERROR(TRANSPOSE(query(БД.ОБ,""SELECT P WHERE D='""&A75&""'"")),""""))"),"")
A76: Монтаж RJ | B76: =IFERROR(__xludf.DUMMYFUNCTION("IF(A76="""","""",IFERROR(TRANSPOSE(query(БД.ОБ,""SELECT P WHERE D='""&A76&""'"")),""""))"),"")
A77: Монтаж RJ | B77: =IFERROR(__xludf.DUMMYFUNCTION("IF(A77="""","""",IFERROR(TRANSPOSE(query(БД.ОБ,""SELECT P WHERE D='""&A77&""'"")),""""))"),"")
A78: Монтаж корпуса | B78: =IFERROR(__xludf.DUMMYFUNCTION("IF(A78="""","""",IFERROR(TRANSPOSE(query(БД.ОБ,""SELECT P WHERE D='""&A78&""'"")),""""))"),"")
A79: Монтаж корпуса | B79: =IFERROR(__xludf.DUMMYFUNCTION("IF(A79="""","""",IFERROR(TRANSPOSE(query(БД.ОБ,""SELECT P WHERE D='""&A79&""'"")),""""))"),"")
A80: Монтаж корпуса | B80: =IFERROR(__xludf.DUMMYFUNCTION("IF(A80="""","""",IFERROR(TRANSPOSE(query(БД.ОБ,""SELECT P WHERE D='""&A80&""'"")),""""))"),"")
A81: Монтаж корпуса | B81: =IFERROR(__xludf.DUMMYFUNCTION("IF(A81="""","""",IFERROR(TRANSPOSE(query(БД.ОБ,""SELECT P WHERE D='""&A81&""'"")),""""))"),"")
A82: Монтаж | B82: =IFERROR(__xludf.DUMMYFUNCTION("IF(A82="""","""",IFERROR(TRANSPOSE(query(БД.ОБ,""SELECT P WHERE D='""&A82&""'"")),""""))"),"")
A83: Монтаж | B83: =IFERROR(__xludf.DUMMYFUNCTION("IF(A83="""","""",IFERROR(TRANSPOSE(query(БД.ОБ,""SELECT P WHERE D='""&A83&""'"")),""""))"),"")
A84: Монтаж | B84: =IFERROR(__xludf.DUMMYFUNCTION("IF(A84="""","""",IFERROR(TRANSPOSE(query(БД.ОБ,""SELECT P WHERE D='""&A84&""'"")),""""))"),"")
A85: Монтаж | B85: =IFERROR(__xludf.DUMMYFUNCTION("IF(A85="""","""",IFERROR(TRANSPOSE(query(БД.ОБ,""SELECT P WHERE D='""&A85&""'"")),""""))"),"")
A86: Монтаж | B86: =IFERROR(__xludf.DUMMYFUNCTION("IF(A86="""","""",IFERROR(TRANSPOSE(query(БД.ОБ,""SELECT P WHERE D='""&A86&""'"")),""""))"),"")
A87: Монтаж | B87: =IFERROR(__xludf.DUMMYFUNCTION("IF(A87="""","""",IFERROR(TRANSPOSE(query(БД.ОБ,""SELECT P WHERE D='""&A87&""'"")),""""))"),"")
A88: Складывание жилы | B88: =IFERROR(__xludf.DUMMYFUNCTION("IF(A88="""","""",IFERROR(TRANSPOSE(query(БД.ОБ,""SELECT P WHERE D='""&A88&""'"")),""""))"),"")
A89: Заделка свободных концов | B89: =IFERROR(__xludf.DUMMYFUNCTION("IF(A89="""","""",IFERROR(TRANSPOSE(query(БД.ОБ,""SELECT P WHERE D='""&A89&""'"")),""""))"),"")
A90: Герметизация | B90: =IFERROR(__xludf.DUMMYFUNCTION("IF(A90="""","""",IFERROR(TRANSPOSE(query(БД.ОБ,""SELECT P WHERE D='""&A90&""'"")),""""))"),"")
A91: Монтаж | B91: =IFERROR(__xludf.DUMMYFUNCTION("IF(A91="""","""",IFERROR(TRANSPOSE(query(БД.ОБ,""SELECT P WHERE D='""&A91&""'"")),""""))"),"")
A92: Монтаж | B92: =IFERROR(__xludf.DUMMYFUNCTION("IF(A92="""","""",IFERROR(TRANSPOSE(query(БД.ОБ,""SELECT P WHERE D='""&A92&""'"")),""""))"),"")
A93: Монтаж | B93: =IFERROR(__xludf.DUMMYFUNCTION("IF(A93="""","""",IFERROR(TRANSPOSE(query(БД.ОБ,""SELECT P WHERE D='""&A93&""'"")),""""))"),"")
A94: Монтаж | B94: =IFERROR(__xludf.DUMMYFUNCTION("IF(A94="""","""",IFERROR(TRANSPOSE(query(БД.ОБ,""SELECT P WHERE D='""&A94&""'"")),""""))"),"")
A95: Монтаж | B95: =IFERROR(__xludf.DUMMYFUNCTION("IF(A95="""","""",IFERROR(TRANSPOSE(query(БД.ОБ,""SELECT P WHERE D='""&A95&""'"")),""""))"),"")
A96: Монтаж | B96: =IFERROR(__xludf.DUMMYFUNCTION("IF(A96="""","""",IFERROR(TRANSPOSE(query(БД.ОБ,""SELECT P WHERE D='""&A96&""'"")),""""))"),"")
A97: Усадка | B97: =IFERROR(__xludf.DUMMYFUNCTION("IF(A97="""","""",IFERROR(TRANSPOSE(query(БД.ОБ,""SELECT P WHERE D='""&A97&""'"")),""""))"),"")
A98: Усадка | B98: =IFERROR(__xludf.DUMMYFUNCTION("IF(A98="""","""",IFERROR(TRANSPOSE(query(БД.ОБ,""SELECT P WHERE D='""&A98&""'"")),""""))"),"")
A99: Усадка | B99: =IFERROR(__xludf.DUMMYFUNCTION("IF(A99="""","""",IFERROR(TRANSPOSE(query(БД.ОБ,""SELECT P WHERE D='""&A99&""'"")),""""))"),"")
A100: Усадка | B100: =IFERROR(__xludf.DUMMYFUNCTION("IF(A100="""","""",IFERROR(TRANSPOSE(query(БД.ОБ,""SELECT P WHERE D='""&A100&""'"")),""""))"),"")
...

Sheet БД.МАТ
A1: Наименование | B1: Группа | C1: Производитель | D1: Серия | E1: Размер до, мм | F1: Размер после, мм | G1: Коэф. усадки | H1: Цвет | I1: Клеевой слой | J1: Материал | K1: Темп. от, °C | L1: Темп. до, °C | M1: Ед. изм. | N1: Закупок | O1: Цена посл., ₽ без НДС | P1: Поставщик | Q1: Ссылка на datasheet | R1: Источник данных
A2: ТУТнг 4/2 черная | B2: ТУТ | C2: КВТ Калуга | D2: ТУТнг-LS | E2: 4 | F2: 2 | G2: 2:1 | H2: черный | I2: нет | J2: полиолефин нг-LS (низкое дымо- и газовыделение) | K2: -55 | L2: 125 | M2: м | N2: 89 | O2: 11.5 | P2: electro-mpo.ru | Q2: https://www.electro-mpo.ru/catalog/materialy/t26_trubki_termousadochnye_chernye_rossiya/t2670_trubka_tut4_2_termousazhivaemaya_dvnutr_4_2m/ | R2: https://www.electro-mpo.ru/catalog/materialy/t26_trubki_termousadochnye_chernye_rossiya/t2670_trubka_tut4_2_termousazhivaemaya_dvnutr_4_2m/
A3: ТУТнг 6/3 черная | B3: ТУТ | C3: КВТ Калуга | D3: ТУТнг-LS | E3: 6 | F3: 3 | G3: 2:1 | H3: черный | I3: нет | J3: полиолефин нг-LS (низкое дымо- и газовыделение) | K3: -55 | L3: 125 | M3: м | N3: 74 | O3: 17.5 | P3: electro-mpo.ru | Q3: https://www.electro-mpo.ru/catalog/materialy/t26_trubki_termousadochnye_chernye_rossiya/t2671_trubka_tut6_3_termousazhivaemaya_dvnutr_6_3m/ | R3: https://www.electro-mpo.ru/catalog/materialy/t26_trubki_termousadochnye_chernye_rossiya/t2671_trubka_tut6_3_termousazhivaemaya_dvnutr_6_3m/
A4: ТУТнг 2/1 черная | B4: ТУТ | C4: КВТ Калуга | D4: ТУТнг-LS | E4: 2 | F4: 1 | G4: 2:1 | H4: черный | I4: нет | J4: полиолефин нг-LS (низкое дымо- и газовыделение) | K4: -55 | L4: 125 | M4: м | N4: 59 | O4: 7 | P4: electro-mpo.ru | Q4: https://www.electro-mpo.ru/catalog/materialy/t26_trubki_termousadochnye_chernye_rossiya/t2669_trubka_tut2_1_termousazhivaemaya_dvnutr_2_1m/ | R4: https://www.electro-mpo.ru/catalog/materialy/t26_trubki_termousadochnye_chernye_rossiya/t2669_trubka_tut2_1_termousazhivaemaya_dvnutr_2_1m/
A5: ТУТнг 1,0/0,5 черная | B5: ТУТ | C5: Rexant | D5: ТУТнг-LS(2:1) 20-1006 | E5: 1 | F5: 0.5 | G5: 2:1 | H5: черный | I5: нет | J5: полиолефин | K5: -40 | L5: 125 | M5: м | N5: 20 | O5: 73 | P5: vseinstrumenti.ru | Q5: https://www.vseinstrumenti.ru/product/termousadka-rexant-1-0-0-5-mm-1-m-chernaya-20-1006-882044/ | R5: https://www.vseinstrumenti.ru/product/termousadka-rexant-1-0-0-5-mm-1-m-chernaya-20-1006-882044/ ; последняя цена 73,0 (08.2026) против 8–9 ₽ ранее — вероятно другая фасовка — решено агентом — проверить
A6: ТУТ 10/5 черная | B6: ТУТ | E6: 10 | F6: 5 | G6: 2:1 | H6: черный | I6: нет | M6: м | N6: 19 | O6: 23.6 | P6: electro-mpo.ru | Q6: https://www.electro-mpo.ru/catalog/materialy/t26_trubki_termousadochnye_chernye_rossiya/t2673_trubka_tut10_5_termousazhivaemaya_dvnutr_10_/ | R6: размер и цвет из обозначения закупки, карточка electro-mpo t2673 ТУТ 10/5; производитель/материал/температуры не сняты — решено агентом — проверить
A7: ТУТ 8/4 черная | B7: ТУТ | E7: 8 | F7: 4 | G7: 2:1 | H7: черный | I7: нет | M7: м | N7: 27 | O7: 19 | P7: electro-mpo.ru | Q7: https://www.electro-mpo.ru/catalog/materialy/t26_trubki_termousadochnye_chernye_rossiya/t2671_trubka_tut6_3_termousazhivaemaya_dvnutr_6_3m/?yadiscount=eyJhIjo1MDAsImRwIjoxLCJsdCI6MTIwLCJwIjoxMCwidCI6MSwidHMiOjE3NzA4MjExMzF9&ysclid=mli56i2uag57995138 | R7: https://www.electro-mpo.ru/catalog/materialy/t26_trubki_termousadochnye_chernye_rossiya/t2671_trubka_tut6_3_termousazhivaemaya_dvnutr_6_3m/ — ссылка в сводке ведёт на карточку ТУТ 6/3мм, а не 8/4мм; размер/цвет/коэф. усадки взяты из текста обозначения — решено агентом — проверить
A8: ТТК 6/2 черная | B8: ТТК | C8: КВТ Калуга | D8: ТТК(3:1) | E8: 6 | F8: 2 | G8: 3:1 | H8: черный | I8: да | J8: полиолефин нг | K8: -55 | L8: 125 | M8: м | N8: 21 | O8: 27 | P8: electro-mpo.ru | Q8: https://www.electro-mpo.ru/catalog/materialy/t32_trubki_termousadochnye_kleevye_3_1_elektromont/t3266-trubka-ttk-6-2-termousazhivaemaya-s-kleem-ch/ | R8: https://www.electro-mpo.ru/catalog/materialy/t32_trubki_termousadochnye_kleevye_3_1_elektromont/t3266-trubka-ttk-6-2-termousazhivaemaya-s-kleem-ch/
A9: ТТК 12/4 черная | B9: ТТК | C9: КВТ Калуга | D9: ТТК(3:1) | E9: 12 | F9: 4 | G9: 3:1 | H9: черный | I9: да | J9: полиолефин нг | K9: -55 | L9: 125 | M9: м | N9: 19 | O9: 112 | P9: electro-mpo.ru | Q9: https://www.electro-mpo.ru/catalog/materialy/t32_trubki_termousadochnye_kleevye_3_1_elektromont/t3268-trubka-ttk-12-4-termousazhivaemaya-s-kleem-ch/ | R9: https://www.electro-mpo.ru/catalog/materialy/t32_trubki_termousadochnye_kleevye_3_1_elektromont/t3268-trubka-ttk-12-4-termousazhivaemaya-s-kleem-ch/
A10: ТУТ 3,0/1,5 черная | B10: ТУТ | C10: Rexant | D10: 20-3006 | E10: 3 | F10: 1.5 | G10: 2:1 | H10: черный | I10: нет | J10: полиолефин | K10: -55 | L10: 105 | M10: м | N10: 16 | O10: 11.5 | P10: electro-mpo.ru | Q10: https://www.electro-mpo.ru/catalog/materialy/t29_trubki_termousadochnye_elektromontazh_etelec_i/t2930-trubka-20-3006-3-1-5mm-termousazhivaemaya-ch/ | R10: https://www.electro-mpo.ru/catalog/materialy/t29_trubki_termousadochnye_elektromontazh_etelec_i/t2930-trubka-20-3006-3-1-5mm-termousazhivaemaya-ch/
A11: ТТК 4,8/1,6 черная | B11: ТТК | C11: КВТ Калуга | D11: ТТК(3:1) | E11: 4.8 | F11: 1.6 | G11: 3:1 | H11: черный | I11: да | J11: полиолефин нг | K11: -55 | L11: 125 | M11: м | N11: 13 | O11: 39.5 | P11: electro-mpo.ru | Q11: https://www.electro-mpo.ru/catalog/materialy/t32_trubki_termousadochnye_kleevye_3_1_elektromont/t3265-trubka-ttk-4-8-1-6-termousazhivaemaya-s-klee/ | R11: https://www.electro-mpo.ru/catalog/materialy/t32_trubki_termousadochnye_kleevye_3_1_elektromont/t3265-trubka-ttk-4-8-1-6-termousazhivaemaya-s-klee/
A12: ТУТнг 12/6 черная | B12: ТУТ | C12: КВТ Калуга | D12: ТУТнг-LS | E12: 12 | F12: 6 | G12: 2:1 | H12: черный | I12: нет | J12: полиолефин нг-LS (низкое дымо- и газовыделение) | K12: -55 | L12: 125 | M12: м | N12: 12 | O12: 32.5 | P12: electro-mpo.ru | Q12: https://www.electro-mpo.ru/catalog/materialy/t26_trubki_termousadochnye_chernye_rossiya/t2674_trubka_tut12_6_termousazhivaemaya_dvnutr_12_/ | R12: https://www.electro-mpo.ru/catalog/materialy/t26_trubki_termousadochnye_chernye_rossiya/t2674_trubka_tut12_6_termousazhivaemaya_dvnutr_12_/
A13: ТУТ 16/8 черная | B13: ТУТ | E13: 16 | F13: 8 | G13: 2:1 | H13: черный | I13: нет | M13: м | N13: 11 | O13: 41.5 | Q13: https://www.electro-mpo.ru/catalog/materialy/t26_trubki_termousadochnye_chernye_rossiya/t2623_trubka_tut16_8_termousazhivaemaya_dvnutr_16_/?ysclid=mqi5cde33z61061371 | R13: https://www.electro-mpo.ru/catalog/materialy/t26_trubki_termousadochnye_chernye_rossiya/t2623_trubka_tut16_8_termousazhivaemaya_dvnutr_16_/ — страница недоступна (404 на дату проверки); размер/цвет/коэф. усадки взяты из текста обозначения — решено агентом — проверить
A14: ТТК 3/1 черная | B14: ТТК | C14: КВТ Калуга | D14: ТТК(3:1) | E14: 3 | F14: 1 | G14: 3:1 | H14: черный | I14: да | J14: полиолефин нг | K14: -55 | L14: 125 | M14: м | N14: 10 | O14: 28.5 | P14: electro-mpo.ru | Q14: https://www.electro-mpo.ru/catalog/materialy/t32_trubki_termousadochnye_kleevye_3_1_elektromont/t3264-trubka-ttk-3-1-3-1-0-termousazhivaemaya-s-kl/ | R14: https://www.electro-mpo.ru/catalog/materialy/t32_trubki_termousadochnye_kleevye_3_1_elektromont/t3264-trubka-ttk-3-1-3-1-0-termousazhivaemaya-s-kl/
A15: ТТК 9/3 черная | B15: ТТК | C15: КВТ Калуга | D15: ТТК(3:1) | E15: 9 | F15: 3 | G15: 3:1 | H15: черный | I15: да | J15: полиолефин нг | K15: -55 | L15: 125 | M15: м | N15: 10 | O15: 73.5 | P15: electro-mpo.ru | Q15: https://www.electro-mpo.ru/catalog/materialy/t32_trubki_termousadochnye_kleevye_3_1_elektromont/t3267-trubka-ttk-9-3-termousazhivaemaya-s-kleem-ch/ | R15: https://www.electro-mpo.ru/catalog/materialy/t32_trubki_termousadochnye_kleevye_3_1_elektromont/t3267-trubka-ttk-9-3-termousazhivaemaya-s-kleem-ch/
A16: Припой ПОС61 1,0мм с флюсом | B16: припой/флюс | J16: Sn61Pb39 (ПОС61), флюс — канифоль (трубчатый, внутри) | K16: 183 | L16: 190 | M16: кг | N16: 12 | O16: 1.6 | P16: prodiel.ru | Q16: https://prodiel.ru/pripoj-pos-61-10-mm-s-flyusom-1-kg | R16: https://prodiel.ru/pripoj-pos-61-10-mm-s-flyusom-1-kg — темп. от/до здесь означает температуру плавления, не рабочий диапазон — решено агентом — проверить
A17: ТТК 8/2 черная | B17: ТТК | C17: КВТ Калуга | D17: ТТК(4:1) | E17: 8 | F17: 2 | G17: 4:1 | H17: черный | I17: да | J17: полиолефин нг | K17: -55 | L17: 125 | M17: м | N17: 7 | O17: 86.5 | P17: electro-mpo.ru | Q17: https://www.electro-mpo.ru/catalog/materialy/t33_trubki_termousadochnye_kleevye_ftoroplastovye_/t3336_trubka_ttk_8_2_termousazhivaemaya_s_kleem_ch/ | R17: https://www.electro-mpo.ru/catalog/materialy/t33_trubki_termousadochnye_kleevye_ftoroplastovye_/t3336_trubka_ttk_8_2_termousazhivaemaya_s_kleem_ch/
A18: ТУТ 1,5/0,75 черная | B18: ТУТ | C18: Rexant | D18: 20-1506 | E18: 1.5 | F18: 0.75 | G18: 2:1 | H18: черный | I18: нет | J18: полиолефин | K18: -55 | L18: 105 | M18: м | N18: 7 | O18: 10 | P18: electro-mpo.ru | Q18: https://www.electro-mpo.ru/catalog/materialy/t29_trubki_termousadochnye_elektromontazh_etelec_i/t29-trubka-20-1506-termousazhivaemaya-tut-ng-1-5-0/ | R18: https://www.electro-mpo.ru/catalog/materialy/t29_trubki_termousadochnye_elektromontazh_etelec_i/t29-trubka-20-1506-termousazhivaemaya-tut-ng-1-5-0/
A19: ТУТ(3:1)нг-LS 6/2 черная | B19: ТУТ | C19: КВТ Калуга | D19: ТУТ(3:1)нг-LS | E19: 6 | F19: 2 | G19: 3:1 | H19: черный | I19: нет | J19: полиолефин нг-LS (низкое дымо- и газовыделение) | K19: -55 | L19: 125 | M19: м | N19: 5 | O19: 35.4 | P19: electro-mpo.ru | Q19: https://www.electro-mpo.ru/catalog/materialy/t26_trubki_termousadochnye_chernye_rossiya/t3102-trubka-tut-3-1-ng-ls-6-2-83375-termousazhiva/ | R19: https://www.electro-mpo.ru/catalog/materialy/t26_trubki_termousadochnye_chernye_rossiya/t3102-trubka-tut-3-1-ng-ls-6-2-83375-termousazhiva/
A20: Оплётка GTRPA-10 | B20: оплётка | C20: ДКС | D20: GTRPA-10 | E20: 10 | F20: 16 | H20: черный | J20: полиамид (нейлон) | K20: -55 | L20: 130 | M20: м | N20: 7 | O20: 108.5 | P20: electro-mpo.ru | Q20: https://www.electro-mpo.ru/catalog/materialy/m50_pletenka_mednaya_luzhenaya_stalnaya_otsinkovan/m5025_oplyetka_gtrpa_10_kabelnaya_10_20mm_poliamid/ | R20: https://www.electro-mpo.ru/catalog/materialy/m50_pletenka_mednaya_luzhenaya_stalnaya_otsinkovan/m5025_oplyetka_gtrpa_10_kabelnaya_10_20mm_poliamid/
A21: Оплётка XS-10 | B21: оплётка | C21: Fortisflex | D21: XS-10 | E21: 10 | F21: 14 | H21: черный | J21: полиэстер, самозаворачивающаяся | K21: -55 | L21: 150 | M21: м | N21: 5 | O21: 168 | P21: electro-mpo.ru | Q21: https://www.electro-mpo.ru/catalog/materialy/m50_pletenka_mednaya_luzhenaya_stalnaya_otsinkovan/m5059-oplyetka-85380-xs-10-kabelnaya-10-14mm-samoz/ | R21: https://www.electro-mpo.ru/catalog/materialy/m50_pletenka_mednaya_luzhenaya_stalnaya_otsinkovan/m5059-oplyetka-85380-xs-10-kabelnaya-10-14mm-samoz/
A22: ТУТ(HF) 4/2 белая | B22: ТУТ | C22: КВТ | D22: ТУТ(HF) | E22: 4 | F22: 2 | G22: 2:1 | H22: белый | I22: нет | J22: ПЭВД, безгалогенная (HF) | M22: м | N22: 4 | O22: 13.5 | P22: electro-mpo.ru | Q22: https://www.electro-mpo.ru/catalog/materialy/t28_trubki_termousadochnye_tsvetnye_rossiya/t2873-trubka-tut-hf-4-2-termousazhivaemaya-bezgalo/ | R22: https://www.electro-mpo.ru/catalog/materialy/t28_trubki_termousadochnye_tsvetnye_rossiya/t2873-trubka-tut-hf-4-2-termousazhivaemaya-bezgalo/
A23: ТУТ 2/1 белая | B23: ТУТ | C23: Rexant | D23: 20-2001 | E23: 2 | F23: 1 | G23: 2:1 | H23: белый | I23: нет | J23: полиолефин | K23: -55 | L23: 105 | M23: м | N23: 4 | O23: 10.5 | P23: electro-mpo.ru | Q23: https://www.electro-mpo.ru/catalog/materialy/t29_trubki_termousadochnye_elektromontazh_etelec_i/t2920-trubka-20-2001-2-1mm-termousazhivaemaya-bela/ | R23: https://www.electro-mpo.ru/catalog/materialy/t29_trubki_termousadochnye_elektromontazh_etelec_i/t2920-trubka-20-2001-2-1mm-termousazhivaemaya-bela/
A24: ТУТ 8/4 белая | B24: ТУТ | C24: Rexant | D24: 20-8001 | E24: 8 | F24: 4 | G24: 2:1 | H24: белый | I24: нет | J24: полиолефин | K24: -55 | L24: 105 | M24: м | N24: 4 | O24: 18 | P24: electro-mpo.ru | Q24: https://www.electro-mpo.ru/catalog/materialy/t29_trubki_termousadochnye_elektromontazh_etelec_i/t2943-trubka-20-8001-8-4mm-termousazhivaemaya-bela/ | R24: https://www.electro-mpo.ru/catalog/materialy/t29_trubki_termousadochnye_elektromontazh_etelec_i/t2943-trubka-20-8001-8-4mm-termousazhivaemaya-bela/
A25: Оплётка XS-13 | B25: оплётка | C25: Fortisflex | D25: XS-13 | E25: 13 | F25: 17 | H25: черный | J25: полиэстер, самозаворачивающаяся | K25: -55 | L25: 150 | M25: м | N25: 4 | O25: 98.4 | P25: electro-mpo.ru | Q25: https://www.electro-mpo.ru/catalog/materialy/m50_pletenka_mednaya_luzhenaya_stalnaya_otsinkovan/m5060-oplyetka-85381-xs-13-kabelnaya-13-17mm-samoz/ | R25: https://www.electro-mpo.ru/catalog/materialy/m50_pletenka_mednaya_luzhenaya_stalnaya_otsinkovan/m5060-oplyetka-85381-xs-13-kabelnaya-13-17mm-samoz/
A26: ТТК 20/6 черная | B26: ТТК | C26: КВТ Калуга | D26: ТТК(3:1) | E26: 20 | F26: 6 | G26: 3:1 | H26: черный | I26: да | J26: полиолефин нг | K26: -55 | L26: 125 | M26: м | N26: 4 | O26: 0 | P26: electro-mpo.ru | Q26: https://www.electro-mpo.ru/catalog/materialy/t32_trubki_termousadochnye_kleevye_3_1_elektromont/t3269-trubka-ttk-18-6-termousazhivaemaya-s-kleem-ch/ | R26: https://www.electro-mpo.ru/catalog/materialy/t32_trubki_termousadochnye_kleevye_3_1_elektromont/t3269-trubka-ttk-18-6-termousazhivaemaya-s-kleem-ch/ — в адресе страницы указано 18/6, но содержимое карточки (арт. 85067) подтверждает 20/6 — решено агентом — проверить
A27: ТУТ 5,0/2,5 черная | B27: ТУТ | C27: Rexant | D27: 20-5006 | E27: 5 | F27: 2.5 | G27: 2:1 | H27: черный | I27: нет | J27: полиолефин | K27: -40 | L27: 125 | M27: м | N27: 4 | O27: 9.8 | P27: promelec.ru | Q27: https://www.promelec.ru/product/474892/ | R27: https://www.promelec.ru/product/474892/
A28: ТУТ(HF) 3/1,5 черная | B28: ТУТ | C28: КВТ | D28: ТУТ(HF) | E28: 3 | F28: 1.5 | G28: 2:1 | H28: черный | I28: нет | J28: полиолефин HF (безгалогенный) | K28: -55 | L28: 125 | M28: м | N28: 3 | O28: 7.2 | P28: kvt-pro.ru | Q28: https://kvt-pro.ru/mufty-nakonechniki/termousadka-termousadochnye-trubki-trubki-tut-kleevye-trubki/termousadochnye-trubki/tut-hf-1/85120-tut-hf-3-15-chern-termousadochnaia-trubka-s-koeffitsientom-usadki-2-1 | R28: https://kvt-pro.ru/mufty-nakonechniki/termousadka-termousadochnye-trubki-trubki-tut-kleevye-trubki/termousadochnye-trubki/tut-hf-1/85120-tut-hf-3-15-chern-termousadochnaia-trubka-s-koeffitsientom-usadki-2-1
A29: Гофра 6,8мм | B29: гофра | C29: ДКС | E29: 6.8 | H29: черный | J29: полипропилен | K29: -40 | L29: 105 | M29: м | N29: 8 | O29: 9.1 | P29: snabcable.ru | Q29: https://snabcable.ru/car/autogofra/gofra/ | R29: https://snabcable.ru/car/autogofra/gofra/ — размер взят из названия по сводке страницы категории (карточка конкретного диаметра на сайте не выделена отдельным URL) — решено агентом — проверить
A30: Изолента ПВХ 15х0,13х20м | B30: лента | C30: Fortisflex | H30: черный | J30: ПВХ | K30: -30 | L30: 80 | M30: шт | N30: 3 | O30: 145.1 | P30: kvt-pro.ru | Q30: https://kvt-pro.ru/izolenta/90809-izolenta-pvkh-15x0-13kh20-chern | R30: https://kvt-pro.ru/izolenta/90809-izolenta-pvkh-15x0-13kh20-chern
A31: Оплётка XS-19 | B31: оплётка | C31: Fortisflex | D31: XS-19 | E31: 19 | F31: 24 | H31: черный | J31: полиэстер, самозаворачивающаяся | K31: -55 | L31: 150 | M31: м | N31: 3 | O31: 294.5 | P31: electro-mpo.ru | Q31: https://www.electro-mpo.ru/catalog/materialy/m50_pletenka_mednaya_luzhenaya_stalnaya_otsinkovan/m5062-oplyetka-85383-xs-19-kabelnaya-19-24mm-samoz/ | R31: https://www.electro-mpo.ru/catalog/materialy/m50_pletenka_mednaya_luzhenaya_stalnaya_otsinkovan/m5062-oplyetka-85383-xs-19-kabelnaya-19-24mm-samoz/
A32: Лента нетканная 20мм | B32: лента | N32: 3 | O32: 16.4
A33: Оплётка XT-20/10 чёрная | B33: оплётка | C33: Fortisflex | D33: XT (85371) | E33: 20 | F33: 10 | H33: чёрный | J33: полиэстер/полиолефин | K33: -40 | L33: 150 | M33: м | N33: 3 | O33: 213.9 | P33: electro-mpo.ru | Q33: https://www.electro-mpo.ru/catalog/materialy/m50_pletenka_mednaya_luzhenaya_stalnaya_otsinkovan/m5052-oplyetka-85371-xt-20-10-kabelnaya-termousazh/ | R33: https://www.electro-mpo.ru/catalog/materialy/m50_pletenka_mednaya_luzhenaya_stalnaya_otsinkovan/m5052-oplyetka-85371-xt-20-10-kabelnaya-termousazh/ — в закупке указано «Оплетка кабельная XT 16/8мм», но ссылка и карточка ведут на XT-20/10 (арт. 85371); модели XT-16/8 у Fortisflex не найдено — решено агентом — проверить
A34: Стяжка 3x60 | B34: стяжка | M34: шт | N34: 3 | O34: 2.5 | P34: Склад | R34: нет ссылки и датащита, только наименование и поставщик «Склад»; материал/цвет не подтверждены — решено агентом — проверить
A35: Стяжка 5x200 | B35: стяжка | M35: шт | N35: 3 | O35: 2.5 | P35: Склад | R35: нет ссылки и датащита, только наименование и поставщик «Склад»; материал/цвет не подтверждены — решено агентом — проверить
A36: Стяжки 2,5x300мм | B36: стяжка | M36: шт | N36: 3 | O36: 2.5 | P36: Склад | R36: нет ссылки и датащита, только наименование и поставщик «Склад»; материал/цвет не подтверждены — решено агентом — проверить
A37: Тканевая лента T150PT | B37: лента | D37: T150PT | H37: чёрный | J37: полиэстер (тканевая термостойкая) | L37: 80 | M37: шт | N37: 3 | O37: 16.4 | P37: Меттатрон | R37: прямой ссылки на карточку нет (поставщик Меттатрон); по общему поиску — тканевая лента T150PT, чёрная, полиэстер, ширина ок. 19мм, до +80°C — решено агентом — проверить
A38: Токопроводящая экранирующая лента 0,1х50мм х20м | B38: лента | J38: полиэфирная ткань с никелевым покрытием, токопроводящий клей | M38: шт | N38: 3 | O38: 43 | P38: prodiel.ru | Q38: https://prodiel.ru/tokoprovodyaschiy-ekraniruyuschiy-skotch-01-mm-kh-50-mm-kh-20-m | R38: https://prodiel.ru/tokoprovodyaschiy-ekraniruyuschiy-skotch-01-mm-kh-50-mm-kh-20-m — размеры (0,1х50мм, рулон 20м) и состав подтверждены карточкой; температура и производитель на странице не указаны
A39: Тройник 9,8x9,8x9,8 | B39: тройник | C39: Schlemmer | D39: Тип B (9806138) | H39: чёрный | J39: полиамид 66 | K39: -40 | L39: 135 | M39: шт | N39: 3 | O39: 0 | P39: akompany.ru | Q39: https://akompany.ru/soedenitel_na_avtotrubu/t-troynik-tip-b-10-10-10-schlemmer-9806138 | R39: https://akompany.ru/soedenitel_na_avtotrubu/t-troynik-tip-b-10-10-10-schlemmer-9806138 — в закупке указано «Тройник 6,8x6,8x6,8», но карточка Schlemmer подтверждает внутренний диаметр всех сторон 9,8мм (типоразмер 10-10-10) — решено агентом — проверить
A40: Тройник 12,7x9,8x9,8 | B40: тройник | C40: Schlemmer | D40: Тип A (9806091) | H40: чёрный | J40: полиамид 66 | K40: -40 | L40: 135 | M40: шт | N40: 3 | O40: 0 | P40: akompany.ru | Q40: https://akompany.ru/soedenitel_na_avtotrubu/t-troynik-tip-a-13-10-10-schlemmer-9806091 | R40: https://akompany.ru/soedenitel_na_avtotrubu/t-troynik-tip-a-13-10-10-schlemmer-9806091 — в закупке указано «Тройник 6,8x6,8x9,8», но карточка Schlemmer подтверждает 12,7/9,8/9,8мм (типоразмер 13-10-10) — решено агентом — проверить
A41: Тройник 12,7x9,8x9,8 (DS) | B41: тройник | C41: DS | D41: аналог Schlemmer 9806091 | H41: чёрный | J41: полиамид | K41: -50 | L41: 120 | M41: шт | N41: 3 | O41: 0 | P41: akompany.ru | Q41: https://akompany.ru/soedenitel_na_avtotrubu/%D1%82-obraznui_nw13%2A10%2A10 | R41: https://akompany.ru/soedenitel_na_avtotrubu/%D1%82-obraznui_nw13%2A10%2A10 — в закупке указано «Тройник 9,8x6,8x6,8»; карточка подтверждает 12,7/9,8/9,8мм (типоразмер 13-10-10), аналог строки выше от другого производителя (DS вместо Schlemmer) — решено агентом — проверить
A42: Трубка гофрированная 4,6мм | B42: гофра | C42: DKC | D42: Тип B, NW4,5, разрезная негорючая | H42: чёрный | J42: полипропилен | M42: м | N42: 5 | O42: 23.1 | P42: akompany.ru | Q42: https://akompany.ru/avtotruba_dks/avtomobilnaya-gofra-dkc-iz-polipropilena-razreznaya-tip-v-negoryuchaya/4p904%D0%B2 | R42: https://akompany.ru/avtotruba_dks/avtomobilnaya-gofra-dkc-iz-polipropilena-razreznaya-tip-v-negoryuchaya/4p904%D0%B2 — наружный диаметр 7,1мм, внутренний 4,6мм; температурный режим на странице не указан
A43: Трубка гофрированная 9,8мм | B43: гофра | C43: DKC | D43: Тип B, NW10, разрезная негорючая | H43: чёрный | J43: полипропилен | M43: м | N43: 4 | O43: 0 | P43: akompany.ru | Q43: https://akompany.ru/avtotruba_dks/avtomobilnaya-gofra-dkc-iz-polipropilena-razreznaya-tip-v-negoryuchaya/4p910%D0%B2 | R43: https://akompany.ru/avtotruba_dks/avtomobilnaya-gofra-dkc-iz-polipropilena-razreznaya-tip-v-negoryuchaya/4p910%D0%B2 — наружный диаметр 12,7мм, внутренний 9,8мм; температурный режим на странице не указан
A44: ТТК 19/6,5мм, черная | B44: ТТК | E44: 19 | F44: 6.5 | H44: чёрный | M44: м | N44: 3 | O44: 65.6 | P44: Меттатрон | R44: нет ссылки/датащита (поставщик Меттатрон); типоразмер и цвет — из наименования закупки, остальные характеристики не подтверждены — решено агентом — проверить
A45: ТТК 24/8мм, черная | B45: ТТК | E45: 24 | F45: 8 | H45: чёрный | M45: м | N45: 3 | O45: 98.4 | P45: Меттатрон | R45: нет ссылки/датащита (поставщик Меттатрон); типоразмер и цвет — из наименования закупки, остальные характеристики не подтверждены — решено агентом — проверить
A46: Ферритовое кольцо 25x12,8мм | B46: феррит | M46: шт | N46: 3 | O46: 32.8 | P46: promelec.ru | Q46: https://www.promelec.ru/product/379216/ | R46: https://www.promelec.ru/product/379216/ — ссылка ведёт на сердечник TDK R12,7x7,90x6,35 N87, что не совпадает с размером 25x12,8мм из закупки; размер взят из наименования закупки, характеристики феррита не подтверждены — решено агентом — проверить
A47: Хомут 2,5x100мм чёрный | B47: хомут | C47: Yueqing Vancol (Китай) | H47: чёрный | J47: полиамид | M47: шт | N47: 3 | O47: 0.5 | P47: electro-mpo.ru | Q47: https://www.electro-mpo.ru/catalog/krepezh_metizy_khomuty/g73_khomuty_plastikovye_stalnye_osnovaniya_dlya_kh/g7332_khomut_2_5kh100mm_gibkiy_chyernyy_dlya_zhgut/ | R47: https://www.electro-mpo.ru/catalog/krepezh_metizy_khomuty/g73_khomuty_plastikovye_stalnye_osnovaniya_dlya_kh/g7332_khomut_2_5kh100mm_gibkiy_chyernyy_dlya_zhgut/ — подтверждено карточкой (2,5х100мм, полиамид, чёрный, для жгутовки)
A48: Плетёнка ПМЛ 3х6 У3 | B48: плетёнка | J48: медь луженая (ПОС-40, исполнение У3) | K48: -45 | L48: 40 | M48: м | N48: 2 | O48: 34 | P48: snabcable.ru | Q48: https://snabcable.ru/network/copper-tinning/pml/ | R48: https://snabcable.ru/network/copper-tinning/pml/ — «3х6» это диапазон диаметров экранируемого кабеля (мм), а не сечение самой плетёнки; «У3» — исполнение для умеренного климата (лужение ПОС-40); производитель на странице не указан — решено агентом — проверить
A49: ТТК Flex 6/2 черная | B49: ТТК | C49: КВТ Калуга | D49: ТТК "Flex" | E49: 6 | F49: 2 | G49: 3:1 | H49: чёрный | I49: да | J49: полиолефин | K49: -55 | L49: 125 | M49: м | N49: 2 | O49: 39.1 | P49: electro-mpo.ru | Q49: https://www.electro-mpo.ru/catalog/materialy/t32_trubki_termousadochnye_kleevye_3_1_elektromont/t3241-trubka-ttk-flex-6-2-termousazhivaemaya-s-kle/ | R49: https://www.electro-mpo.ru/catalog/materialy/t32_trubki_termousadochnye_kleevye_3_1_elektromont/t3241-trubka-ttk-flex-6-2-termousazhivaemaya-s-kle/ — в закупке указано «ТТК 6/3мм», но ссылка и карточка подтверждают ТТК "Flex" 6/2 (3:1); близко к уже имеющейся строке «ТТК 6/2 черная» (др. товарная линия и цена) — решено агентом добавить отдельной строкой — проверить, не дубль ли
A50: ТУТнг 4/2 красная | B50: ТУТ | C50: КВТ | D50: ТУТнг (65994) | E50: 4 | F50: 2 | G50: 2:1 | H50: красный | I50: нет | J50: полиолефин нг | K50: -40 | L50: 100 | M50: м | N50: 2 | O50: 11.6 | P50: kvt.su | Q50: https://kvt.su/prod/heat-shrink-tubes/general-purpose-tubes/tutng-color/sku_65994/ | R50: https://kvt.su/prod/heat-shrink-tubes/general-purpose-tubes/tutng-color/sku_65994/ — прямая ссылка закупки (категория без sku) не открылась, карточка найдена поиском по артикулу 65994; усадка при +90..+120°C — решено агентом — проверить
A51: Оплётка GTRPA-03 чёрная | B51: оплётка | C51: ДКС | D51: GTRPA-03 | E51: 3 | F51: 5 | H51: чёрный | J51: полиамид | K51: -55 | L51: 130 | M51: м | N51: 7 | O51: 54.5 | P51: electro-mpo.ru | Q51: https://www.electro-mpo.ru/catalog/materialy/m50_pletenka_mednaya_luzhenaya_stalnaya_otsinkovan/m5020_oplyetka_gtrpa_03_kabelnaya_3_6mm_poliamid_d/ | R51: https://www.electro-mpo.ru/catalog/materialy/m50_pletenka_mednaya_luzhenaya_stalnaya_otsinkovan/m5020_oplyetka_gtrpa_03_kabelnaya_3_6mm_poliamid_d/ — в закупке указано «Оплетка 15PET-3», но ссылка ведёт на карточку GTRPA-03 (полиамид, ДКС); товар 15PET-3 по этой ссылке не найден — решено агентом — проверить
A52: Тройник 6,8x6,8x6,8 | B52: тройник | C52: DS | D52: 9806083, типоразмер 7,5-7,5-7,5 | H52: чёрный | J52: полиамид | K52: -50 | L52: 120 | M52: шт | N52: 2 | O52: 27.5 | P52: akompany.ru | Q52: https://akompany.ru/soedenitel_na_avtotrubu/perehodnik-na-avtotrubu-t-757575 | R52: https://akompany.ru/soedenitel_na_avtotrubu/perehodnik-na-avtotrubu-t-757575 — в закупке указано «Тройник 4,6x4,6x4,6», карточка (DS 9806083) подтверждает внутренний диаметр всех сторон 6,8мм (типоразмер 7,5-7,5-7,5) — решено агентом — проверить
A53: ТУТ(HF) 10/5 белая | B53: ТУТ | C53: КВТ Калуга | D53: ТУТ(HF) (82915) | E53: 10 | F53: 5 | G53: 2:1 | H53: белый | I53: нет | J53: полиолефин, безгалогенная (HF) | M53: м | N53: 2 | O53: 23 | P53: electro-mpo.ru | Q53: https://www.electro-mpo.ru/catalog/materialy/t28_trubki_termousadochnye_tsvetnye_rossiya/t2880_trubka_tut10_5_termousazhivaemaya_dvnutr_10_/ | R53: https://www.electro-mpo.ru/catalog/materialy/t28_trubki_termousadochnye_tsvetnye_rossiya/t2880_trubka_tut10_5_termousazhivaemaya_dvnutr_10_/ — на странице указана только температура усадки (+80..+110°C), рабочий диапазон эксплуатации не указан — решено агентом — проверить
A54: ТУТ(HF) 6/3 белая | B54: ТУТ | C54: КВТ Калуга | D54: ТУТ(HF) (82913) | E54: 6 | F54: 3 | G54: 2:1 | H54: белый | I54: нет | J54: полиолефин, безгалогенная (HF) | M54: м | N54: 2 | O54: 16 | P54: ФРАКСИС | Q54: https://www.electro-mpo.ru/catalog/materialy/t28_trubki_termousadochnye_tsvetnye_rossiya/t2876_trubka_tut6_3_termousazhivaemaya_dvnutr_6_3m/ | R54: https://www.electro-mpo.ru/catalog/materialy/t28_trubki_termousadochnye_tsvetnye_rossiya/t2876_trubka_tut6_3_termousazhivaemaya_dvnutr_6_3m/ — на странице указана только температура усадки (+80..+110°C), рабочий диапазон эксплуатации не указан — решено агентом — проверить
A55: Заглушка полости разъёма Deutsch HD30 (0413-217-1605) | B55: уплотнитель | C55: TE Connectivity / Deutsch | D55: HD30, Size 16, Locking | H55: белый | J55: пластик (PBT) | M55: шт | N55: 2 | O55: 29.2 | P55: elitan.ru | Q55: https://www.te.com/en/product-0413-217-1605.html | R55: https://www.te.com/en/product-0413-217-1605.html — заглушка неиспользуемой полости разъёма (не сам провод), ссылка закупки (elitan.ru) вела на страницу поиска без карточки — решено агентом, идентифицировано по номеру детали
A56: Уплотнитель Superseal 1.5, красный (281934-3) | B56: уплотнитель | C56: TE Connectivity | D56: Superseal 1.5 | H56: красный | J56: силикон | M56: шт | N56: 2 | O56: 0 | P56: Заказчик | Q56: https://www.promelec.ru/product/321040/ | R56: https://www.promelec.ru/product/321040/ — уплотнитель провода для разъёма Superseal 1.5, под провод 2,6-3,3мм; поставщик «Заказчик» — давальческий материал
A57: Уплотнитель MATE-N-LOK, синий (794758-1) | B57: уплотнитель | C57: TE Connectivity / AMP | D57: Mini-Universal MATE-N-LOK | H57: синий | J57: силикон | K57: -40 | L57: 90 | M57: шт | N57: 2 | O57: 9 | P57: elitan.ru | Q57: https://www.tme.com/us/en-us/details/794758-1/raster-signal-connectors-4-14mm/te-connectivity/ | R57: https://www.tme.com/us/en-us/details/794758-1/raster-signal-connectors-4-14mm/te-connectivity/ — уплотнитель провода 1,02-2,11мм (26-18AWG); ссылка закупки (elitan.ru) вела на страницу поиска — решено агентом, идентифицировано по номеру детали
A58: Уплотнитель MCP, коричневый (963293-1) | B58: уплотнитель | C58: TE Connectivity / AMP | D58: MCP (Metri-Pack) | H58: коричневый | J58: силикон | K58: -40 | L58: 130 | M58: шт | N58: 2 | O58: 5.1 | P58: elitan.ru | Q58: https://www.te.com/en/product-963293-1.html | R58: https://www.te.com/en/product-963293-1.html — одиночное уплотнение провода для разъёмов MCP, диаметр полости 5,2мм; ссылка закупки (elitan.ru) вела на страницу поиска — решено агентом, идентифицировано по номеру детали
A59: Оплётка GTRPA-05 чёрная | B59: оплётка | C59: ДКС | D59: GTRPA-05 | E59: 5 | F59: 8 | H59: чёрный | J59: полиамид | K59: -55 | L59: 130 | M59: м | N59: 4 | O59: 69 | P59: electro-mpo.ru | Q59: https://www.electro-mpo.ru/catalog/materialy/m50_pletenka_mednaya_luzhenaya_stalnaya_otsinkovan/m5022_oplyetka_gtrpa_05_kabelnaya_5_10mm_poliamid_/ | R59: https://www.electro-mpo.ru/catalog/materialy/m50_pletenka_mednaya_luzhenaya_stalnaya_otsinkovan/m5022_oplyetka_gtrpa_05_kabelnaya_5_10mm_poliamid_/
A60: Оплётка GTRPA-06 чёрная | B60: оплётка | C60: ДКС | D60: GTRPA-06 | E60: 6 | F60: 10 | H60: чёрный | J60: полиамид | K60: -55 | L60: 130 | M60: м | N60: 2 | O60: 81.5 | P60: Двальческе | Q60: https://www.electro-mpo.ru/catalog/materialy/m50_pletenka_mednaya_luzhenaya_stalnaya_otsinkovan/m5023_oplyetka_gtrpa_06_kabelnaya_6_12mm_poliamid_/ | R60: https://www.electro-mpo.ru/catalog/materialy/m50_pletenka_mednaya_luzhenaya_stalnaya_otsinkovan/m5023_oplyetka_gtrpa_06_kabelnaya_6_12mm_poliamid_/
A61: Оплётка GTRPA-12 чёрная | B61: оплётка | C61: ДКС | D61: GTRPA-12 | E61: 12 | F61: 20 | H61: чёрный | J61: полиамид | K61: -55 | L61: 130 | M61: м | N61: 2 | O61: 128.5 | P61: electro-mpo.ru | Q61: https://www.electro-mpo.ru/catalog/materialy/m50_pletenka_mednaya_luzhenaya_stalnaya_otsinkovan/m5026_oplyetka_gtrpa_12_kabelnaya_12_24mm_poliamid/ | R61: https://www.electro-mpo.ru/catalog/materialy/m50_pletenka_mednaya_luzhenaya_stalnaya_otsinkovan/m5026_oplyetka_gtrpa_12_kabelnaya_12_24mm_poliamid/
A62: Гильза кабельная 08-0752 (0,5-1,5мм², L40мм) красная | B62: гильза | C62: Rexant | D62: ПК-т 1.5 (СИЗ) | H62: красный | I62: да | J62: полиэтилен (изоляция) с термоклеем, луженый медный проводник | M62: шт | N62: 2 | O62: 20.5 | P62: electro-mpo.ru | Q62: https://www.electro-mpo.ru/catalog/klemmniki_klemmy_szhimy/k29_kolpachki_izoliruyushchie_dlya_skrutki_provodo/k29-gilza-kabelnaya-08-0752-izol-pk-t-1-5-termousa/ | R62: https://www.electro-mpo.ru/catalog/klemmniki_klemmy_szhimy/k29_kolpachki_izoliruyushchie_dlya_skrutki_provodo/k29-gilza-kabelnaya-08-0752-izol-pk-t-1-5-termousa/ — в закупке указано «Rexant 08-752 термовтулка»; карточка подтверждает гильзу-коннектор 08-0752 ПК-т 1,5, термоусаживаемую, для пайки встык, 0,5–1,5мм², L40мм, красная, IP67; температурный режим на карточке не указан — решено агентом — проверить
A63: Гильза кабельная 2B20P (QUADRO, 1,5-2,5мм²) синяя | B63: гильза | C63: DKC | D63: QUADRO 2B20P | H63: синий | I63: нет | J63: медь луженая, изолированная | M63: шт | N63: 2 | O63: 13.9 | P63: svetelektro.net | Q63: https://svetelektro.net/nakonechniki-gilzy-mufty/2b20p-dkc.html | R63: https://svetelektro.net/nakonechniki-gilzy-mufty/2b20p-dkc.html — в закупке указано «Гильза EG B20/P», ссылка ведёт на карточку DKC 2B20P (QUADRO), гильза кабельная изолированная, луженая медь, L23мм, сечение 1,5–2,5мм², 27А/600В, продаётся упаковкой по 100шт — решено агентом — проверить
A64: Клей-герметик Kafuter K-704B чёрный 45г | B64: клей/герметик | C64: Kafuter | D64: K-704B | H64: чёрный | J64: силикон | M64: шт | N64: 2 | O64: 229.5 | P64: vnoutbuke.ru | Q64: https://vnoutbuke.ru/product/kley_germetik_silikonovyy_kafuter_k_704b_chernyy_45_gramm/ | R64: https://vnoutbuke.ru/product/kley_germetik_silikonovyy_kafuter_k_704b_chernyy_45_gramm/ — силиконовый клей-герметик, чёрный, тюбик 45г; температурный режим на карточке не указан — решено агентом — проверить
A65: Клей-герметик Силагерм 1044 белый | B65: клей/герметик | C65: Технология-Пласт | D65: 1044 | H65: белый | J65: силикон (однокомпонентный, электроизоляционный, вулканизация на воздухе) | K65: -60 | L65: 250 | M65: шт | N65: 2 | O65: 1270.5 | P65: silagerm.com | Q65: https://silagerm.com/products/27305792 | R65: https://silagerm.com/products/27305792 — картридж 310мл/500г, электроизоляционный силиконовый герметик, аналог ВГО-1
A66: Лак Plastik-71 акриловый изоляционный | B66: лак | C66: Solins | D66: Plastik-71 | H66: бесцветный | J66: акрил | K66: -70 | L66: 150 | M66: шт | N66: 2 | O66: 188.5 | P66: chipdip.ru | Q66: https://www.chipdip.ru/product/plastik-71-100ml-lak-akrilovyy-izolyatsionnyy-dlya-solins-9000072805 | R66: https://www.chipdip.ru/product/plastik-71-100ml-lak-akrilovyy-izolyatsionnyy-dlya-solins-9000072805 — флакон 100мл, акриловый изоляционный лак для печатных плат
A67: Оплётка XP-10 чёрная | B67: оплётка | C67: Fortisflex | D67: XP-10 (85362) | E67: 7 | F67: 17 | H67: чёрный | J67: полиэстер | K67: -80 | L67: 160 | M67: м | N67: 2 | O67: 44.5 | P67: kvt-pro.ru | Q67: https://kvt-pro.ru/mufty-nakonechniki/zashita-provodov/xp/85362-xp-10-opletka-kabelnaia-iz-poliestera | R67: https://kvt-pro.ru/mufty-nakonechniki/zashita-provodov/xp/85362-xp-10-opletka-kabelnaia-iz-poliestera
A68: Оплётка XP-6 чёрная | B68: оплётка | C68: Fortisflex | D68: XP-6 (85360) | E68: 3 | F68: 9 | H68: чёрный | J68: полиэстер | K68: -60 | L68: 160 | M68: м | N68: 3 | O68: 31.5 | P68: electro-mpo.ru | Q68: https://www.electro-mpo.ru/catalog/materialy/m50_pletenka_mednaya_luzhenaya_stalnaya_otsinkovan/m5041-oplyetka-85360-xp-6-kabelnaya-4-13mm-poliest/ | R68: https://www.electro-mpo.ru/catalog/materialy/m50_pletenka_mednaya_luzhenaya_stalnaya_otsinkovan/m5041-oplyetka-85360-xp-6-kabelnaya-4-13mm-poliest/ — в URL карточки указано 4-13мм, но таблица характеристик на странице даёт диапазон 3-9мм; использован диапазон из таблицы — решено агентом — проверить
A69: Оплётка GTRPA-04 чёрная | B69: оплётка | C69: ДКС | D69: GTRPA-04 | E69: 4 | F69: 6 | H69: чёрный | J69: полиамид | K69: -55 | L69: 130 | M69: м | N69: 3 | O69: 57 | P69: electro-mpo.ru | Q69: https://www.electro-mpo.ru/catalog/materialy/m50_pletenka_mednaya_luzhenaya_stalnaya_otsinkovan/m5021_oplyetka_gtrpa_04_kabelnaya_4_8mm_poliamid_d/ | R69: https://www.electro-mpo.ru/catalog/materialy/m50_pletenka_mednaya_luzhenaya_stalnaya_otsinkovan/m5021_oplyetka_gtrpa_04_kabelnaya_4_8mm_poliamid_d/
A70: Оплётка XP-3 чёрная | B70: оплётка | C70: Fortisflex | D70: XP-3 (85359) | E70: 1 | F70: 6 | H70: чёрный | J70: полиэстер | K70: -60 | L70: 160 | M70: м | N70: 5 | O70: 23 | P70: electro-mpo.ru | Q70: https://www.electro-mpo.ru/catalog/materialy/m50_pletenka_mednaya_luzhenaya_stalnaya_otsinkovan/m5040-oplyetka-85359-xp-3-kabelnaya-2-8mm-polieste/ | R70: https://www.electro-mpo.ru/catalog/materialy/m50_pletenka_mednaya_luzhenaya_stalnaya_otsinkovan/m5040-oplyetka-85359-xp-3-kabelnaya-2-8mm-polieste/ — в закупке фигурирует под двумя обозначениями «Оплетка 85359 XP-3» (стр.26) и «Оплетка Fortisflex 85359» (стр.28), обе ссылки ведут на одну карточку (m5040/85359) — объединено в одну строку, закупок суммировано (2+2=4) — решено агентом — проверить
A71: Оплётка XP-8 чёрная | B71: оплётка | C71: Fortisflex | D71: XP-8 (85361) | E71: 5 | F71: 12 | H71: чёрный | J71: полиэстер | K71: -60 | L71: 160 | M71: м | N71: 2 | O71: 42 | P71: electro-mpo.ru | Q71: https://www.electro-mpo.ru/catalog/materialy/m50_pletenka_mednaya_luzhenaya_stalnaya_otsinkovan/m5042-oplyetka-85361-xp-8-kabelnaya-5-16mm-poliest/ | R71: https://www.electro-mpo.ru/catalog/materialy/m50_pletenka_mednaya_luzhenaya_stalnaya_otsinkovan/m5042-oplyetka-85361-xp-8-kabelnaya-5-16mm-poliest/ — в URL карточки указано 5-16мм, таблица характеристик даёт 5-12мм; использован диапазон из таблицы — решено агентом — проверить
A72: Оплётка XP-12 чёрная | B72: оплётка | C72: Fortisflex | D72: XP-12 (85363) | E72: 8 | F72: 20 | H72: чёрный | J72: полиэстер | K72: -60 | L72: 160 | M72: м | N72: 2 | O72: 48 | P72: electro-mpo.ru | Q72: https://www.electro-mpo.ru/catalog/materialy/m50_pletenka_mednaya_luzhenaya_stalnaya_otsinkovan/m5044-oplyetka-85363-xp-12-kabelnaya-8-24mm-polies/ | R72: https://www.electro-mpo.ru/catalog/materialy/m50_pletenka_mednaya_luzhenaya_stalnaya_otsinkovan/m5044-oplyetka-85363-xp-12-kabelnaya-8-24mm-polies/ — в закупке указано 8-20мм, совпадает с таблицей характеристик карточки; URL карточки содержит 8-24мм — использован диапазон из таблицы
A73: Оплётка стекловолоконная CGS0.06BK чёрная | B73: оплётка | C73: First Cable | D73: CGS0.06BK | E73: 6 | F73: 9 | H73: чёрный | J73: стекловолокно в силиконовой оболочке | L73: 650 | M73: м | N73: 2 | O73: 71.3 | P73: 1-cable.ru | Q73: https://www.1-cable.ru/models/50118-0301.html | R73: https://www.1-cable.ru/models/50118-0301.html — толщина стенки 0,79мм, продаётся упаковками по 100м; нижняя граница температуры на карточке не указана
A74: Нитка ЛХ 200 (лавсан-хлопок) белая, 500м | B74: нитки | C74: Щит | D74: НЛХ ЛХ 200 | H74: белый | J74: лавсан + хлопок | M74: шт | N74: 2 | O74: 1.2 | P74: vseinstrumenti.ru | Q74: https://www.vseinstrumenti.ru/product/nitka-lavsan-hlopok-schit-nlh-lh-200-teks-v-bob-po-500-m-1088139/ | R74: https://www.vseinstrumenti.ru/product/nitka-lavsan-hlopok-schit-nlh-lh-200-teks-v-bob-po-500-m-1088139/ — 200 текс (≈0,7мм), бобина 500м
A75: Термоклей стержни Gigant G-8441 11x300мм прозрачные | B75: клей/герметик | C75: Gigant | D75: G-8441 | H75: прозрачный | J75: EVA, смола, воск | M75: шт | N75: 2 | O75: 0.8 | P75: vseinstrumenti.ru | Q75: https://www.vseinstrumenti.ru/product/sterzhni-kleevye-11h300-mm-34-sht-prozrachnye-gigant-g-8441-18507060/ | R75: https://www.vseinstrumenti.ru/product/sterzhni-kleevye-11h300-mm-34-sht-prozrachnye-gigant-g-8441-18507060/ — температура плавления 90°C, продаются упаковкой по 34шт
A76: Хомут 3,6x300мм чёрный | B76: хомут | C76: Vancol Electric (Китай) | H76: чёрный | J76: полиамид | K76: -35 | L76: 85 | M76: шт | N76: 2 | O76: 4.1 | P76: electro-mpo.ru | Q76: https://www.electro-mpo.ru/catalog/krepezh_metizy_khomuty/g73_khomuty_plastikovye_stalnye_osnovaniya_dlya_kh/g7340-khomut-3-6kh300mm-gibkiy-chyernyy-dlya-zhgut/ | R76: https://www.electro-mpo.ru/catalog/krepezh_metizy_khomuty/g73_khomuty_plastikovye_stalnye_osnovaniya_dlya_kh/g7340-khomut-3-6kh300mm-gibkiy-chyernyy-dlya-zhgut/ — в закупке указано общее «Стяжка», ссылка ведёт на типоразмер 3,6x300мм; классифицировано как «хомут» по аналогии с уже заведёнными позициями той же серии electro-mpo g73 (Vancol) — решено агентом — проверить
A77: Тройник 12,7x12,7x6,8 (Тип B) | B77: тройник | C77: Schlemmer | D77: Тип B (9806159) | H77: чёрный | J77: полиамид 66 | K77: -40 | L77: 135 | M77: шт | N77: 2 | O77: 14.3 | P77: akompany.ru | Q77: https://akompany.ru/soedenitel_na_avtotrubu/t-troynik-tip-b-13-13-75-schlemmer-9806159 | R77: https://akompany.ru/soedenitel_na_avtotrubu/t-troynik-tip-b-13-13-75-schlemmer-9806159 — в закупке указано «Тройник 8,5x4,6x4,6», карточка Schlemmer 9806159 подтверждает типоразмер 13-13-7,5 (внутр. диаметр 12,7/12,7/6,8мм) — решено агентом — проверить
A78: Тройник 12,7x12,7x12,7 (DS) | B78: тройник | C78: DS | D78: аналог Schlemmer 9806115, NW13x13x13 | H78: чёрный | J78: полиамид | K78: -50 | L78: 120 | M78: шт | N78: 2 | O78: 27.7 | P78: akompany.ru | Q78: https://akompany.ru/soedenitel_na_avtotrubu/%D1%82-obraznui_nw13%2A13%2A13 | R78: https://akompany.ru/soedenitel_na_avtotrubu/%D1%82-obraznui_nw13%2A13%2A13 — в закупке указано «Тройник 9,8x9,8x8,5», карточка DS (аналог Schlemmer 9806115, NW13x13x13) подтверждает внутр. диаметр всех сторон 12,7мм — решено агентом — проверить
A79: Трубка гофрированная неразрезная 4,6мм | B79: гофра | C79: DKC | D79: Тип B неразрезная | E79: 4.6 | F79: 7.1 | H79: чёрный | J79: полипропилен | K79: -40 | L79: 105 | M79: м | N79: 2 | O79: 13.1 | P79: akompany.ru | Q79: https://akompany.ru/avtotruba_dks/avtomobilnaya-gofra-dkc-iz-polipropilena-nerazreznaya-tip-v-negoryuchaya/40904в | R79: https://akompany.ru/avtotruba_dks/avtomobilnaya-gofra-dkc-iz-polipropilena-nerazreznaya-tip-v-negoryuchaya/40904в — неразрезной вариант (тип «40904в»), отличается от уже заведённой в базе разрезной «Трубка гофрированная 4,6мм» (тип «4p904в»)
A80: Медная лента Bonkeel Prof 10мм x20м | B80: лента | C80: Bonkeel | D80: Prof | J80: медная фольга, самоклеящаяся, токопроводящая | M80: шт | N80: 2 | O80: 61.5 | P80: vseinstrumenti.ru | Q80: https://www.vseinstrumenti.ru/product/mednaya-lenta-prof-20m-10mm-bonkeel-663685-22085714/ | R80: https://www.vseinstrumenti.ru/product/mednaya-lenta-prof-20m-10mm-bonkeel-663685-22085714/ — токопроводящая медная фольга-лента 10мм×20м на клеевой основе; на карточке заявлено назначение для антистатических полов, материал (медная фольга) применим и для экранирования жгутов — решено агентом — проверить область применения
A81: Лента тканевая 20мм | B81: лента | J81: тканевая, состав не подтверждён | M81: шт | N81: 2 | O81: 163.9 | R81: нет ссылки на карточку ни у «Лента тканевая 20мм», ни у «Тканевая лента T150PT» (обе от поставщика Меттатрон; модель T150PT на сайте mettatron.ru веб-поиском не найдена). Проверено: НЕ дубликат — цена последней закупки различается ~в 10 раз (T150PT — 16,4₽/шт против 163,9₽/шт у «20мм»), при отсутствии данных о длине рулона разница ширины (19 vs 20мм) её не объясняет — решено агентом — проверить: строки оставлены раздельными, слияние закупок НЕ выполнено.
A82: Скоба ПР1384.000 (латунь Л68, на несущей ленте, 1,5-2,5мм²) | B82: гильза | J82: латунь Л68 (ГОСТ 2208-2007), покрытие олово-висмут (/44) | M82: шт | N82: 2 | O82: 2 | P82: akompany.ru | Q82: https://akompany.ru/kabelnye-nakonechniki-klemmy-kontakty-razemy/pr-1384000-skoba-na-nesushchey-lente-sechenie-15-25mm2-ol | R82: https://akompany.ru/kabelnye-nakonechniki-klemmy-kontakty-razemy/pr-1384000-skoba-na-nesushchey-lente-sechenie-15-25mm2-ol — карточка подтверждает: обжимная скоба-соединитель ПР1384.000 из ленты латуни Л68 (ГОСТ 2208-2007) толщиной 0,4мм, покрытие олово-висмут (/44), для сечения проводов 1,5-2,5мм², применяется для опрессовки соединений в автомобильной электропроводке (стартер, генератор, вентилятор охлаждения), поставляется на несущей ленте (5000шт/катушка). Изготовитель на странице прямо не назван (только «российский производитель») — не указан. Группа «гильза» — решено агентом — проверить (см. примечание к группе).
A83: Лента 3M PT1100 (акриловая двусторонняя VHB, 6мм×33м) | B83: лента | C83: 3M | D83: PT1100 | H83: чёрный | I83: да | J83: акриловый пенный скотч (VHB), лайнер — красный полиэтилен | K83: -40 | L83: 90 | M83: шт | N83: 2 | O83: 45.1 | P83: lenta-3m.ru | Q83: https://lenta-3m.ru/shop/dvustoronnie-lenty-vhb/dvustoronnye-lenty-vhb/3m-pt1100-lenta-dvustoronnyaya-akrilovaya-chernaya-dlya-moldingov-i-spojlerov-tolshhina-11mm/3m-pt1100-lenta-dvustoronnyaya-akrilovaya-shirina-6mm-x-33m/ | R83: https://lenta-3m.ru/... (3m-pt1100-lenta-dvustoronnyaya-akrilovaya-shirina-6mm-x-33m) — карточка подтверждает: двусторонняя акриловая лента 3M PT1100, толщина 1,1мм, ширина в закупке 6мм, рулон 33м, чёрная, клеевой слой на обеих сторонах (акрил VR-2/VR-1), лайнер — красный ПЭ, назначение — крепление молдингов/спойлеров/накладок кузова, -40…+90°C, стойкость к влаге и растворителям.
A84: Трубка гофрированная 8,5мм | B84: гофра | C84: DKC | D84: Тип B, NW8.5, разрезная негорючая | E84: 8.5 | F84: 12 | H84: чёрный | J84: полипропилен | K84: -40 | L84: 105 | M84: м | N84: 2 | O84: 20.1 | P84: akompany.ru | Q84: https://akompany.ru/avtotruba_dks/avtomobilnaya-gofra-dkc-iz-polipropilena-razreznaya-tip-v-negoryuchaya/4p908%D0%B2 | R84: https://akompany.ru/avtotruba_dks/avtomobilnaya-gofra-dkc-iz-polipropilena-razreznaya-tip-v-negoryuchaya/4p908%D0%B2 — карточка подтверждает внутр./наружн. диаметр 8,5/12мм, тип В (негорючий); допускается кратковременно до +150°C (рабочий диапазон -40..+105 указан отдельно)
A85: Трубка ТВ-40 ПВХ 4мм (кембрик) чёрная | B85: кембрик | C85: Этиол / Спектр изопласт | D85: ТВ-40 | E85: 4 | H85: чёрный | I85: нет | J85: ПВХ пластикат (поливинилхлорид) | M85: м | N85: 5 | O85: 7.9 | P85: electro-mpo.ru | Q85: https://www.electro-mpo.ru/catalog/materialy/t40_trubka_elektroizolyatsionnaya_kembrik/t4072_trubka_tv_40_pvkh_4mm_kembrik_chyernaya_ross/ | R85: https://www.electro-mpo.ru/catalog/materialy/t40_trubka_elektroizolyatsionnaya_kembrik/t4072_trubka_tv_40_pvkh_4mm_kembrik_chyernaya_ross/ — в закупке встречается под тремя названиями: «Трубка ПВХ 4мм» (2 закупки), «Трубка ТВ-40 4мм» (2 закупки), «ТВ-40 ПВХ 4мм - 12мм» (1 закупка) — все три ссылки ведут на одну карточку (арт. Т4072); объединено в одну строку, закупок суммировано (2+2+1=5), цена — по самой поздней покупке (2026-05) — решено агентом — проверить; температурный диапазон на карточке не указан; новая группа «кембрик» — не термоусаживаемая ПВХ-трубка, в существующем словаре БД.МАТ такой группы не было
A86: Трубка ТВ-40 ПВХ 6мм (кембрик) чёрная | B86: кембрик | C86: Этиол / Спектр изопласт | D86: ТВ-40 | E86: 6 | H86: чёрный | I86: нет | J86: ПВХ пластикат (поливинилхлорид) | M86: м | N86: 4 | O86: 12.1 | P86: electro-mpo.ru | Q86: https://www.electro-mpo.ru/catalog/materialy/t40_trubka_elektroizolyatsionnaya_kembrik/t4074_trubka_tv_40_pvkh_6mm_kembrik_chyernaya_ross/ | R86: https://www.electro-mpo.ru/catalog/materialy/t40_trubka_elektroizolyatsionnaya_kembrik/t4074_trubka_tv_40_pvkh_6mm_kembrik_chyernaya_ross/ — в закупке встречается под двумя названиями «Трубка ПВХ 6мм» (2) и «Трубка ТВ-40 6мм» (2) — одна и та же карточка (арт. Т4074); объединено, закупок суммировано (2+2=4), цена по самой поздней покупке (2026-05) — решено агентом — проверить; температурный диапазон на карточке не указан
A87: Оплётка стекловолоконная FSHT(C) 2,0мм белая | B87: оплётка | C87: Raychman | D87: FSHT(C) | E87: 2 | H87: белый | I87: нет | J87: стекловолокно E-glass без полимерного покрытия | K87: -50 | L87: 450 | M87: м | N87: 2 | O87: 21.3 | P87: chipdip.ru | Q87: https://www.chipdip.ru/product/fsht-c-2-0-mm-belaya-vysokotemperaturnaya-raychman-8067312329?from=suggest_product | R87: https://www.chipdip.ru/product/fsht-c-2-0-mm-belaya-vysokotemperaturnaya-raychman-8067312329 — в закупке указано «Трубка Радиант ТСП-200 2мм», ссылка ведёт на карточку Raychman FSHT(C) — плетёный стеклошнур-чулок, НЕ термоусаживаемый, до +500°C кратковременно (длительно -50..+450) — ссылка приоритетнее наименования, решено агентом — проверить
A88: Оплётка стекловолоконная FSHT(C) 3,0мм белая | B88: оплётка | C88: Raychman | D88: FSHT(C) | E88: 3 | H88: белый | I88: нет | J88: стекловолокно E-glass без полимерного покрытия | K88: -50 | L88: 450 | M88: м | N88: 2 | O88: 27 | P88: chipdip.ru | Q88: https://www.chipdip.ru/product/fsht-c-3-0-mm-belaya-vysokotemperaturnaya-raychman-8067312330 | R88: https://www.chipdip.ru/product/fsht-c-3-0-mm-belaya-vysokotemperaturnaya-raychman-8067312330 — в закупке указано «Трубка Радиант ТСП-200 3мм», ссылка ведёт на карточку Raychman FSHT(C), тот же тип, что и Ø2,0мм выше — решено агентом — проверить
A89: ТТК Flex 15/5 чёрная | B89: ТТК | C89: КВТ | D89: ТТК "Flex" (85208) | E89: 15 | F89: 5 | G89: 3:1 | H89: чёрный | I89: да | J89: полиолефин | K89: -55 | L89: 125 | M89: м | N89: 2 | O89: 114.8 | P89: electro-mpo.ru | Q89: https://www.electro-mpo.ru/catalog/materialy/t32_trubki_termousadochnye_kleevye_3_1_elektromont/t3244-trubka-ttk-flex-15-5-termousazhivaemaya-s-kl/ | R89: https://www.electro-mpo.ru/catalog/materialy/t32_trubki_termousadochnye_kleevye_3_1_elektromont/t3244-trubka-ttk-flex-15-5-termousazhivaemaya-s-kl/ — в закупке указано «ТТК 15,4/4мм», карточка (арт. 85208) подтверждает ТТК "Flex" 15/5 (3:1) — ссылка приоритетнее наименования — решено агентом — проверить
A90: ТУТнг 2,5/1,25 черная | B90: ТУТ | C90: Rexant | D90: ТУТнг | E90: 2.5 | F90: 1.25 | G90: 2:1 | H90: чёрный | I90: нет | J90: полиолефин | K90: -40 | L90: 125 | M90: м | N90: 2 | O90: 8.2 | P90: promelec.ru | Q90: https://www.promelec.ru/product/474830/?ysclid=mnher3jt2w902288511 | R90: https://www.promelec.ru/product/474830/ — рабочий диапазон -40..+125°C, температура начала усадки 110°C (не рабочая) — решено агентом — проверить
A91: ТУТ(3:1)нг-LS 20/6 черная | B91: ТУТ | C91: КВТ Калуга | D91: ТУТ(3:1)нг-LS (85089) | E91: 20 | F91: 6 | G91: 3:1 | H91: чёрный | I91: нет | J91: полиолефин нг-LS (низкое дымо- и газовыделение) | M91: м | N91: 2 | O91: 105 | P91: electro-mpo.ru | Q91: https://www.electro-mpo.ru/catalog/materialy/t26_trubki_termousadochnye_chernye_rossiya/t3106-trubka-tut-3-1-ng-ls-20-6-85089-termousazhiva/ | R91: https://www.electro-mpo.ru/catalog/materialy/t26_trubki_termousadochnye_chernye_rossiya/t3106-trubka-tut-3-1-ng-ls-20-6-85089-termousazhiva/ — температурный диапазон на карточке этого артикула не приведён; у сестринской позиции «ТУТ(3:1)нг-LS 6/2» в базе указано -55/+125, но для 85089 это не подтверждено — оставлено пустым, решено агентом — проверить
A92: ТУТ 3,0/1,5 белая | B92: ТУТ | C92: Rexant | D92: 20-3001 | E92: 3 | F92: 1.5 | G92: 2:1 | H92: белый | J92: полиолефин | K92: -55 | L92: 105 | M92: м | N92: 2 | O92: 12 | P92: electro-mpo.ru | Q92: https://www.electro-mpo.ru/catalog/materialy/t29_trubki_termousadochnye_elektromontazh_etelec_i/t2925-trubka-20-3001-3-1-5mm-termousazhivaemaya-be/ | R92: https://www.electro-mpo.ru/catalog/materialy/t29_trubki_termousadochnye_elektromontazh_etelec_i/t2925-trubka-20-3001-3-1-5mm-termousazhivaemaya-be/ — клеевой слой на карточке не указан, оставлено пустым
A93: ТУТ(HF) 4/2 прозрачная | B93: ТУТ | C93: КВТ | D93: ТУТ-HF (83266) | E93: 4 | F93: 2 | G93: 2:1 | H93: прозрачный | I93: нет | J93: полиолефин HF (безгалогенный) | K93: -55 | L93: 125 | M93: м | N93: 2 | O93: 10.7 | P93: kvt-pro.ru | Q93: https://kvt-pro.ru/mufty-nakonechniki/termousadka-termousadochnye-trubki-trubki-tut-kleevye-trubki/termousadochnye-trubki/tut-hf/83266-trubka-tut-hf-4-2-prozrachnaia-kvt-2-1 | R93: https://kvt-pro.ru/mufty-nakonechniki/termousadka-termousadochnye-trubki-trubki-tut-kleevye-trubki/termousadochnye-trubki/tut-hf/83266-trubka-tut-hf-4-2-prozrachnaia-kvt-2-1
A94: Ферритовое кольцо разъёмное Cablexpert 7мм | B94: феррит | C94: Cablexpert | D94: FR-C-7 | E94: 7 | H94: чёрный | J94: ферритовый сердечник в пластиковом корпусе (клипса) | M94: шт | N94: 2 | O94: 16.7 | P94: vseinstrumenti.ru | Q94: https://www.vseinstrumenti.ru/product/ferritovoe-koltso-cablexpert-plastikovaya-zaschelka-vnutrennij-diametr-7mm-fr-c-7-2159990/?ysclid=mholu8dysi142957164 | R94: https://www.vseinstrumenti.ru/product/ferritovoe-koltso-cablexpert-plastikovaya-zaschelka-vnutrennij-diametr-7mm-fr-c-7-2159990/ — разъёмный (защёлкивающийся) тип на кабель Ø7мм, в отличие от уже заведённого сплошного кольца 25x12,8мм — другой форм-фактор, решено агентом — проверить
A95: Хомут 3x300мм чёрный | B95: хомут | C95: Ural PAK | D95: АЭ-91203300-100 | H95: чёрный | J95: нейлон | K95: -40 | L95: 85 | M95: шт | N95: 2 | O95: 2.5 | P95: vseinstrumenti.ru | Q95: https://www.vseinstrumenti.ru/product/homut-nejlonovyj-ural-pak-3h300-mm-chernyj-100-sht-ae-91203300-100-13354561/?ysclid=mhvvszts94158259621 | R95: https://www.vseinstrumenti.ru/product/homut-nejlonovyj-ural-pak-3h300-mm-chernyj-100-sht-ae-91203300-100-13354561/ — ширина 3мм (не 3,6мм как у уже заведённого «Хомут 3,6x300мм», другой производитель Vancol) — отдельная позиция
A96: Припой Sn60Pb39Cu1 1,0мм с флюсом RA05 (Felder) | B96: припой/флюс | C96: Felder GmbH Loettechnik | D96: 1864102005 | J96: Sn60Pb39Cu1, флюс RA05 малогалогенный 2,5% | M96: кг | N96: 1 | O96: 1.6 | P96: promelec.ru | Q96: https://www.promelec.ru/product/130837/ | R96: https://www.promelec.ru/product/130837/ — отличается от уже заведённого «Припой ПОС61»: другой сплав (Sn60Pb39Cu1 vs Sn61Pb39), другой флюс (RA05 2,5% vs канифоль) и производитель (Felder); температура плавления на карточке не указана — не указана (не придумана), решено агентом — проверить, не дубль ли
A97: ТТК 16/4 черная | B97: ТТК | C97: КВТ Калуга | D97: ТТК(4:1) (59676) | E97: 16 | F97: 4 | G97: 4:1 | H97: чёрный | I97: да | J97: полиолефин | K97: -55 | L97: 125 | M97: м | N97: 1 | O97: 176 | P97: electro-mpo.ru | Q97: https://www.electro-mpo.ru/catalog/materialy/t33_trubki_termousadochnye_kleevye_ftoroplastovye_/t3338_trubka_ttk_16_4_termousazhivaemaya_s_kleem_ch/ | R97: https://www.electro-mpo.ru/catalog/materialy/t33_trubki_termousadochnye_kleevye_ftoroplastovye_/t3338_trubka_ttk_16_4_termousazhivaemaya_s_kleem_ch/
A98: ТУТ HTS-16 16/8 черная | B98: ТУТ | C98: Yueqing Vancol (Китай) / МПО Электромонтаж | D98: HTS-16 | E98: 16 | F98: 8 | G98: 2:1 | H98: чёрный | I98: нет | J98: полиолефин | M98: м | N98: 1 | O98: 174.2 | P98: electro-mpo.ru | Q98: https://www.electro-mpo.ru/catalog/materialy/t29_trubki_termousadochnye_elektromontazh_etelec_i/t2909-trubka-hts-16-16-8mm-termousazhivaemaya-chye/ | R98: https://www.electro-mpo.ru/catalog/materialy/t29_trubki_termousadochnye_elektromontazh_etelec_i/t2909-trubka-hts-16-16-8mm-termousazhivaemaya-chye/ — в закупке указано «ТТК 16/8мм», но карточка (серия HTS) — обычная безклеевая термоусадка, не ТТК; переклассифицировано в группу ТУТ — ссылка приоритетнее наименования, решено агентом — проверить; рабочий температурный диапазон на карточке не указан (дана только температура усадки от +125°C)
A99: ТУТ HTS-14 14/7 черная | B99: ТУТ | C99: Yueqing Vancol (Китай) / МПО Электромонтаж | D99: HTS-14 | E99: 14 | F99: 7 | G99: 2:1 | H99: чёрный | I99: нет | J99: полиолефин | M99: м | N99: 1 | O99: 0 | P99: electro-mpo.ru | Q99: https://www.electro-mpo.ru/catalog/materialy/t29_trubki_termousadochnye_elektromontazh_etelec_i/t2907-trubka-hts-14-14-7mm-termousazhivaemaya-chye/?ysclid=mfl5lfalqk341220303 | R99: https://www.electro-mpo.ru/catalog/materialy/t29_trubki_termousadochnye_elektromontazh_etelec_i/t2907-trubka-hts-14-14-7mm-termousazhivaemaya-chye/ — рабочий температурный диапазон на карточке не указан (дана только температура усадки от +125°C); цена последней закупки в сводке указана как 0,0
A100: ТУТнг-LS 8/4 черная | B100: ТУТ | C100: КВТ Калуга | D100: ТУТнг-LS (60089) | E100: 8 | F100: 4 | G100: 2:1 | H100: чёрный | I100: нет | J100: полиолефин нг, низкое дымо- и газовыделение | K100: -55 | L100: 125 | M100: м | N100: 1 | O100: 20.1 | P100: electro-mpo.ru | Q100: https://www.electro-mpo.ru/catalog/materialy/t26_trubki_termousadochnye_chernye_rossiya/t2672_trubka_tut8_4_termousazhivaemaya_dvnutr_8_4m/ | R100: https://www.electro-mpo.ru/catalog/materialy/t26_trubki_termousadochnye_chernye_rossiya/t2672_trubka_tut8_4_termousazhivaemaya_dvnutr_8_4m/ — в закупке указано «ТУТ 8/4мм» без уточнения цвета/марки, карточка подтверждает чёрную ТУТнг-LS-8/4 (арт. 60089)
...

Sheet БД.ПРОВ
A1: Марка | B1: Тип провода | C1: Стандарт / производитель | D1: Сечение, мм2 | E1: AWG | F1: Жила: проволок × диаметр, мм | G1: Число жил | H1: Цвета | I1: Наружный диаметр, мм | J1: Изоляция | K1: Экран | L1: Волновое сопротивление, Ом | M1: Темп. от, °C | N1: Темп. до, °C | O1: Напряжение, В | P1: Ток, А | Q1: Масса, г/м | R1: Закупок | S1: Цена посл., ₽/м без НДС | T1: Поставщик | U1: Ссылка на datasheet | V1: Источник данных
A2: RG316 | B2: коаксиальный | C2: MIL-DTL-17 RG-316/U; реселлер baltic-signal.ru | F2: 7×0,17 (посеребр. медь) | G2: 1 | I2: 2.45 | J2: ПТФЭ (диэлектрик) / ФЭП (оболочка) | K2: посеребрённая медная оплетка 80×0,1 мм | L2: 50 | M2: -60 | N2: 200 | O2: 2000 | Q2: 20 | R2: 43 | S2: 81.1 | T2: Склад, АО "ВНИИР-Прогресс", Давальческое | U2: https://baltic-signal.ru/catalog/accessories/kabel/kabel-rg-316-50-om/ | V2: baltic-signal.ru (осн.); напряжение 2000В — из даташита Huber+Suhner RG316/U (у baltic-signal не указано) — решено агентом — проверить
A3: UL1061 28AWG | B3: монтажный | C3: UL AWM Style 1061, SR-PVC, 300V/80°C | D3: 0.08 | E3: 28 | F3: 7×0,127 (луж. медь, 7/36AWG) | G3: 1 | H3: чёрный, красный, белый, синий, жёлтый, зелёный, оранжевый, коричневый, серый, фиолетовый | I3: 0.89 | J3: полутвёрдый ПВХ (SR-PVC) | M3: -10 | N3: 80 | O3: 300 | Q3: 1.49 | R3: 157 | S3: 5.4 | T3: Склад, Фраксис, Слад, Слкад, Скад, Полина, Давальческое | U3: https://www.remingtonindustries.com/content/UL1061%20Hook%20Up%20Wire%20Data%20Sheet.pdf | V3: Remington/Farnell/rdswire.com UL1061 datasheet; сечение 0,08мм2 и диаметр пряди 0,127мм — по стандартной таблице AWG (7/36), не прямое значение из даташита — решено агентом — проверить. Объединены 8 цветовых позиций (черный,красный,белый,синий,желтый,зеленый,оранжевый,коричневый)
A4: RG-58 A/U | B4: коаксиальный | C4: ГОСТ 31565-2012; VEGATEL RG-58 A/U Cu | F4: 1×0,90 (медь, сплошная — заявлено продавцом) | G4: 1 | H4: чёрный | I4: 4.95 | J4: сплошной полиэтилен (SPE) | K4: алюминиевая фольга (2-сторонняя, 96%) + оплетка | L4: 50 | M4: -60 | N4: 80 | Q4: 27 | R4: 28 | S4: 36.9 | U4: https://www.vegatel.ru/kabel/vegatel-rg-58/kabel-vegatel-rg-58-a-u-cu-gost-re-chernii-buhta-100m | V4: vegatel.ru; жила заявлена продавцом как сплошная медь — для RG-58 A/U обычно многопроволочная (7 прядей) — решено агентом — проверить. Монтажный диапазон -25..+50°C (в таблице — рабочий -60..+80°C)
A5: RG1.37 | B5: коаксиальный | C5: нестандартное обозначение реселлера (тонкий 50-омный коаксиал, аналог RF1.37) | F5: 7×0,105 (посеребр. медь) | G5: 1 | H5: чёрный | I5: 1.37 | J5: ФЭП (FEP) | K5: луженая медная оплетка | L5: 50 | M5: -60 | N5: 200 | O5: 1000 | Q5: 4.6 | R5: 21 | S5: 29.5 | T5: Склад, Фраксис, CINTY, Давальческое, MEI DUO YUAN KEJI | U5: https://gsm-repiteri.ru/prodazha/cable/cable-koaksialnyy-rf1-37 | V5: gsm-repiteri.ru; независимого даташита производителя не найдено — решено агентом — проверить
A6: НВ-4 0,20 | B6: монтажный | C6: ГОСТ 17515-72 | D6: 0.2 | G6: 1 | H6: чёрный, красный, белый, зелёный, жёлтый, синий, коричневый, оранжевый, фиолетовый, голубой, серый | I6: 1.5 | J6: ПВХ-пластикат | M6: -50 | N6: 105 | O6: 600 | R6: 133 | S6: 6.7 | U6: https://snabcable.ru/mounting/nv-nve/nv/ | V6: snabcable.ru; страндинг жилы страницей не указан. У НВ-4 есть варианты на 600В (OD 1,5мм) и 1000В (OD 1,7мм) — взят вариант 600В как базовый — решено агентом — проверить. Объединены 9 цветовых позиций
A7: UL1061 30AWG | B7: монтажный | C7: UL AWM Style 1061, SR-PVC, 300V/80°C | D7: 0.05 | E7: 30 | F7: 7×0,101 (луж. медь, 7/38AWG) | G7: 1 | H7: чёрный, белый, красный, синий, жёлтый, зелёный | I7: 0.81 | J7: полутвёрдый ПВХ (SR-PVC) | M7: -10 | N7: 80 | O7: 300 | Q7: 0.11 | R7: 65 | S7: 4.9 | T7: Китай, Склад, Слкад, Давальческое | U7: https://www.remingtonindustries.com/hook-up-wire/electronics/ul1061-300-volt/ | V7: rdswire.com UL1061 style page; диаметр пряди 0,101мм — по стандартной таблице AWG (7/38), не прямое значение из даташита — решено агентом — проверить. Объединены 5 цветовых позиций
A8: RG178 | B8: коаксиальный | C8: MIL-DTL-17 RG-178/U | F8: 7×0,10 (посеребр. медь) | G8: 1 | H8: чёрный | I8: 1.78 | J8: ПТФЭ | K8: посеребрённая медная оплетка 48×0,1 мм | L8: 50 | M8: -60 | N8: 200 | O8: 1000 | Q8: 7 | R8: 16 | S8: 73.8 | T8: Фраксис, Склад, ООО"ЗЭП "ФРАКСИС", Давальческое, Полина | U8: https://gsm-repiteri.ru/prodazha/cable/cable-rg-178-50-om | V8: gsm-repiteri.ru, согласуется с типовой спецификацией RG-178/U
A9: НВ-4 0,50 | B9: монтажный | C9: ГОСТ 17515-72 | D9: 0.5 | G9: 1 | H9: чёрный, жёлтый, красный, белый | I9: 1.8 | J9: ПВХ-пластикат | M9: -50 | N9: 105 | O9: 600 | R9: 36 | S9: 11.9 | U9: https://snabcable.ru/mounting/nv-nve/nv/ | V9: snabcable.ru; вариант 600В (OD 1,8мм) взят как базовый, есть также вариант 1000В (OD 2,0мм) — решено агентом — проверить
A10: RG174 | B10: коаксиальный | C10: MIL-DTL-17 RG-174/U | F10: 7×0,16 (медь) | G10: 1 | H10: чёрный | I10: 2.8 | J10: сшитый полиэтилен (XLPE, по данным продавца) | K10: луженая омедненная алюминиевая оплетка 64×0,1 мм | L10: 50 | M10: -60 | N10: 70 | O10: 1000 | Q10: 15 | R10: 17 | S10: 20.5 | T10: ИП Астафьева Юлия Андреевна, Давальческое, Заказчик | U10: https://gsm-repiteri.ru/prodazha/cable/kabel-rg-174-50-om | V10: gsm-repiteri.ru; в сводке закупок цена указана как 0,0 — похоже на ошибку данных, оставлено пустым — решено агентом — проверить. Изоляция/экран у продавца отличаются от типового Belden RG-174 (PE и луженая медь) — вероятно удешевлённый вариант
A11: RG402 | B11: коаксиальный (полужёсткий) | C11: MIL-DTL-17 RG-402/U (CF-141-50-FEP) | F11: 1×0,91 (посеребр. медь, сплошная) | G11: 1 | I11: 4.1 | J11: ПТФЭ (сплошной) | K11: медная оплетка/трубка (продавец пишет "оплетка", у полужёсткого RG402 обычно сплошная медная трубка) — решено агентом — проверить | L11: 50 | M11: -60 | N11: 155 | Q11: 44 | R11: 14 | S11: 245.9 | T11: Давальческое, Склад | U11: https://baltic-signal.ru/catalog/accessories/kabel/kabel-rg-402/ | V11: baltic-signal.ru
A12: НВ-4 0,12 | B12: монтажный | C12: ГОСТ 17515-72 | D12: 0.12 | G12: 1 | H12: красный, чёрный, белый, зелёный, жёлтый, синий | I12: 1.3 | J12: ПВХ-пластикат | M12: -50 | N12: 105 | O12: 600 | Q12: 2.35 | R12: 53 | S12: 6.6 | T12: Давальческое | U12: https://snabcable.ru/mounting/nv-nve/nv/ | V12: snabcable.ru (пример веса 2,35 кг/км дан на странице именно для сечения 0,12мм2). Объединены 6 цветовых позиций
A13: RG405 | B13: коаксиальный (полужёсткий) | C13: MIL-DTL-17 RG-405/U (CF-086-50-FEP) | F13: 1×0,51 (посеребр. медь, сплошная) | G13: 1 | I13: 2.69 | J13: ПТФЭ | K13: медная оплетка/трубка (продавец пишет "оплетка", у полужёсткого RG405 обычно сплошная медная трубка) — решено агентом — проверить | L13: 50 | M13: -60 | N13: 155 | Q13: 20 | R13: 14 | S13: 147.5 | T13: Давальческое | U13: https://baltic-signal.ru/catalog/accessories/kabel/kabel-rg-405-cf-086-50-fep/ | V13: baltic-signal.ru
A14: Силиконовый провод 28AWG | B14: силиконовый | C14: генерик (китайское производство), prodiel.ru | D14: 0.08 | E14: 28 | F14: 16×0,08 (луж. медь) | G14: 1 | H14: чёрный, красный, жёлтый, зелёный, белый, синий, фиолетовый | I14: 1.2 | J14: силиконовая резина (метилвинилполисилоксан + SiO2) | M14: -60 | N14: 200 | O14: 600 | P14: 0.8 | R14: 77 | S14: 14.6 | T14: Китай, Продиэлком | U14: https://prodiel.ru/provod/provod-gibkiy-v-silikone/silicon-28-awg/ | V14: prodiel.ru (4 карточки товара, идентичные характеристики); объединены позиции "Силикон" и "Силиконовый" 28AWG (один и тот же товар, разное написание у покупателей) — 7 цветовых/написательных позиций. Цена последней закупки неоднозначна (10,8-11,5 в одном месяце у разных позиций) — решено агентом — проверить
A15: 5D-FB | B15: коаксиальный | C15: JIS 5D-FB | F15: 1×1,80 (медненный алюминий, сплошная) | G15: 1 | H15: чёрный | I15: 7.54 | J15: вспененный полиэтилен | K15: алюминиевая фольга + алюминиево-магниевая оплетка 120×0,15 мм | L15: 50 | M15: -60 | N15: 75 | Q15: 60 | R15: 13 | S15: 61.5 | T15: Давальческое | U15: https://gsm-repiteri.ru/prodazha/cable/kabel-5d-fb-pvc-chernyy | V15: gsm-repiteri.ru; жила из омедненного алюминия и оплетка Al-Mg — удешевлённый вариант относительно типовой JIS-спецификации (медь/луженая медь) — решено агентом — проверить
A16: ПВАМ 0,50 | B16: силовой | C16: ТУ 16.К19-12-2003 | D16: 0.5 | G16: 1 | H16: красный, чёрный, жёлтый, синий, белый, зелёный, голубой, розовый, фиолетовый, серый | I16: 1.6 | J16: ПВХ-пластикат маслобензостойкий | M16: -40 | N16: 105 | O16: 48 (ном.) / 1000 (испыт.) | Q16: 6 | R16: 47 | S16: 7.9 | U16: https://snabcable.ru/car/pvam-pvame-pvamde/pvam/ | V16: snabcable.ru; жила — медь многопроволочная 5-го класса гибкости, страндинг страницей не указан
A17: ПВАМ 0,35 | B17: силовой | C17: ТУ 16.К19-12-2003 | D17: 0.35 | G17: 1 | H17: красный, чёрный, зелёный, белый, жёлтый, оранжевый | I17: 1.4 | J17: ПВХ-пластикат маслобензостойкий | M17: -40 | N17: 105 | O17: 48 (ном.) / 1000 (испыт.) | Q17: 5 | R17: 30 | S17: 10.8 | T17: Заказчик | U17: https://snabcable.ru/car/pvam-pvame-pvamde/pvam/ | V17: snabcable.ru
A18: ПВВС 4×0,35 | B18: многожильный кабель | C18: семейство кабелей сигнализации/блокировки (кандидаты: ГОСТ 31995-2012 / ГОСТ Р 56292-2014, точный номер для этой маркировки не подтверждён) | D18: 0.35 | G18: 4 | H18: чёрный (оболочка) | J18: полиэтилен (изоляция жил) / оболочка — источники расходятся: rfopt.ru/pvvs-4h035 указывает свинцовую оболочку (нетипично), общее описание серии rfopt.ru/pvvs — пластмассовую — решено агентом — проверить | M18: -40 | N18: 60 | O18: 380 (перем.) / 700 (пост.) — по описанию серии, для конкретной позиции не подтверждено | R18: 8 | S18: 59 | U18: https://rfopt.ru/pvvs-4h035 | V18: rfopt.ru (карточка товара + общее описание серии pvvs); наружный диаметр и вес страницей не даны — оставлено пустым. Темп./напряжение — по общему описанию серии ПВВС, не по этой конкретной позиции — решено агентом — проверить
A19: НВ-4 0,75 | B19: монтажный | C19: ГОСТ 17515-72 | D19: 0.75 | G19: 1 | H19: чёрный, коричневый, желто-зелёный, синий, красный, жёлтый, зелёный | I19: 2.1 | J19: ПВХ-пластикат | M19: -50 | N19: 105 | O19: 600 | R19: 43 | S19: 23 | U19: https://snabcable.ru/mounting/nv-nve/nv/ | V19: snabcable.ru; цена последней закупки у разных цветов в одном месяце расходится (15,6-19,5) — взято модальное значение 15,6 — решено агентом — проверить
A20: UL2725 28AWG | B20: монтажный (экранированный многожильный) | C20: UL AWM Style 2725 (регламентируется UL758) | D20: 0.08 | E20: 28 | F20: 7×0,127 (луж. медь, по типовым датащитам) | G20: 1 | J20: ПВХ | K20: возможен (стиль 2725 обычно применяется к экранированным многожильным кабелям) | N20: 60 | O20: 30 | R20: 7 | S20: 32.3 | T20: Склад, Фраксис | V20: ВАЖНОЕ РАСХОЖДЕНИЕ: по независимым датащитам (ul-cables.com/p/ul2725, кабельные сборки типа ulcul.com/.../UL2725-28AWG-x-1Pair-24AWG-x-2C-AEB.pdf) style 2725 — это экранированный МНОГОжильный кабель (напр. для USB), рассчитанный на 30В/60-80°C, а НЕ одиночный монтажный провод на 300В/105°C, как можно было бы предположить по аналогии с UL1061/2725. Конкретная позиция покупателя (без ссылки) не идентифицирована — приведены типовые параметры одной жилы 28AWG из таких кабелей — решено агентом — проверить
A21: ПГВА 0,50 | B21: силовой | C21: ТУ 16.К17-021-94 | D21: 0.5 | G21: 1 | H21: красный, чёрный | I21: 2.3 | J21: ПВХ-пластикат | M21: -40 | N21: 70 | O21: 48 | R21: 12 | S21: 8.9 | U21: https://snabcable.ru/car/pvam-pvame-pvamde/pgva/ | V21: snabcable.ru; жила — медь многопроволочная 3-го класса гибкости, страндинг страницей не указан
A22: Силиконовый провод 20AWG | B22: силиконовый | C22: генерик (китайское производство), prodiel.ru | D22: 0.5 | E22: 20 | F22: 100×0,08 (луж. медь) | G22: 1 | H22: чёрный, жёлтый, красный, серый | I22: 1.8 | J22: силиконовая резина | M22: -60 | N22: 200 | O22: 600 | P22: 13.87 | R22: 17 | S22: 55.7 | V22: данные по сниппету поиска (карточки товара prodiel.ru), не проверено прямым WebFetch в этой сессии; ток 13,87А выглядит нетипично точным по сравнению с другими типоразмерами — решено агентом — проверить
A23: Силиконовый провод 30AWG | B23: силиконовый | C23: генерик (китайское производство), prodiel.ru | D23: 0.05 | E23: 30 | F23: 11×0,08 (луж. медь) | G23: 1 | H23: чёрный, красный, жёлтый, синий, зелёный, оранжевый | I23: 0.8 | J23: силиконовая резина | M23: -60 | N23: 200 | O23: 600 | P23: 0,5 (длит.) / 0,8 (кратк.) | Q23: 1.5 | R23: 37 | S23: 4.1 | T23: Китай | U23: https://prodiel.ru/provod-silikonoviy-30awg-005-mm-2500-m-cherniy | V23: prodiel.ru
A24: НВ-4 0,35 | B24: монтажный | C24: ГОСТ 17515-72 | D24: 0.35 | G24: 1 | H24: чёрный, красный, белый, зелёный, жёлтый, синий | I24: 1.6 | J24: ПВХ-пластикат | M24: -50 | N24: 105 | O24: 600 | R24: 43 | S24: 12.3 | U24: https://snabcable.ru/mounting/nv-nve/nv/ | V24: snabcable.ru; объединены варианты написания "НВ-4 0,35мм2", "НВ4-0,35мм2", "НВ4 0,35" — канонизировано как НВ-4 0,35
A25: Силиконовый провод 26AWG | B25: силиконовый | C25: генерик (китайское производство), prodiel.ru | D25: 0.15 | E25: 26 | F25: 30×0,08 (луж. медь) | G25: 1 | H25: красный, чёрный, белый, жёлтый, зелёный, коричневый, синий | I25: 1.5 | J25: силиконовая резина (метилвинилполисилоксан) | M25: -60 | N25: 200 | O25: 600 | P25: 1.5 | R25: 23 | S25: 23.4 | U25: https://prodiel.ru/provod-gibkiy-silikonoviy-awg-26-012-mm-kv-krasniy-100-m | V25: prodiel.ru (2 карточки товара, идентичные характеристики)
A26: UL758 10AWG | B26: монтажный | C26: UL758 — номер стандарта AWM (Appliance Wiring Material) в целом, НЕ конкретный style/марка | D26: 5.26 | E26: 10 | G26: 1 | H26: black, red | R26: 10 | S26: 117.5 | T26: Полина, Китай | V26: UL758 — это обозначение стандарта безопасности UL для класса проводов AWM, а не конкретная конструкция; покупатель указал только "UL758 10AWG" без ссылки, конкретный AWM-style не идентифицирован — решено агентом — проверить. Сечение 5,26мм2 — по стандартной таблице AWG для 10AWG, не из даташита
A27: МС16-13 0,08 | B27: монтажный (высокотемпературный) | C27: ТУ 16-505.083-78 | D27: 0.08 | F27: 7×0,15 (посеребр. медь, марка МСр/БМС) | G27: 1 | H27: белый, зелёный, красный, чёрный, жёлтый, коричневый, оранжевый, синий | I27: 0.72 | J27: фторопластовая плёнка марки 4Д (обмотка) | M27: -60 | N27: 200 | O27: 100 (AC до 10кГц) / 150 (DC) | R27: 36 | S27: 63.1 | U27: https://snabcable.ru/onboard/ms-e-o-16-26-13/ms-16-13/ | V27: snabcable.ru + агрегированные данные по ряду сечений МС16-13 (bystrokabel.ru); жила 7×0,15мм для 0,08мм2 — не проверено первичным текстом ТУ 16-505.083-78 — решено агентом — проверить
A28: МС16-13 0,12 | B28: монтажный (высокотемпературный) | C28: ТУ 16-505.083-78 | D28: 0.12 | F28: 7×0,15 (посеребр. медь) | G28: 1 | H28: красный, чёрный, белый, зелёный, синий, коричневый, оранжевый | I28: 0.9 | J28: фторопластовая плёнка марки 4Д (обмотка) | M28: -60 | N28: 200 | O28: 100 (AC до 10кГц) / 150 (DC) | Q28: 1.9 | R28: 26 | S28: 118.1 | U28: https://snabcable.ru/onboard/ms-e-o-16-26-13/ms-16-13/ | V28: snabcable.ru + bystrokabel.ru (карточка МС16-13 0,12): жила 7×0,15мм, OD 0,90мм, масса 1,9кг/км, ТУ 16-505.083-78 — решено агентом — проверить (данные по типовому ряду сечений, не первичный текст ТУ). Цена закупки у разных цветов расходится (97,8–100,7) — взято среднее 99,1 — решено агентом — проверить. Объединены 5 цветовых позиций (красный,чёрный,белый,зелёный,синий)
A29: ПВАМ 1,0 | B29: силовой | C29: ТУ 16.К19-12-2003 | D29: 1 | G29: 1 | H29: голубой, красный, чёрный, жёлтый, зелёный, оранжевый, розовый, белый, желто-зеленый, коричнево-серый, коричневый, красно-черный, серый | I29: 2.1 | J29: ПВХ-пластикат маслобензостойкий | M29: -40 | N29: 105 | O29: 48 (ном.) / 1000 (испыт.) | Q29: 12 | R29: 38 | S29: 17.6 | U29: https://snabcable.ru/car/pvam-pvame-pvamde/pvam/ | V29: snabcable.ru; жила — медь многопроволочная (класс гибкости страницей не указан, по аналогии с сечениями 0,50/0,35 в базе — 5-й класс) — решено агентом — проверить. Объединены 3 цветовые позиции (голубой,красный,чёрный)
A30: Силиконовый провод 10AWG | B30: силиконовый | C30: генерик (китайское производство), prodiel.ru | D30: 6 | E30: 10 | F30: 1050×0,08 (луж. медь) | G30: 1 | H30: красный, чёрный | I30: 5.4 | J30: силиконовая резина (метилвинилполисилоксан) | M30: -60 | N30: 200 | O30: 300 | P30: 65 (длит.) / 140 (кратк.) | R30: 20 | S30: 188.5 | U30: https://prodiel.ru/provod/provod-gibkiy-v-silikone/silicon-10-awg/ | V30: rccopter.ru обзор + карточка товара prodiel.ru (provod-silikonoviy-10awg-6-mm-kv); реальное сечение 6мм2 отличается от теоретического AWG10 (5,26мм2) — решено агентом — проверить. Напряжение 300В по rccopter, у соседних сечений линейки продавец указывает 600В — расхождение не разрешено — решено агентом — проверить. Объединены 2 цветовые позиции (красный,чёрный)
A31: Силиконовый провод 12AWG | B31: силиконовый | C31: генерик (китайское производство), prodiel.ru | D31: 3.4 | E31: 12 | F31: 680×0,08 (луж. медь) | G31: 1 | H31: красный, чёрный | I31: 4.5 | J31: силиконовая резина (метилвинилполисилоксан + SiO2) | M31: -60 | N31: 200 | O31: 600 | P31: 30 | R31: 10 | S31: 201.5 | T31: Китай | U31: https://prodiel.ru/provod-gibkiy-medniy-luzheniy-awg-12-40-mm-kv-krasniy-100-m | V31: prodiel.ru карточки товара (awg-12-40-mm-kv, красный/чёрный); сопротивление 5,74 Ом/км при 20°C. Объединены 2 цветовые позиции
A32: Силиконовый провод 8AWG | B32: силиконовый | C32: генерик (китайское производство), prodiel.ru | D32: 8.25 | E32: 8 | F32: 1650×0,08 (луж. медь) | G32: 1 | H32: красный, чёрный | I32: 6 | J32: силиконовая резина (метилвинилполисилоксан) | M32: -60 | N32: 200 | O32: 600 | P32: 80 | R32: 8 | S32: 450.6 | U32: https://prodiel.ru/provod-gibkiy-medn-luzh-awg-8-83-mm-kv-krasniy-100-m | V32: prodiel.ru карточки товара (medn-luzh-awg-8-83-mm-kv); сопротивление 2,17 Ом/км при 20°C, медь 99,8%/луж. 0,2%. Объединены 2 цветовые позиции
A33: UL758 12AWG | B33: монтажный | C33: UL758 — номер стандарта AWM в целом, конкретный style не идентифицирован (см. также запись UL758 10AWG) | D33: 3.31 | E33: 12 | F33: 19×0,47 (луж. медь, по типовому стороннему даташиту) | G33: 1 | H33: black, red | I33: 3.94 | J33: ПВХ | M33: -20 | N33: 105 | O33: 600 | R33: 8 | S33: 100.8 | T33: Фраксис | V33: Ссылка покупателем не дана; сечение 3,31мм2 — по стандартной таблице AWG для 12AWG, не из даташита; жила/OD/температура — по типовому стороннему 12AWG hookup-wire datasheet (пример с digikey), не подтверждено для конкретного товара у Фраксис — решено агентом — проверить. Объединены 2 цветовые позиции (black,red)
A34: Силиконовый провод 18AWG | B34: силиконовый | C34: генерик (китайское производство), prodiel.ru | D34: 0.75 | E34: 18 | F34: 150×0,08 (луж. медь) | G34: 1 | H34: чёрный, красный | I34: 2.3 | J34: силиконовая резина (метилвинилполисилоксан) | M34: -60 | N34: 200 | O34: 600 | P34: 6 | R34: 13 | S34: 50 | U34: https://prodiel.ru/provod-gibkiy-medniy-luzheniy-awg-18-075-mm-kv-cherniy-305-m | V34: Покупатель указал как «UL758 18AWG», но по ссылке на prodiel.ru товар — силиконовый провод (метилвинилполисилоксан), а не даташит UL758 AWM; переименовано в «Силиконовый провод 18AWG» по фактическим характеристикам страницы — решено агентом — проверить. Сопротивление 24,47 Ом/км при 20°C, медь 99,8%/луж. 0,2%. Объединены 2 цветовые позиции (Black→чёрный, Red→красный)
A35: МГТФ 0,07 | B35: монтажный (термостойкий) | C35: ТУ 16-505.185-71 | D35: 0.07 | G35: 1 | H35: белый | I35: 0.75 | J35: фторопласт (сетчатая обмотка) | M35: -60 | N35: 220 | O35: 250 (AC, 5кГц) / 350 (DC) | Q35: 1.22 | R35: 6 | S35: 17.3 | U35: https://snabcable.ru/mounting/mgtf-mgtfe/mgtf/ | V35: chuvashkabel (через поиск), ТУ 16-505.185-71; OD 0,75мм, масса 1,22 кг/км для сечения 0,07мм2. Цена последней закупки указана 0,0 — похоже на ошибку данных (см. МГТФ 0,35 — 16,3) — решено агентом — проверить. Число проволок жилы страницей не уточнено
A36: МГТФ 0,35 | B36: монтажный (термостойкий) | C36: ТУ 16-505.185-71 | D36: 0.35 | G36: 1 | I36: 1.19 | J36: фторопласт (сетчатая обмотка) | M36: -60 | N36: 220 | O36: 250 (AC, 5кГц) / 350 (DC) | Q36: 4.25 | R36: 4 | S36: 16.3 | U36: https://snabcable.ru/mounting/mgtf-mgtfe/mgtf/ | V36: chuvashkabel (через поиск), ТУ 16-505.185-71; OD 1,19мм, масса 4,25 кг/км для сечения 0,35мм2. Число проволок жилы страницей не уточнено
A37: ШВПМ 2x0,5 | B37: аудио/сигнальный шнур | C37: ГОСТ 3578-005-39793330-2010 | D37: 0.5 | F37: 16×0,20 | G37: 2 | I37: 4,8×2,34 | J37: ПВХ | M37: -40 | N37: 70 | O37: 100 | Q37: 19.2 | R37: 4 | S37: 45.5 | U37: https://paritet.su/catalog/shvpm_dlya_audio/shvpm_2kh0_50_mm_kv/ | V37: paritet.su карточка товара; сопротивление жилы 39 Ом/км при 20°C. Экран страницей не упомянут (несмотря на категорию «для аудио») — решено агентом — проверить. Минимальная температура монтажа -15°C
A38: ПВАМ 2,5 | B38: силовой | C38: ТУ 16.К19-12-2003 | D38: 2.5 | G38: 1 | I38: 3 | J38: ПВХ-пластикат маслобензостойкий | M38: -40 | N38: 105 | O38: 48 (ном.) / 1000 (испыт.) | Q38: 28 | R38: 3 | S38: 0 | T38: Заказчик | U38: https://snabcable.ru/car/pvam-pvame-pvamde/pvam/ | V38: snabcable.ru; цена последней закупки указана 0,0 — вероятно ошибка данных (у других сечений ПВАМ цена 9–16) — решено агентом — проверить. Номинальное напряжение 48В принято по аналогии с другими сечениями серии, для 2,5мм2 отдельно страницей не подтверждено — решено агентом — проверить. Цвет не указан покупателем
A39: ПуГВ 1,0 | B39: монтажный (повышенной гибкости) | C39: ГОСТ 31947-2012, ТУ 16-705.501-2010 | D39: 1 | G39: 1 | H39: белый, жёлто-зелёный, синий | I39: 2.5 | J39: ПВХ-пластикат | M39: -50 | N39: 65 | O39: 450 | Q39: 16 | R39: 9 | S39: 18 | U39: https://snabcable.ru/mounting/mgtf-mgtfe/pv-3-pugv/ | V39: electro-mpo.ru (карточка жёлто-зелёный) + ruscable.ru (общий профиль ПуГВ); жила 5-го класса гибкости, страндинг страницей не указан — решено агентом — проверить. Цена последней закупки у цветов расходится (18,0–18,5) — взято модальное 18,0 — решено агентом — проверить. Объединены 3 цветовые позиции (белый,жёлто-зелёный,синий)
A40: FTP 2PR 24AWG CAT5e | B40: витая пара (LAN) | C40: REXANT, ТУ; категория 5e | E40: 24 | F40: многопроволочная (страндинг не уточнён) | G40: 4 | H40: серый | I40: 5 | J40: жилы — HDPE, оболочка — ПВХ 0,5мм | K40: фольга (FTP) | L40: 100 | M40: -40 | N40: 60 | R40: 3 | S40: 56 | U40: https://www.vseinstrumenti.ru/product/kabel-rexant-vitaya-para-ftp-2pr-24awg-cat5e-stranded-buhta-305-m-01-0125-1293812/ | V40: vseinstrumenti.ru карточка REXANT FTP 2PR 24AWG CAT5e; частотный диапазон 100МГц; 4 проводника (2 пары). Волновое сопротивление 100 Ом — по определению категории 5e, страницей отдельно не указано — решено агентом — проверить
A41: H05RN-F 3x0,75 | B41: гибкий резиновый (переносной) | C41: H05RN-F (гармонизированное обозначение) | D41: 0.75 | F41: медь многопроволочная, 6 класс гибкости | G41: 3 | I41: 8.9 | J41: резина | M41: -50 | N41: 75 | O41: 500 | R41: 3 | S41: 73.8 | U41: https://n-kabel.ru/position/h05rn-f-3x075/ | V41: n-kabel.ru карточка; оболочка — шланговая резина (неопрен/полихлоропрен), чёрная, отдельная жила заземления. Диапазон -50…+40°C заявлен как рабочий, до +75°C — длительная температура жилы; в «Темп. до» оставлено граничное +75 — решено агентом — проверить. Цвета отдельных жил страницей не детализированы
A42: SSTP-4P-Cat.7-PATCH-IN-LSZH | B42: витая пара (LAN, экранированная) | C42: IEC 61156-5/6, ISO/IEC 11801 класс F; CABEUS | E42: 26 | F42: 7×0,16 (медь) | G42: 8 | H42: оранжевый | J42: LSZH | K42: S/FTP (фольга по парам + общий экран) | L42: 100 | R42: 3 | S42: 91.7 | T42: Склад | U42: https://cabeus.ru/product/6812/ | V42: Данные собраны из поисковых сниппетов (tinko.ru, cabeus.ru, polus.ru) — прямая загрузка страницы cabeus.ru не удалась (JS-рендер, «Loading...»). Категория 7 (600МГц), S/FTP, 4 пары, 26AWG, жила 7×0,16мм многопроволочная (patch), LSZH нг(А)-HF, бухта 305м, 8 проводников (4 пары). Цвет оболочки «оранжевый» — по стороннему магазину polus.ru, не подтверждён официальным даташитом cabeus — решено агентом — проверить. Наружный диаметр и температурный диапазон не найдены — оставлено пустым
A43: UL1015 26AWG | B43: монтажный (AWM) | C43: UL AWM Style 1015, PVC, 600V/105°C | D43: 0.13 | E43: 26 | F43: 7×0,15 (луж. медь) | G43: 1 | H43: чёрный | I43: 2.1 | J43: ПВХ | M43: -20 | N43: 105 | O43: 600 | R43: 3 | S43: 7 | T43: Склад | V43: iewc.com/rs-online.com каталожные данные UL1015 26AWG (7 жил, 0,13мм2, OD 2,1мм, луж.медь, ПВХ); прямая ссылка покупателя не дана, характеристики — по типовым даташитам сторонних продавцов, не от поставщика Склад — решено агентом — проверить. Диапазон -20…105°C — типовой для PVC 105°C AWM, отдельно не подтверждён — решено агентом — проверить
A44: UL1015 28AWG | B44: монтажный (AWM) | C44: UL AWM Style 1015, PVC, 600V/105°C | D44: 0.08 | E44: 28 | F44: 7×0,127 (луж. медь, по аналогии с UL1061 28AWG) | G44: 1 | H44: белый, жёлтый, зелёный, красный, оранжевый, синий, чёрный | J44: ПВХ | M44: -20 | N44: 105 | O44: 600 | R44: 21 | S44: 6.6 | T44: Склад, Китай | V44: Прямая ссылка на товар не дана; сечение/жила приняты по аналогии с записью UL1061 28AWG в базе (7×0,127мм), не из отдельного даташита UL1015 28AWG — решено агентом — проверить. Наружный диаметр не найден — оставлено пустым. Объединены 7 цветовых позиций; «оранжвый» (опечатка) → оранжевый
A45: 5D-FB Cu | B45: коаксиальный | C45: JIS 5D-FB (вариант с медной жилой) | F45: 1×1,80 (медь, сплошная) | G45: 1 | H45: чёрный | I45: 7.54 | J45: вспененный полиэтилен | K45: алюминиевая фольга + алюминиево-магниевая оплетка 120×0,15 мм (двойной) | L45: 50 | M45: -60 | N45: 75 | Q45: 63 | R45: 4 | S45: 110.7 | U45: https://gsm-repiteri.ru/prodazha/cable/kabel-5d-fb-cu-pvc-chernyy | V45: gsm-repiteri.ru; отличие от записи «5D-FB» в базе — центральный проводник сплошная медь (не омедненный алюминий), вариант «Cu» в наименовании товара; вес 63 г/м (6,3 кг/100м), близок к алюминиевому варианту (61,5 г/м) — решено агентом — проверить, отдельная позиция от «5D-FB»
A46: LMR-100 | B46: коаксиальный | C46: обозначение реселлера kroks.ru «LMR-100 Cu Solid PE TC PVC» (не оригинальный Times Microwave LMR-100 датащит) | F46: 1×0,48 (медь, сплошная — по типовой конструкции LMR-100, не подтверждено для этой позиции) | G46: 1 | I46: 2.79 | J46: полиэтилен (Solid PE) | K46: алюминиевая фольга + луженая медная оплетка (TC) | L46: 50 | M46: -40 | N46: 85 | R46: 4 | S46: 53.3 | T46: Давальческое, ООО "Арисмо инжиниринг" | U46: https://kroks.ru/shop/cable-rf/kabel-koaksialnyj-lmr-100-cu-solid-pe-tc-pvc-o/ | V46: kroks.ru (наименование товара «LMR-100 Cu Solid PE TC PVC») + типовые даташиты Times Microwave LMR-100 для справки; это обозначение реселлера, не полный официальный даташит производителя для данной позиции — диаметр жилы, оболочка и температурный диапазон не подтверждены напрямую для товара kroks — решено агентом — проверить. Объединены варианты написания поставщика «ООО "Арисмо инжинеринг"»/«ООО "Арисмо инжиниринг"» → канонично «ООО "Арисмо инжиниринг"»
A47: UL1571 26AWG | B47: монтажный | C47: UL AWM Style 1571, PVC, 300V/80°C | D47: 0.13 | E47: 26 | F47: 7×0,14 (медь) | G47: 1 | H47: белый, жёлтый, зелёный, синий, коричневый, красный, чёрный | J47: ПВХ | M47: -30 | N47: 80 | O47: 300 | R47: 18 | S47: 8.3 | T47: Склад | U47: https://dart.com.ru/index.php?productcode=250695 | V47: dart.com.ru (карточка «белый», аналогичные карточки для др. цветов по productcode 250698-250700); сечение 0,13мм2 по стандартной таблице AWG26, напряжение 300В — по типовому даташиту UL Style 1571 (rdswire.com/iewc.com), не считано напрямую со страницы товара — решено агентом — проверить. Материал жилы (луж./нелуж. медь) и наружный диаметр страницей не уточнены. Объединены 4 цветовые позиции (белый,жёлтый,зелёный,синий)
A48: UL758 28AWG | B48: монтажный | C48: UL758 — номер стандарта AWM в целом, конкретный style не идентифицирован (см. также UL758 10AWG/12AWG в базе) | D48: 0.08 | E48: 28 | F48: 7×0,127 (луж. медь, по аналогии с UL1061/UL1015 28AWG) | G48: 1 | H48: чёрный, синий, зелёный, красный, белый, жёлтый | I48: 0.9 | J48: ПВХ | M48: -20 | N48: 105 | O48: 600 | R48: 18 | S48: 3.4 | V48: Ссылка покупателем не дана (как и для UL758 10AWG/12AWG в базе); конкретный AWM-style для 28AWG не идентифицирован. Сечение/жила 0,08мм2 7×0,127 приняты по аналогии с УЖЕ существующими в базе UL1061 28AWG и UL1015 28AWG (тот же типоразмер). Температура/напряжение у сторонних источников расходятся между 300В/80°C и 600В/105°C для разных UL758-style на 28AWG — взят вариант 600В/-20…105°C по аналогии с UL1015 28AWG — решено агентом — проверить. Объединены 6 цветовых позиций (Black,Blue,Green,Red,White,Yellow)
A49: КСПВГ 6x0,12 | B49: многожильный (сигнальный/контрольный) | C49: ГОСТ 3581-001-39793330-2000 | D49: 0.12 | F49: 7×0,15 | G49: 6 | I49: 3.7 | J49: ПВХ | M49: -50 | N49: 70 | O49: 450 | Q49: 17.6 | R49: 3 | S49: 0 | U49: https://paritet.su/catalog/gibkie_kspvg_kspevg/kspvg_6kh0_12_mm_kv/ | V49: paritet.su карточка товара; цена последней закупки в сводке указана 0,0 — похоже на ошибку данных (аналогично МГТФ 0,07 в базе) — решено агентом — проверить. Экран отсутствует (индекс «Г» — гибкий, без «Э»); минимальная температура монтажа -15°C
A50: МГШВ 0,2 | B50: монтажный | C50: ГОСТ (конкретный номер страницей не указан); Автопровод/Беларускабель | D50: 0.2 | G50: 1 | H50: чёрный | I50: 1.6 | J50: шёлк (оплётка) + ПВХ (оболочка) | O50: 380 (AC до 10кГц) / 500 (DC) | Q50: 3.9 | R50: 3 | S50: 6.5 | T50: АО НПП "Системные Технологии" | U50: https://www.electro-mpo.ru/catalog/provod_i_kabel/p69_mgshv_mgshve_provod_montazhnyy_gost_podolskkab/p6921-provod-mgshv-0-2-kv-mm-gost-chernyy-avtoprov/ | V50: electro-mpo.ru карточка (только чёрный цвет представлен на странице); страндинг жилы страницей не уточнён, температурный диапазон не указан — решено агентом — проверить
A51: НВ-4 0,14 | B51: монтажный | C51: ГОСТ 17515-72 (по аналогии с др. сечениями НВ-4 в базе) | D51: 0.14 | G51: 1 | H51: белый, зелёный, красный, чёрный, жёлтый | J51: ПВХ-пластикат | M51: -50 | N51: 105 | O51: 600 | R51: 14 | S51: 6.6 | U51: https://snabcable.ru/mounting/nv-nve/nv/ | V51: snabcable.ru; сечение 0,14мм2 — отдельная строка ряда ГОСТ 17515-72 (между 0,12 и 0,20 в базе); OD и страндинг для этого сечения страницей отдельно не подтверждены, взят типовой 600В-вариант по аналогии с др. записями НВ-4 в базе — решено агентом — проверить. Объединены 4 цветовые позиции (белый,зелёный,красный,чёрный)
A52: НВ-4 1,50 | B52: монтажный | C52: ГОСТ 17515-72 | D52: 1.5 | G52: 1 | H52: жёлто-зелёный, коричневый, синий | I52: 2.5 | J52: ПВХ-пластикат | M52: -50 | N52: 105 | O52: 600 | Q52: 17 | R52: 9 | S52: 0 | U52: https://snabcable.ru/mounting/nv-nve/nv/ | V52: snabcable.ru; вариант 600В (OD 2,5мм, масса ~16,95 кг/км) взят как базовый — есть также 1000В/НВ-3 1000В (OD 2,7мм) — решено агентом — проверить. Цена последней закупки в сводке 0,0 у всех трёх цветов — похоже на ошибку данных — решено агентом — проверить. Объединены 3 цветовые позиции (жёлто-зелёный,коричневый,синий)
A53: ПВАМ 0,75 | B53: силовой | C53: ТУ 16.К19-12-2003 | D53: 0.75 | G53: 1 | H53: чёрный, зелёный, красный, оранжевый, розовый, серый | I53: 1.9 | J53: ПВХ-пластикат маслобензостойкий | M53: -40 | N53: 105 | O53: 48 (ном.) / 1000 (испыт.) | R53: 13 | S53: 0 | T53: Заказчик, Давальческое | V53: snabcable.ru (общая страница ПВАМ, сечение 0,75мм2: OD 1,9мм, прайс поставщика 15,9); цена последней закупки в сводке закупок указана 0,0 — расходится с прайсом, похоже на ошибку данных — решено агентом — проверить. Ссылка на конкретную карточку покупателем не дана
A54: ПВАМ 1,50 | B54: силовой | C54: ТУ 16.К19-12-2003 | D54: 1.5 | G54: 1 | H54: чёрный, белый | I54: 2.4 | J54: ПВХ-пластикат маслобензостойкий | M54: -40 | N54: 105 | O54: 48 (ном.) / 1000 (испыт.) | R54: 7 | S54: 24.4 | V54: snabcable.ru (общая страница ПВАМ, сечение 1,5мм2: OD 2,4мм); ссылка на конкретную карточку покупателем не дана
A55: ПВС 3x1,5 | B55: гибкий силовой (переносной) | C55: ГОСТ 7399-97 (BREKS, Брянск) | D55: 1.5 | F55: многопроволочная (медь) | G55: 3 | I55: 7.8 | J55: ПВХ | O55: 380 | Q55: 93 | R55: 3 | S55: 0 | U55: https://www.electro-mpo.ru/catalog/provod_i_kabel/p23_pvs_pvsn_provod_gibkiy_gost_rossiya/p2350-provod-pvs-3kh1-5-kv-mm-belyy-gost-breks-brya/ | V55: electro-mpo.ru карточка (BREKS/Брянск); температурный диапазон и цвет страницей/покупателем не даны — оставлены пустыми. Цена последней закупки 0,0 — похоже на ошибку данных — решено агентом — проверить
A56: ШВВП 2x0,75 | B56: гибкий бытовой шнур | C56: ГОСТ (Калужский кабельный завод) | D56: 0.75 | F56: многопроволочная (медь) | G56: 2 | I56: 5.6 | J56: ПВХ | O56: 380 | Q56: 33 | R56: 3 | S56: 0 | U56: https://www.electro-mpo.ru/catalog/provod_i_kabel/p24_pvs_pvsn_shvvp_pbppg_h03vv_f_h05vv_f_frdr_fror/p2468-provod-shvvp-2kh0-75-kv-mm-chernyy-gost-kalu/ | V56: electro-mpo.ru карточка (Калужский кабельный завод, вариант «чёрный»); цвет покупателем не указан — оставлен пустым. Цена последней закупки 0,0 — похоже на ошибку данных — решено агентом — проверить
A57: ШВВП 2x0,5 | B57: гибкий бытовой шнур | C57: ГОСТ (Breks, Брянск) | D57: 0.5 | F57: многопроволочная (медь, 5 класс гибкости) | G57: 2 | I57: 6×4 (овал) | J57: ПВХ | O57: 380 | Q57: 26 | R57: 2 | S57: 20.5 | U57: https://www.electro-mpo.ru/catalog/provod_i_kabel/p24_pvs_pvsn_shvvp_pbppg_h03vv_f_h05vv_f_frdr_fror/p2454-provod-shvvp-2kh0-5-kv-mm-belyy-gost-breks-b/ | V57: electro-mpo.ru карточка (белый, Breks/Брянск); сечение шнура овальное (ширина×высота), не круглое — решено агентом — проверить формат записи. Цвет покупателем не указан
A58: ШТЛЭн-4 | B58: телефонный шнур экранированный | C58: ТУ 16-505.386-78 (семейство ШТЛЭ/ШТСПЭ) | D58: 0.12 | F58: мишурные нити (конструкция не детализирована) | G58: 4 | I58: 5.6 | J58: ПВХ пластикат | K58: оплётка из мишурных нитей | M58: -30 | N58: 50 | R58: 3 | S58: 0 | T58: Давальческое | V58: https://optochip.org/vniikp/2/8/2/ТУ16-505.386-78 — по тексту ТУ16-505.386-78: марка ШТЛЭн (линейный шнур с мишурными жилами), исполнение «-4» = 4 жилы, сечение мишурной нити 0,12мм² (ном.), наружный диаметр 5,6мм max, изоляция — ПВХ пластикат, экран — оплётка из мишурных нитей, рабочий диапазон −30…+50°C, стойкость 15000 двойных перегибов; испытательное напряжение изоляции 500В/1мин (не рабочее — в поле «Напряжение» не перенесено). Изготовитель конкретной партии не определён — Давальческое, цена/поставщик не применимы. Заменяет прежнюю оценку «по аналогии с родственной серией ШТЛП» — теперь данные взяты по тексту самого ТУ марки ШТЛЭ/ШТЛЭн.
A59: ШТСПЭн 2х2-А | B59: телефонный шнур спаренный экранированный | C59: ТУ 16-505.386-78 (семейство ШТСПЭ) | D59: 0.03 | F59: медная проволока (гибкая жила, раскладка проволок не детализирована) | G59: 4 | I59: 3,9 x 6,2 | J59: смесь полиэтилена с полипропиленом | K59: оплётка из медных проволок 0,05–0,06 мм на каждую пару | M59: -30 | N59: 50 | Q59: 62 | R59: 3 | S59: 0 | T59: Давальческое | V59: https://optochip.org/vniikp/2/8/2/ТУ16-505.386-78 — точной марки «ШТСПЭн» (с мишурными жилами) НЕ найдено ни в одном источнике (в т.ч. на ufimcabel.ru, перечисляющем весь ассортимент ШТСЭ/ШТСИЭ/ШТСПЭ/ШТЛЭ/ШТЛЭн/ШТЛИЭ/ШТЛИЭО/ШТЭА — «ШТСПЭн» там нет). Под ТУ16-505.386-78 документирована марка ШТСПЭ (2х2, гибкие МЕДНЫЕ жилы — не мишурные нити), сечение жилы 0,03мм², наружный диаметр 3,9×6,2мм, изоляция — смесь ПЭ/ПП, экран — оплётка из медных проволок Ø0,05-0,06мм на каждую пару, рабочий диапазон −30…+50°C, масса 62,0кг/1000м. Суффикс «-А» в закупочном наименовании «ШТСПЭн 2х2-А» НЕ идентифицирован ни в одном источнике — решено агентом — проверить: возможно обозначает конкретное исполнение экрана/оболочки, отсутствующее в открытых каталогах, либо является внутренним обозначением закупки. Жила скорректирована с «мишурные нити» на «медная проволока» (см. отдельную строку). Изготовитель конкретной партии не определён — Давальческое.
A60: CCCU-15G-26 | B60: коммуникационный (многожильный) | C60: UL2464 (маркировка продавца) | D60: 0.129 | E60: 26 | F60: многожильная (луж. медь) | G60: 15 | H60: серый | I60: 6.9 | J60: ПВХ полутвёрдый (0,85 мм) | K60: нет | M60: 0 | N60: 70 | R60: 2 | S60: 69.7 | U60: https://www.brownbear.ru/catalog/cable/kabel-kommunikatsionnyy/kabel_kommunikatsionnyy_15_provodov_26_awg_bukhta_50m_neekranirovannyy_seryy.html | V60: brownbear.ru карточка товара; точный страндинг жилы страницей не детализирован — решено агентом — проверить
A61: CCCU-4G | B61: коммуникационный (многожильный) | C61: UL2464 (маркировка продавца) | D61: 0.081 | E61: 28 | F61: 7×0,127 (луж. медь) | G61: 4 | H61: серый | I61: 3.6 | J61: ПВХ полутвёрдый (0,8 мм) | K61: нет | M61: 0 | N61: 70 | R61: 2 | S61: 20.5 | U61: https://www.brownbear.ru/catalog/cable/kabel-kommunikatsionnyy/kabel_kommunikatsionnyy_4_provoda_28_awg_bukhta_50m_neekranirovannyy_seryy.html | V61: brownbear.ru карточка товара, аналогично CCCU-15G-26 (тот же стандарт UL2464)
A62: 8D-FB | B62: коаксиальный | C62: JIS 8D-FB (вариант CCA) | F62: 1×2,56 (медненный алюминий, сплошная) | G62: 1 | H62: чёрный | I62: 10.15 | J62: вспененный полиэтилен (диэлектрик Ø7,35мм) | K62: алюминиевая фольга + алюминиево-магниевая оплётка (двухслойный) | L62: 50 | M62: -60 | N62: 75 | Q62: 115 | R62: 3 | S62: 125 | U62: https://gsm-repiteri.ru/prodazha/cable/kabel-8d-fb-cca | V62: gsm-repiteri.ru; жила из медненного алюминия (CCA) — как и у «5D-FB» в базе (удешевлённый вариант относительно типовой JIS-спецификации) — решено агентом — проверить. Затухание 13,6дБ/100м на 900МГц; монтажный диапазон -20…+50°C (в таблице — рабочий -60…+75°C)
A63: LMR-400 LSZH | B63: коаксиальный (низкопотерьный) | C63: Times Microwave LMR-400-LSZH (LS Cable & System) | F63: 1×2,77 (медненный алюминий) | G63: 1 | I63: 10.29 | J63: вспененный полиэтилен | K63: двойной: алюминиевая фольга + оплётка луж. медь 90% | L63: 50 | M63: -40 | N63: 85 | Q63: 100 | R63: 2 | S63: 573.8 | U63: https://www.1-cable.ru/models/10605-6201.html | V63: 1-cable.ru (LS Cable & System) + типовой Times Microwave LMR-400-LSZH datasheet (темп./масса, т.к. на странице 1-cable.ru не даны); жила — алюминий с медным покрытием, аналогично «LMR-100» в базе; оболочка LSZH безгалогенная — решено агентом — проверить
A64: PAAR-TRONIC-CY 8x2x0,25 | B64: многожильный экранированный (сигнальный, DIN 47100) | C64: LAPP/Helukabel PAAR-TRONIC-CY / UNITRONIC CY PiDY | D64: 0.25 | F64: многопроволочная (медь) | G64: 16 | H64: серый | I64: 14.2 | J64: ПВХ | K64: оплётка луж. медь (общий экран), безгалогенный | M64: -30 | N64: 80 | Q64: 330 | R64: 2 | S64: 691.3 | T64: КабельРФ | V64: Точная карточка товара покупателем не дана; данные обобщены по линейке LAPP/Helukabel PAAR-TRONIC-CY / UNITRONIC CY PiDY TP (8x2x0,25): ПВХ, цветовая маркировка DIN 47100, экран из луж. меди, -30…+80°C (фикс.)/-5…+80°C (гибк., указано в темп.от базовое). OD≈14,2мм и масса≈330г/м взяты из стороннего поиска, возможно относятся к двухэкранному варианту CY-CY — не подтверждено напрямую для базовой CY — решено агентом — проверить. GR (в наименовании покупателя) = серый цвет оболочки
A65: RG316-D | B65: коаксиальный | C65: MIL-DTL-17 RG-316/D; Huber+Suhner ENVIROFLEX-316-D | F65: 7×0,18 (посеребр. медненная сталь) | G65: 1 | H65: чёрный, синий | I65: 3.16 | L65: 50 | N65: 105 | O65: 1300 | R65: 3 | S65: 352.5 | T65: Склад | U65: https://www.chipdip.ru/product/enviroflex-316-d-100-m-rg316-d-coaxial-huber-suhner-8014772762 | V65: chipdip.ru (Huber+Suhner ENVIROFLEX-316-D = RG316/D) — отдельная марка от «RG316» (=RG316/U) в базе: другой наружный диаметр (3,16 vs 2,45мм), напряжение (1300В vs 2000В) и материал жилы (посеребр. медненная сталь vs посеребр. медь). Диэлектрик и точная конструкция экрана страницей не даны — оставлены пустыми — решено агентом — проверить. Оболочка LSFH (безгалогенная), полоса до 6ГГц
A66: Силиконовый провод 24AWG | B66: силиконовый | C66: генерик (китайское производство), prodiel.ru | D66: 0.2 | E66: 24 | F66: 40×0,08 (луж. медь) | G66: 1 | H66: чёрный | I66: 1.6 | J66: силиконовая резина (метилвинилполисилоксан) | M66: -60 | N66: 200 | O66: 600 | P66: 2 | R66: 3 | S66: 18.9 | U66: https://prodiel.ru/provod-silikonoviy-24awg-02-mm-kv-100-m-cherniy | V66: prodiel.ru карточка товара (24AWG чёрный); сопротивление 91,7 Ом/км при 20°C, медь 99,8%/луж. 0,2%
A67: ParLan Patch U/UTP Cat5e 2x2x0,48 | B67: витая пара (LAN, патч-корд) | C67: ГОСТ 3574-010-39793330-2009 (Паритет ParLan); также IEC 61156-6, TIA/EIA-568-A | E67: 26 | F67: 7×0,16 (медь) | G67: 4 | I67: 5.185 | J67: ПВХ | L67: 100 | M67: -50 | N67: 70 | O67: 145 | R67: 3 | S67: 36.7 | U67: https://paritet.su/catalog/cat5e_u_utp_6/parlan_patch_u_utp_cat5e_pvc_2kh2kh0_48/ | V67: paritet.su карточка «ParLan Patch U/UTP Cat5e PVC 2х2х0,48» (4 жилы = 2 пары, 26AWG, 7×0,16мм медь, ПВХ, OD 5,185мм, серый, до 100МГц, монтаж не ниже -15°C, хранение от -50°C); волновое сопротивление 100 Ом и напряжение 145В — по общему описанию линейки ParLan Cat5e U/UTP, для этой конкретной карточки отдельно не даны — решено агентом — проверить. Ссылка покупателя (anlan.ru) не открылась (JS-рендер «Loading...»), использована карточка производителя (Паритет).
A68: Sucoform 141 Cu FEP | B68: коаксиальный (полужёсткий, формуемый) | C68: Huber+Suhner SUCOFORM_141_FEP (RG402-типоразмер) | F68: 1×0,94 (посеребр. медь, сплошная) | G68: 1 | J68: ПТФЭ (2,95мм) | K68: луженая медная оплётка (99%) | L68: 50 | N68: 165 | O68: 1900 | Q68: 40 | R68: 2 | S68: 0 | T68: Давальческое | U68: https://www.mouser.com/datasheet/2/829/HUBER_2bSUHNER_SUCOFORM_141_FEP_DataSheet-1489508.pdf | V68: Huber+Suhner SUCOFORM_141_FEP datasheet (Mouser): формуемый полужёсткий коаксиал RG402-размера, жила 0,94мм посеребр.медь, диэлектрик ПТФЭ 2,95мм, оплётка луж.медь 99%, 50 Ом, 165°C, раб.напряжение ≤1,9кВ (исп. 5кВ), масса 4кг/100м=40г/м. Наружный диаметр с FEP-оболочкой (вариант «Cu FEP» покупателя) отдельно не подтверждён — оставлен пустым — решено агентом — проверить. Давальческое — цена 0,0 корректна
A69: TSK1160 | B69: USB-кабель (экранированный, многожильный) | C69: Tasker TSK1160, UL AWM Style 2725 | E69: 26 | F69: многопроволочная (OFC, страндинг не детализирован) | G69: 4 | K69: экранированный (тип экрана страницей не детализирован) | Q69: 38 | R69: 2 | S69: 499.2 | U69: https://www.tasker.it/db_files/products/79d2ee375b.pdf | V69: Tasker TSK1160 datasheet (tasker.it) + TME/yeint.fi листинги: USB2.0 кабель, UL AWM Style 2725, OFC (бескислородная медь), состав 1x2x0,14мм2 (сигнальная пара) + 2x0,22мм2 (питание), чёрный, экранированный, масса 3,8кг/100м=38г/м. Сам PDF — бинарный, таблица страндинга/изоляции/температуры не считана напрямую — решено агентом — проверить. Ссылка покупателя (elitan.ru) не дала данных о товаре — использован даташит производителя
A70: U/UTP Cat 5 25 пар 24 AWG | B70: витая пара (LAN, магистральный) | C70: Cabeus; ГОСТ 31565, ГОСТ 54429, ТР ТС 004/2011 | E70: 24 | F70: 1× (однопроволочная, медь) | G70: 50 | J70: полиэтилен (жилы) / LSZH нг(A)-HF (оболочка) | L70: 100 | R70: 2 | S70: 327.9 | U70: https://www.etm.ru/cat/nn/1574940 | V70: etm.ru карточка (Cabeus, 25 пар, 24AWG, однопроволочная медь, изоляция — высокоскоростной ПЭ, оболочка LSZH нг(A)-HF, серая, до 100МГц, U/UTP); волновое сопротивление 100 Ом — по определению категории Cat5, страницей отдельно не указано — решено агентом — проверить. Наружный диаметр и температурный диапазон страницей не даны — оставлены пустыми
A71: UL1007 30AWG | B71: монтажный | C71: UL AWM Style 1007, PVC, 300V/80°C | D71: 0.05 | E71: 30 | F71: 7×0,101 (луж. медь, 7/38AWG, по аналогии с UL1061 30AWG в базе) | G71: 1 | H71: белый, красный, синий, чёрный | J71: ПВХ | M71: -20 | N71: 80 | O71: 300 | R71: 8 | S71: 6.6 | V71: Ссылка покупателем не дана. Данные — по типовому даташиту UL AWM Style 1007 (remingtonindustries.com, iewc.com): 7×0,101мм (7/38AWG) луж.медь — по аналогии с уже существующей в базе записью UL1061 30AWG (тот же типоразмер жилы, тот же класс изделия); 300В — стандартный рейтинг Style 1007. Температура у разных поставщиков расходится (80°C классический / 105°C у отдельных партий компаунда) — принято 80°C по умолчанию — решено агентом — проверить. Наружный диаметр не подтверждён — оставлен пустым. Объединены 4 цветовые позиции (белый,красный,синий,чёрный)
A72: UL1571 28AWG | B72: монтажный | C72: UL AWM Style 1571, PVC, 300V/80°C (по аналогии с UL1571 26AWG в базе) | D72: 0.08 | E72: 28 | F72: 7×0,127 (луж. медь, по аналогии с UL1061/UL1015 28AWG в базе) | G72: 1 | H72: белый, жёлтый, зелёный, красный, серый, синий, чёрный | J72: ПВХ | M72: -30 | N72: 80 | O72: 300 | R72: 14 | S72: 10.7 | U72: https://aliexpress.ru/item/1005007475438542.html | V72: Карточка aliexpress (одна на все цвета, sku_id разный по цвету). Сечение/жила 0,08мм2, 7×0,127мм — по аналогии с уже существующей в базе записью UL1571 26AWG (тот же Style 1571) и стандартной таблицей AWG для 28AWG (7/36) — не считаны напрямую с карточки — решено агентом — проверить. Объединены 7 цветовых позиций (белый,жёлтый,зелёный,красный,серый,синий,чёрный)
A73: Кабель высоковольтный 150kV 0,75мм2 8мм | B73: силовой (высоковольтный) | C73: генерик (реселлер AliExpress, маркировка «GEVZ»), двухслойный силиконовый высоковольтный провод | D73: 0.75 | F73: многопроволочная (медь, страндинг не детализирован) | G73: 1 | I73: 8 | J73: силиконовая резина, двухслойная изоляция | M73: -60 | N73: 200 | O73: 150000 | R73: 2 | S73: 1847.5 | U73: https://aliexpress.ru/item/1005005929231862.html | V73: Карточка AliExpress не отрендерилась при прямом чтении (JS «Loading...»); характеристики (0,75мм2, OD 8мм, 150кВ, двойная силиконовая изоляция) подтверждены через поиск по тем же значениям (реселлер маркирует линейку «GEVZ», диапазон 10-150кВ на сечениях 0,75-2,5мм2, типовой температурный диапазон силиконовых высоковольтных проводов этого класса -60…+200°C) — конструкция жилы и точный тип изоляции не считаны напрямую с карточки товара — решено агентом — проверить
A74: КВСФ-75 | B74: коаксиальный (бортовой) | C74: ГОСТ-based (Камкабель/ОКБ КП), бортовые мультиплексные системы | F74: 1× (медь посеребрённая, сплошная) | G74: 1 | I74: 4.2 | J74: фторопласт Ф-4МБ | K74: оплётка луж. медь | L74: 75 | M74: -60 | N74: 200 | O74: 250 | R74: 2 | S74: 491.8 | U74: https://cable.ru/cable/marka-kvsf_75.php | V74: cable.ru карточка марки КВСФ-75: коаксиал для бортовых мультиплексных систем передачи, оплётка луж.медь, оболочка Ф-4Д+Ф-4МБ, 75±5 Ом, -60…+200°C, макс. 250В (30МГц и выше), ёмкость 65пФ/м, срок службы ≥20 лет
A75: КДВВГ 6x0,14 | B75: многожильный (сигнальный/контрольный) | C75: Паритет, ГОСТ (номер страницей не указан) | D75: 0.14 | F75: 12×0,12 | G75: 6 | J75: ПВХ пластикат | M75: -50 | N75: 70 | O75: 300 | R75: 2 | S75: 58.2 | U75: https://www.etm.ru/cat/nn/9446989 | V75: etm.ru карточка (Паритет, арт. 108449): 6 жил по 12×0,12мм медь, изоляция и оболочка — ПВХ пластикат, без экрана, -50…+70°C, 300В (10кГц), особо гибкий инструментальный кабель. Наружный диаметр и номер ГОСТ страницей не даны — оставлены пустыми
A76: КДЭВГ 9х0,14 | B76: многожильный экранированный (сигнальный/контрольный) | C76: ГОСТ 3581-011-39793330-2009; пожаробезопасность ГОСТ 31565-2012 | D76: 0.14 | F76: (5 класс по ГОСТ 22483-2021) | G76: 9 | I76: 6.1 | J76: ПВХ | K76: экранированный (тип экрана страницей не детализирован) | M76: -50 | N76: 70 | O76: 200 | Q76: 60.6 | R76: 2 | S76: 147.5 | U76: https://paritet.su/catalog/kdvevg_liycy/kdvevg_9kh0_14_tsifr_mark/ | V76: paritet.su карточка: 9 жил 0,14мм2, гибкая скрутка 5 класса, ПВХ изоляция, экран, OD 6,1мм, масса 60,6кг/км=60,6г/м, -50…+70°C, 200В, радиус изгиба 40мм, ГОСТ 3581-011-39793330-2009 / пожаробезопасность ГОСТ 31565-2012 (п.1.8.2.5.4)
A77: КСПВГ 2х0,20 | B77: многожильный (сигнальный/контрольный) | C77: Паритет (Подольск), ГОСТ | D77: 0.2 | F77: многопроволочная (медь) | G77: 2 | I77: 2,2×3,2 | J77: полиэтилен (жилы) / ПВХ-пластикат (оболочка) | O77: 145 | Q77: 10 | R77: 2 | S77: 28.6 | U77: https://www.electro-mpo.ru/catalog/provod_i_kabel/p63_kspv_kpsvv_kspp_kspvg_ksvv_kpsvvng_a_ls_kpsvvn/p6508-kabel-kspvg-2kh0-20-kv-mm-100416-gost-parite/ | V77: electro-mpo.ru карточка (Паритет, Подольск): 2 жилы 0,20мм2, стандартная скрутка, изоляция ПЭ, оболочка ПВХ-пластикат, OD 2,2×3,2мм (овал), масса 10кг/км=10г/м, 145В (10кГц), для пожарной/охранной сигнализации. Температурный диапазон страницей не дан — оставлен пустым
A78: КСПВГ 4x0,20 | B78: многожильный (сигнальный/контрольный) | C78: Breks (Брянск), ГОСТ | D78: 0.2 | F78: многопроволочная (медь) | G78: 4 | I78: 3.6 | J78: полиэтилен (жилы) / ПВХ-пластикат (оболочка) | O78: 145 | Q78: 18 | R78: 2 | S78: 0 | U78: https://www.electro-mpo.ru/catalog/provod_i_kabel/p63_kspv_kpsvv_kspp_kspvg_ksvv_kpsvvng_a_ls_kpsvvn/p6376-kabel-kspvg-4kh0-20-kv-mm-gost-breks-bryansk/ | V78: electro-mpo.ru карточка (Breks, Брянск): 4 жилы 0,20мм2, ПЭ изоляция, ПВХ-пластикат оболочка, OD 3,6мм, масса 18кг/км=18г/м, 145В, для пожарной/охранной сигнализации. Цена последней закупки в сводке 0,0 (см. Закупок) — похоже на ошибку данных, как и у др. подобных записей — решено агентом — проверить. Температурный диапазон страницей не дан
A79: КСПВГ 4x0,35 | B79: многожильный (сигнальный/контрольный) | C79: Breks (Брянск), ГОСТ | D79: 0.35 | F79: многопроволочная (медь), гибкая | G79: 4 | I79: 4.2 | J79: полиэтилен (жилы) / ПВХ-пластикат (оболочка) | O79: 145 | Q79: 25 | R79: 2 | S79: 31 | U79: https://www.electro-mpo.ru/catalog/provod_i_kabel/p63_kspv_kpsvv_kspp_kspvg_ksvv_kpsvvng_a_ls_kpsvvn/p6387-kabel-kspvg-4kh0-35-kv-mm-gost-breks-bryansk/ | V79: electro-mpo.ru карточка (Breks, Брянск, П6387): 4 гибкие жилы 0,35мм2, ПЭ изоляция, ПВХ-пластикат оболочка, OD 4,2мм, масса 25кг/км=25г/м, 145В, монтаж «под штукатурку». Температурный диапазон страницей не дан
A80: КСПВГ 4x0,50 | B80: многожильный (сигнальный/контрольный) | C80: ГОСТ 3581-011-39793330-2009 (Паритет) | D80: 0.5 | F80: 19×0,18 (медь, 5 класс по ГОСТ 22483-2021) | G80: 4 | I80: 5.3 | J80: ПВХ (жилы) / резиновый компаунд (оболочка) | M80: -50 | N80: 70 | O80: 200 | Q80: 46.3 | R80: 2 | S80: 75.6 | U80: https://paritet.su/catalog/kdvvg_liyy/kdvvg_4kh0_50_tsvet_mark/ | V80: ВАЖНО: ссылка покупателя ведёт на карточку «КДВВГ 4х0,50» (paritet.su), а не «КСПВГ» — марка в закупке (КСПВГ 4x0,5) и марка по ссылке (КДВВГ 4х0,50) расходятся; название сохранено по написанию покупателя (согласовано с соседними КСПВГ 2х0,20/4х0,20/4х0,35 в этой же партии), характеристики взяты со страницы по факту данной ссылки — решено агентом — проверить: возможно опечатка покупателя либо КСПВГ и КДВВГ здесь взаимозаменяемы у поставщика. 4 жилы 19×0,18мм (5 класс), ПВХ/резина, OD 5,3мм, масса 46,3кг/км=46,3г/м, -50…+70°C, 200В, ГОСТ 3581-011-39793330-2009
A81: КСПЭВГ 4x0,35 | B81: многожильный экранированный (сигнальный/контрольный) | C81: Паритет (Подольск), ГОСТ, экранированный | D81: 0.35 | F81: многопроволочная (медь) | G81: 4 | I81: 4.7 | J81: полиэтилен (жилы) / ПВХ-пластикат (оболочка) | K81: контактный проводник из луж. медной проволоки | Q81: 31 | R81: 2 | S81: 106.6 | U81: https://www.electro-mpo.ru/catalog/provod_i_kabel/p64_kspev_kspvev_kpsvev_kmvev_kpsvevng_a_ls_kpseng/p6532-kabel-kspevg-4kh0-35-kv-mm-100266-gost-ekran/ | V81: electro-mpo.ru карточка (Паритет, Подольск, арт. 100266): 4 жилы 0,35мм2, ПЭ изоляция, ПВХ-пластикат оболочка, экран — контактный проводник из луж.медной проволоки, OD 4,7мм, масса 31кг/км=31г/м, для систем связи/сигнализации/телекоммуникаций. Температура и напряжение страницей не даны
A82: МГТФ 0,20 | B82: монтажный (термостойкий) | C82: ТУ 16-505.185-71 | D82: 0.2 | F82: (конструкция как у др. сечений МГТФ в базе) | G82: 1 | I82: 1.04 | J82: фторопласт (сетчатая обмотка) | M82: -60 | N82: 220 | O82: 1500 | Q82: 2.96 | R82: 2 | S82: 16.1 | U82: https://snabcable.ru/mounting/mgtf-mgtfe/mgtf/ | V82: snabcable.ru таблица МГТФ по сечениям, строка 0,20мм2: OD 1,04мм, масса 2,96кг/км=2,96г/м; общий диапазон серии -60…+220°C, 1500В — ТУ 16-505.185-71 (как у уже существующих в базе МГТФ 0,07/0,35)
A83: МГТФ 1,0 | B83: монтажный (термостойкий) | C83: ТУ 16-505.185-71 | D83: 1 | F83: (конструкция как у др. сечений МГТФ в базе) | G83: 1 | I83: 1.9 | J83: фторопласт (сетчатая обмотка) | M83: -60 | N83: 220 | O83: 1500 | Q83: 10.75 | R83: 2 | S83: 45.1 | U83: https://snabcable.ru/mounting/mgtf-mgtfe/mgtf/ | V83: snabcable.ru таблица МГТФ по сечениям, строка 1,0мм2: OD 1,9мм, масса 10,75кг/км=10,75г/м; общий диапазон серии -60…+220°C, 1500В — ТУ 16-505.185-71
A84: МГШВ 0,75 | B84: монтажный | C84: ТУ 16-505.437-82 | D84: 0.75 | F84: (конструкция как у МГШВ 0,2 в базе) | G84: 1 | H84: красный | I84: 2.5 | J84: шёлк (оплётка) + ПВХ (оболочка) | M84: -50 | N84: 70 | O84: 1000 | R84: 2 | S84: 23.4 | T84: АО НПП "Системные Технологии" | U84: https://snabcable.ru/mounting/nv-nve/mgshv/ | V84: snabcable.ru таблица МГШВ по сечениям, строка 0,75мм2: OD 2,5мм, оплётка из полиэфирной нити в два противоположных слоя + ПВХ оболочка, -50…+70°C, 1000В (исп. 2000В/50Гц), ТУ 16-505.437-82. Масса страницей для этого сечения не дана
A85: МКШ 2x0,75 | B85: монтажный (межприборный) | C85: монтажный провод (снабжённый ГОСТ номер страницей не указан) | D85: 0.75 | F85: (материал/страндинг страницей не детализированы) | G85: 2 | I85: 7.5 | J85: ПВХ | M85: -50 | N85: 60 | O85: 500 | Q85: 50 | R85: 2 | S85: 29.6 | U85: https://www.kable-m.ru/cable/mksh-2h0-75 | V85: kable-m.ru карточка: 2 жилы 0,75мм2, ПВХ оболочка, без экрана, OD 7,5мм, масса 50кг/км=50г/м, -50…+60°C, 500В AC(до 400Гц)/750В DC, испытательное 2000В/50Гц, климат УХЛ. Материал/страндинг жилы и номер ГОСТ страницей не даны
A86: МС 15-11 0,12 | B86: монтажный (теплостойкий) | C86: ТУ16-705.199-81 | D86: 0.12 | F86: многопроволочная (медь луженая, 4 класс по ГОСТ 22483-2012) | G86: 1 | J86: фторопласт-4МБ (0,2мм) | M86: -60 | N86: 155 | O86: 100 | R86: 2 | S86: 26.2 | U86: https://cable.ru/cable/group-ms_15_11_description.php | V86: cable.ru + tatlon.ru описание серии МС 15-11: монтажный теплостойкий провод, многопроволочная луж.медная жила 4 класса (ГОСТ 22483), монолитная изоляция фторопласт-4МБ 0,2мм, -60…+155°C, 100В переменного тока до 50МГц, ТУ16-705.199-81, 7 цветов исполнения. Ссылка покупателя (vpkvazar.ru) вернула 404 — использованы альтернативные источники. Наружный диаметр не найден — оставлен пустым
A87: НВМ 0,35 | B87: монтажный | C87: ГОСТ 17515-72 | D87: 0.35 | F87: многопроволочная (медь, 4 класс по ГОСТ 22483-2021) | G87: 1 | H87: зелёный, красный, чёрный | I87: 1.6 | J87: ПВХ-пластикат | M87: -50 | N87: 105 | O87: 600 | Q87: 6 | R87: 6 | S87: 13.4 | U87: https://bystrokabel.ru/item/nvm/nvm-0-35-4-600 | V87: bystrokabel.ru карточка НВМ-0,35 4 600: многопроволочная медная жила 4 класса, ПВХ-пластикат 0,35мм, OD 1,6мм, масса 6,0кг/км=6,0г/м, -50…+105°C, 600В AC(до 10кГц)/840В DC, испытательное 2кВ/50Гц, ГОСТ 17515-72, климат УХЛ (в отличие от НВ — климат В). Ссылка покупателя не дана (нет ни в одной из 3 строк). Объединены 3 цветовые позиции (зелёный,красный,чёрный)
A88: ПуГВнг(А)-LS 1х1,0 | B88: монтажный (пониженной пожароопасности) | C88: ГОСТ, Breks (Брянск), нг(А)-LS | D88: 1 | F88: многопроволочная (медь, 5 класс гибкости) | G88: 1 | H88: красный, чёрный | I88: 2.5 | J88: ПВХ-композиция пониженной пожароопасности, низкое дымогазовыделение | O88: 450 | R88: 4 | S88: 16.4 | U88: https://www.electro-mpo.ru/catalog/provod_i_kabel/p05_pugv_pugvng_a_ls_provod_mednyy_ustanovochnyy_g/p0581-provod-pugvng-a-ls-1kh1-0-kv-mm-krasnyy-gost/ | V88: electro-mpo.ru карточка (Breks, Брянск): жила медь многопроволочная 5 класса гибкости, изоляция ПВХ пониженной пожароопасности низкого дымогазовыделения, OD 2,5мм, до 450В (400Гц), нг(А)-LS (не распространяет горение, низкое дымовыделение), сертификат по низкодымности. Температурный диапазон страницей не дан. Объединены 2 цветовые позиции (красный,чёрный)
A89: Силиконовый провод 16AWG | B89: силиконовый | C89: генерик (китайское производство), prodiel.ru | D89: 1.26 | E89: 16 | F89: 252×0,08 (луж. медь) | G89: 1 | H89: чёрный | I89: 3 | J89: силиконовая резина (силикон + диоксид кремния + силиконовое масло) | M89: -60 | N89: 200 | O89: 600 | P89: 10 | R89: 2 | S89: 86.3 | U89: https://prodiel.ru/provod-gibkiy-medniy-luzheniy-awg-16-15-mm-kv-cherniy-50-m | V89: prodiel.ru карточка товара (16AWG чёрный): 1,26мм2, 252×0,08мм луж.медь (99,8%/0,2%), OD 3мм, 600В, рекоменд. ток 10А, сопротивление 14,45 Ом/км при 20°C
A90: 1/2 Baltic Signal BSF-50-12 LSZH | B90: коаксиальный (фидерный, гибкий) | C90: реселлер Baltic Signal, фидер 1/2" | F90: 1× (медненный алюминий, сплошная) 4,8 | G90: 1 | H90: чёрный | I90: 15.7 | J90: вспененный полиэтилен (диэлектрик Ø12,3мм) | K90: гофрированная медная трубка (сплошной экран) Ø13,8мм | L90: 50 | M90: -60 | N90: 85 | O90: 1600 | Q90: 200 | R90: 1 | S90: 300 | U90: https://gsm-repiteri.ru/prodazha/cable/koaksialnyy-fider-1-2-baltic-signal-bsf-50-12-lszh-fr | V90: gsm-repiteri.ru карточка Baltic Signal BSF-50-12 LSZH FR: фидерный кабель 1/2", жила омедненный алюминий Ø4,8мм, диэлектрик вспененный ПЭ Ø12,3мм, экран — гофрированная медная трубка Ø13,8мм, оболочка LSZH чёрная Ø15,7мм, 50±1 Ом, макс. 1600В (пробивное 8000В), мощность до 40кВт, затухание 6,87дБ/100м@900МГц, монтажный диапазон -40…+60°C (в таблице указан рабочий -60…+85°C), масса 20кг/100м=200г/м, мин. радиус изгиба 50/125мм — решено агентом — проверить (рабочий vs монтажный диапазон)
A91: 10D-FB PE | B91: коаксиальный | C91: JIS 10D-FB, реселлер kroks.ru (CCA/PE/AL/PE, для внешней прокладки) | F91: 1×3,5 (медненный алюминий CCA, сплошная) | G91: 1 | I91: 13.1 | J91: вспененный полиэтилен (диэлектрик Ø9,70мм) | K91: алюминиевая фольга + алюминиевая оплётка | L91: 50 | R91: 1 | S91: 229.5 | U91: https://kroks.ru/shop/cable-rf/kabel-koaksialnyj-10d-fb-cca-pe-al-pe-dlya-vneshnej-prokladki/ | V91: kroks.ru карточка «10D-FB CCA/PE/AL/PE для внешней прокладки» (покупатель писал слитно «10DFBPE»): жила CCA Ø3,5мм, диэлектрик вспененный ПЭ Ø9,70мм, экран фольга+оплётка Al, оболочка PE, наружный диаметр 13,1мм, 50 Ом, ёмкость 84пФ/м. Температурный диапазон, масса и цвет страницей не даны (упаковка указывает ~140г на изделие ~1м — ненадёжно, не перенесено) — решено агентом — проверить
A92: 6XV1830-0EH10 | B92: сигнальный (промышленная шина PROFIBUS, экранированный) | C92: Siemens SIMATIC NET PROFIBUS FC Standard Cable GP; 02YSY(ST)CY 1x2x0,64мм2 | D92: 0.64 | E92: 22 | G92: 2 | H92: фиолетовый | I92: 8 | J92: ПВХ (силикон-свободный) | K92: алюминиевая фольга + оплётка луж. медь | M92: -40 | N92: 75 | O92: 600 | R92: 1 | S92: 0 | T92: Давальческое | U92: https://support.industry.siemens.com/teddatasheet/?format=pdf&mlfbs=6XV1830-0EH10&language=en&caller=SIOS | V92: Siemens PROFIBUS FC Standard Cable GP datasheet: двухжильная экранированная шинная пара 22AWG (0,64мм2), оплётка луж.медь по алюминиевой фольге, оболочка ПВХ фиолетовая Ø8мм, макс. напряжение 600В (номинальное Ue=100В), -40…+75°C. Волновое сопротивление PROFIBUS-типовое (135-165 Ом) страницей отдельно не подтверждено — оставлено пустым — решено агентом — проверить. Давальческое — цена 0,0 корректна
A93: 8D-FB Cu | B93: коаксиальный | C93: JIS 8D-FB (вариант с медной жилой), реселлер gsm-repiteri.ru | F93: 1×2,60 (медь, сплошная) | G93: 1 | H93: чёрный | I93: 10.3 | J93: вспененный полиэтилен (диэлектрик Ø7,30мм) | K93: алюминиевая фольга + алюминиево-магниевая оплётка 168×0,15мм | L93: 50 | M93: -60 | N93: 75 | Q93: 123 | R93: 1 | S93: 221.3 | U93: https://gsm-repiteri.ru/prodazha/cable/cable-8d-fb-cu-pvc-chernyy | V93: gsm-repiteri.ru карточка «8D-FB Cu PVC чёрный»: сплошная медная жила Ø2,60мм (в отличие от «8D-FB» уже в базе — там жила CCA), диэлектрик вспененный ПЭ Ø7,30мм, экран двойной — фольга Al + оплётка Al-Mg 168×0,15мм, оболочка ПВХ чёрная Ø10,30мм, 50±3 Ом, коэфф. укорочения 82%, затухание 13,6дБ/100м@900МГц, -60…+75°C, масса 12,3кг/100м=123г/м. Отдельная позиция от «8D-FB» — по аналогии с уже занесённой парой «5D-FB»/«5D-FB Cu»
A94: МГТФ 0,14 | B94: монтажный (термостойкий) | C94: ТУ 16-505.185-71 | D94: 0.14 | G94: 1 | I94: 0.9 | J94: фторопласт (сетчатая обмотка) | M94: -60 | N94: 220 | O94: 1500 | Q94: 2.26 | R94: 1 | S94: 12.5 | T94: АО "Радиоавионика" | U94: https://snabcable.ru/mounting/mgtf-mgtfe/mgtf/ | V94: snabcable.ru таблица МГТФ по сечениям, строка 0,14мм2: OD 0,90мм, масса 2,26кг/км=2,26г/м; общий диапазон серии -60…+220°C, 1500В — ТУ 16-505.185-71 (как у уже занесённых МГТФ 0,07/0,20/0,35/1,0)
A95: МНВ-4 0,12 | B95: монтажный (многопроволочный, малогабаритный) | C95: ГОСТ 17515-72 / ТУ16-505.928-76, класс 4 по ГОСТ 22483-2012 | D95: 0.12 | F95: многопроволочная (медь луженая, 4 класс) | G95: 1 | H95: белый, жёлтый, зелёный, коричневый, красный, синий, чёрный | J95: ПВХ-пластикат (0,180-0,275мм) | M95: -50 | N95: 105 | O95: 100 (AC до 10кГц) / 150 (DC) | R95: 7 | S95: 8.3 | T95: ВП Квазар, Фраксис | U95: https://dart.com.ru/index.php?categorycode=4077 | V95: dart.com.ru категория малогабаритных монтажных проводов (categorycode=4077) + общее описание МНВ-4 (cable.ru, bystrokabel.ru, rfopt.ru): многопроволочная луж.медная жила 4 класса по ГОСТ22483-2012 (ГОСТ17515-72/ТУ16-505.928-76), сечение 0,05-0,2мм2, изоляция ПВХ-пластикат 0,180-0,275мм, -50…+105°C, до 100В(10кГц)/150В DC. Точный наружный диаметр для сечения 0,12мм2 не найден — оставлен пустым — решено агентом — проверить. Цена закупки у «зелёный»(54,8, ВП Квазар) и «коричневый»(20,8, Фраксис) заметно выше остальных пяти цветов (все 8,3) — вероятно другой поставщик/партия — взято модальное значение 8,3 — решено агентом — проверить. Объединены 7 цветовых позиций
A96: РК50-2-11 | B96: коаксиальный | C96: ГОСТ 15565-2012 | F96: 1×0,67 (медь, сплошная) | G96: 1 | I96: 3.2 | J96: полиэтилен 90% (диэлектрик Ø2,25мм) / ПВХ (оболочка) | K96: медная оплётка (90% покрытие) | L96: 50 | M96: -50 | N96: 70 | Q96: 19.7 | R96: 1 | S96: 59.8 | U96: https://paritet.su/catalog/rk_50_2/paraks_rk_50_2_11/ | V96: paritet.su карточка РК50-2-11: жила медь сплошная Ø0,67мм, диэлектрик ПЭ 90% Ø2,25мм, оплётка медная 90%, оболочка ПВХ Ø3,2мм, 50 Ом, затухание 104дБ/мкВ@5-30МГц/100м, ёмкость 9,6пФ/м, -50…+70°C, влажность до 98%@35°C, масса 19,7г/м, ГОСТ 15565-2012, для систем телевещания
A97: ШВПМ 2x0,75 | B97: аудио/сигнальный шнур | C97: ГОСТ (Калужский кабельный завод, П7513) | D97: 0.75 | F97: (страндинг страницей не детализирован) | G97: 2 | H97: красно-чёрный | I97: 5,6×2,7 (овал) | J97: ПВХ-пластикат | O97: 42 | Q97: 27 | R97: 2 | S97: 0 | U97: https://www.electro-mpo.ru/catalog/provod_i_kabel/p75_akusticheskie_kabeli_shnury/p7513-audioshnur-shvpm-2kh0-75-kv-mm-gost-krasno-ch/ | V97: electro-mpo.ru карточка П7513 (Калужский кабельный завод): 2 жилы 0,75мм2, медь, ПВХ-пластикат, OD 5,6×2,7мм (овал), масса 0,027кг/м=27г/м, до 42В AC, красно-чёрный, для подключения акустики/радиооборудования. Температурный диапазон страницей не дан. Цена последней закупки в сводке 0,0 (обе строки) — похоже на ошибку данных, как у аналогичных записей в базе — решено агентом — проверить
A98: AGR2 Core 0,3 | B98: силиконовый (аккумуляторный/RC) | C98: реселлер AliExpress, линейка "AGR2" (супергибкий силиконовый кабель) | D98: 0.3 | F98: многопроволочная (луж. медь, страндинг не детализирован) | G98: 1 | J98: силиконовая резина | M98: -60 | N98: 180 | R98: 1 | S98: 208.3 | U98: https://aliexpress.ru/item/32906320925.html | V98: Карточка AliExpress не отрендерилась напрямую (JS «Loading...»); идентифицирована через поиск — линейка «5m Super Soft Silicone Wire AGR2 Core 0.3-2.5mm2»: многопроволочная луж.медь, силиконовая резина, маслостойкая, -60…+180°C, для аккумуляторных/RC применений. Конструкция жилы (число проволок) и цвет страницей не подтверждены — решено агентом — проверить
A99: Cat5 C5-F/U-26/7FRPVC-BK Teldor | B99: витая пара (LAN, патч-корд) | C99: Teldor C5-F/U-26/7FRPVC-BK, UL1581 VW-1 | D99: 0.13 | E99: 26 | F99: 7×0,17 (медь) | G99: 8 | H99: чёрный | I99: 5.7 | J99: FR-PVC (огнестойкий ПВХ) | K99: алюминиевая фольга (F/UTP) + дренажный проводник | L99: 100 | R99: 1 | S99: 115.5 | U99: https://www.1-cable.ru/models/13012-6002.html | V99: 1-cable.ru карточка Teldor C5-F/U-26/7FRPVC-BK: 4 пары (8 проводников) AWG26/7 (7×0,17мм медь), 0,13мм2, FR-PVC изоляция и оболочка, экран — алюм. фольга (F/UTP), OD 5,7мм, чёрный, 100МГц, UL1581 VW-1. Волновое сопротивление 100 Ом — по определению категории Cat5e, страницей отдельно не указано — решено агентом — проверить
A100: Cat5 RC5-LB1 | B100: витая пара (LAN, патч-корд, outdoor/DMX) | C100: Klotz RC5-LB1; IEC 708, IEC 60332-1, IEC 60754-2 | D100: 0.15 | E100: 26 | F100: 19×0,10 (голая медь) | G100: 8 | H100: бордовый, чёрный | I100: 6.3 | J100: полиэтилен (цветовое кодирование IEC708) / PUR (оболочка) | K100: оплётка луж. медь (80% покрытие) | L100: 100 | R100: 1 | S100: 1346.4 | U100: https://www.1-cable.ru/models/13012-17.html | V100: 1-cable.ru карточка Klotz RC5-LB1: 4 пары (8 проводников) AWG26 (19×0,10мм голая медь, 0,15мм2), изоляция ПЭ с цветовой маркировкой IEC708, оплётка луж.медь 80%, оболочка PUR бордовая/чёрная, OD 6,3мм, S/UTP, 100МГц, для outdoor/DMX применений. Волновое сопротивление 100 Ом — типовое для Cat5e S/UTP, страницей отдельно не указано — решено агентом — проверить
...

Sheet БД.ОП-ТК
A1: КОД ОПЕРАЦИИ | B1: НАЗВАНИЕ | C1: ТИПОВЫЕ ДЕФЕКТЫ | D1: БЕЗОПАСНОСТЬ | E1: РЕВИЗИЯ | F1: ИЗМЕНЕНО | G1: КЕМ
A2: CUT_COAX+1strip | B2: Резка с разделкой | C2: ТИПОВЫЕ ДЕФЕКТЫ (Критерии отбраковки / NG) для резки и зачистки: Согласно IPC/WHMA-A-620F (класс 3) и КД, браком на данном этапе считаются: 1. Дефекты токопроводящей жилы (Самые критичные): Подрезка жил: Обрыв, глубокие надрезы или царапины на проволочках многопроволочной жилы (или на монолите) ножами станка. Приводит к занижению фактического сечения и перелому провода при вибрации. Распушение жил: Потеря исходной структуры скрутки жилы при стягивании изоляции. Распушенные проволочки не позволят качественно провести лужение или опрессовку (жилы не зайдут в терминал). Вытягивание жил: Нарушение шага скрутки жилы внутри провода из-за избыточного усилия стягивания изоляции (тупые ножи или неверный диаметр врезания). 2. Дефекты изоляции: Смятие изоляции: Профиль провода деформирован, сплющен или имеет глубокие следы (прокусы) от слишком сильного прижима подающих роликов станка. Рваный край изоляции: Срез неровный, имеет бахрому или заусенцы. Остатки изоляции: Изоляционная оболочка снята не полностью, на медных жилах остались фрагменты пластика, которые помешают электрическому контакту при опрессовке. 3. Отклонения геометрии: Длина зачистки вне допуска: Слишком короткая зачистка не обеспечит нужный вылет жил при опрессовке терминала, а слишком длинная приведет к оголению меди за пределами разъема (риск короткого замыкания). | D2: ВАЖНО! ТРЕБОВАНИЕ БЕЗОПАСНОСТИ: Все механические манипуляции по настройке, замене матриц, регулировке ножей и обслуживанию оборудования проводить исключительно в полностью обесточенном состоянии. В процессе работы использовать средства индивидуальной защиты (перчатки, защитные очки при пайке).
A3: CUT_COAX+2strip | B3: Резка с разделкой | C3: ТИПОВЫЕ ДЕФЕКТЫ (Критерии отбраковки / NG) для резки и зачистки: Согласно IPC/WHMA-A-620F (класс 3) и КД, браком на данном этапе считаются: 1. Дефекты токопроводящей жилы (Самые критичные): Подрезка жил: Обрыв, глубокие надрезы или царапины на проволочках многопроволочной жилы (или на монолите) ножами станка. Приводит к занижению фактического сечения и перелому провода при вибрации. Распушение жил: Потеря исходной структуры скрутки жилы при стягивании изоляции. Распушенные проволочки не позволят качественно провести лужение или опрессовку (жилы не зайдут в терминал). Вытягивание жил: Нарушение шага скрутки жилы внутри провода из-за избыточного усилия стягивания изоляции (тупые ножи или неверный диаметр врезания). 2. Дефекты изоляции: Смятие изоляции: Профиль провода деформирован, сплющен или имеет глубокие следы (прокусы) от слишком сильного прижима подающих роликов станка. Рваный край изоляции: Срез неровный, имеет бахрому или заусенцы. Остатки изоляции: Изоляционная оболочка снята не полностью, на медных жилах остались фрагменты пластика, которые помешают электрическому контакту при опрессовке. 3. Отклонения геометрии: Длина зачистки вне допуска: Слишком короткая зачистка не обеспечит нужный вылет жил при опрессовке терминала, а слишком длинная приведет к оголению меди за пределами разъема (риск короткого замыкания). | D3: ВАЖНО! ТРЕБОВАНИЕ БЕЗОПАСНОСТИ: Все механические манипуляции по настройке, замене матриц, регулировке ножей и обслуживанию оборудования проводить исключительно в полностью обесточенном состоянии. В процессе работы использовать средства индивидуальной защиты (перчатки, защитные очки при пайке).
A4: CUT_NEYLON | B4: Резка линейных материалов | C4: ТИПОВЫЕ ДЕФЕКТЫ (NG): распускание (расплетание) торца рукава (нет оплавления среза); пережим/деформация рукава; косой рез; несоответствие длины КД; чрезмерное оплавление (закрытие просвета). | D4: ВАЖНО! ТРЕБОВАНИЕ БЕЗОПАСНОСТИ: Все механические манипуляции по настройке, замене матриц, регулировке ножей и обслуживанию оборудования проводить исключительно в полностью обесточенном состоянии. В процессе работы использовать средства индивидуальной защиты (перчатки, защитные очки при пайке).
A5: CUT_TUT_long | B5: Резка линейных материалов | C5: ТИПОВЫЕ ДЕФЕКТЫ (NG): сплющивание (слипание стенок) трубки ТУТ; косой рез (неперпендикулярный); заусенцы/надрывы на торце; несоответствие длины КД; преждевременная усадка от нагрева. | D5: ВАЖНО! ТРЕБОВАНИЕ БЕЗОПАСНОСТИ: Все механические манипуляции по настройке, замене матриц, регулировке ножей и обслуживанию оборудования проводить исключительно в полностью обесточенном состоянии. В процессе работы использовать средства индивидуальной защиты (перчатки, защитные очки при пайке).
A6: CUT_TUT_short | B6: Резка | C6: ТИПОВЫЕ ДЕФЕКТЫ (Критерии отбраковки / NG) для резки ТУТ: В соответствии с требованиями к монтажу (опираясь на IPC/WHMA-A-620F по изоляционным материалам), отбраковке подлежат отрезки, имеющие следующие дефекты: 1. Дефекты кромок (Критично для ТУТ): Рваный край / Заусенцы: Неровный срез с бахромой (приводит к неравномерной усадке и риску пробоя изоляции). Продольные надрезы и микротрещины на торце: Недопустимы, так как при нагреве (усадке) трубка гарантированно порвется вдоль надреза. 2. Нарушение геометрии реза и профиля: Косой рез: Плоскость среза не перпендикулярна продольной оси трубки (угол отклонения превышает допустимый норматив, оголяя часть зоны, подлежащей изоляции). Сплющивание (слипание) трубки: Необратимая деформация профиля трубки механизмом подачи или тупым ножом, препятствующая свободному надеванию ТУТ на провод/контакт. 3. Габаритные отклонения: Длина вне допуска: Отрезок короче или длиннее заданного чертежом размера. (Слишком короткая ТУТ не обеспечит должного перекрытия изоляции, слишком длинная может налезть на контактную зону). | D6: ВАЖНО! ТРЕБОВАНИЕ БЕЗОПАСНОСТИ: Все механические манипуляции по настройке, замене матриц, регулировке ножей и обслуживанию оборудования проводить исключительно в полностью обесточенном состоянии. В процессе работы использовать средства индивидуальной защиты (перчатки, защитные очки при пайке).
A7: CUT_WIRE+1crimp | B7: Автомат резка + опрессовка | C7: ТИПОВЫЕ ДЕФЕКТЫ (Критерии отбраковки / NG) для резки и зачистки: Согласно IPC/WHMA-A-620F (класс 3) и КД, браком на данном этапе считаются: 1. Дефекты токопроводящей жилы (Самые критичные): Подрезка жил: Обрыв, глубокие надрезы или царапины на проволочках многопроволочной жилы (или на монолите) ножами станка. Приводит к занижению фактического сечения и перелому провода при вибрации. Распушение жил: Потеря исходной структуры скрутки жилы при стягивании изоляции. Распушенные проволочки не позволят качественно провести лужение или опрессовку (жилы не зайдут в терминал). Вытягивание жил: Нарушение шага скрутки жилы внутри провода из-за избыточного усилия стягивания изоляции (тупые ножи или неверный диаметр врезания). 2. Дефекты изоляции: Смятие изоляции: Профиль провода деформирован, сплющен или имеет глубокие следы (прокусы) от слишком сильного прижима подающих роликов станка. Рваный край изоляции: Срез неровный, имеет бахрому или заусенцы. Остатки изоляции: Изоляционная оболочка снята не полностью, на медных жилах остались фрагменты пластика, которые помешают электрическому контакту при опрессовке. 3. Отклонения геометрии: Длина зачистки вне допуска: Слишком короткая зачистка не обеспечит нужный вылет жил при опрессовке терминала, а слишком длинная приведет к оголению меди за пределами разъема (риск короткого замыкания). | D7: ВАЖНО! ТРЕБОВАНИЕ БЕЗОПАСНОСТИ: Все механические манипуляции по настройке, замене матриц, регулировке ножей и обслуживанию оборудования проводить исключительно в полностью обесточенном состоянии. В процессе работы использовать средства индивидуальной защиты (перчатки, защитные очки при пайке).
A8: CUT_WIRE+1strip | B8: Резка с разделкой | C8: ТИПОВЫЕ ДЕФЕКТЫ (Критерии отбраковки / NG) для резки и зачистки: Согласно IPC/WHMA-A-620F (класс 3) и КД, браком на данном этапе считаются: 1. Дефекты токопроводящей жилы (Самые критичные): Подрезка жил: Обрыв, глубокие надрезы или царапины на проволочках многопроволочной жилы (или на монолите) ножами станка. Приводит к занижению фактического сечения и перелому провода при вибрации. Распушение жил: Потеря исходной структуры скрутки жилы при стягивании изоляции. Распушенные проволочки не позволят качественно провести лужение или опрессовку (жилы не зайдут в терминал). Вытягивание жил: Нарушение шага скрутки жилы внутри провода из-за избыточного усилия стягивания изоляции (тупые ножи или неверный диаметр врезания). 2. Дефекты изоляции: Смятие изоляции: Профиль провода деформирован, сплющен или имеет глубокие следы (прокусы) от слишком сильного прижима подающих роликов станка. Рваный край изоляции: Срез неровный, имеет бахрому или заусенцы. Остатки изоляции: Изоляционная оболочка снята не полностью, на медных жилах остались фрагменты пластика, которые помешают электрическому контакту при опрессовке. 3. Отклонения геометрии: Длина зачистки вне допуска: Слишком короткая зачистка не обеспечит нужный вылет жил при опрессовке терминала, а слишком длинная приведет к оголению меди за пределами разъема (риск короткого замыкания). | D8: ВАЖНО! ТРЕБОВАНИЕ БЕЗОПАСНОСТИ: Все механические манипуляции по настройке, замене матриц, регулировке ножей и обслуживанию оборудования проводить исключительно в полностью обесточенном состоянии. В процессе работы использовать средства индивидуальной защиты (перчатки, защитные очки при пайке).
A9: CUT_WIRE+1strip+1mark | B9: Резка с разделкой+ маркировка | C9: ТИПОВЫЕ ДЕФЕКТЫ (Критерии отбраковки / NG) для резки и зачистки: Согласно IPC/WHMA-A-620F (класс 3) и КД, браком на данном этапе считаются: 1. Дефекты токопроводящей жилы (Самые критичные): Подрезка жил: Обрыв, глубокие надрезы или царапины на проволочках многопроволочной жилы (или на монолите) ножами станка. Приводит к занижению фактического сечения и перелому провода при вибрации. Распушение жил: Потеря исходной структуры скрутки жилы при стягивании изоляции. Распушенные проволочки не позволят качественно провести лужение или опрессовку (жилы не зайдут в терминал). Вытягивание жил: Нарушение шага скрутки жилы внутри провода из-за избыточного усилия стягивания изоляции (тупые ножи или неверный диаметр врезания). 2. Дефекты изоляции: Смятие изоляции: Профиль провода деформирован, сплющен или имеет глубокие следы (прокусы) от слишком сильного прижима подающих роликов станка. Рваный край изоляции: Срез неровный, имеет бахрому или заусенцы. Остатки изоляции: Изоляционная оболочка снята не полностью, на медных жилах остались фрагменты пластика, которые помешают электрическому контакту при опрессовке. 3. Отклонения геометрии: Длина зачистки вне допуска: Слишком короткая зачистка не обеспечит нужный вылет жил при опрессовке терминала, а слишком длинная приведет к оголению меди за пределами разъема (риск короткого замыкания). | D9: ВАЖНО! ТРЕБОВАНИЕ БЕЗОПАСНОСТИ: Все механические манипуляции по настройке, замене матриц, регулировке ножей и обслуживанию оборудования проводить исключительно в полностью обесточенном состоянии. В процессе работы использовать средства индивидуальной защиты (перчатки, защитные очки при пайке).
A10: CUT_WIRE+1strip+2mark | B10: Резка с разделкой+ маркировка | C10: ТИПОВЫЕ ДЕФЕКТЫ (Критерии отбраковки / NG) для резки и зачистки: Согласно IPC/WHMA-A-620F (класс 3) и КД, браком на данном этапе считаются: 1. Дефекты токопроводящей жилы (Самые критичные): Подрезка жил: Обрыв, глубокие надрезы или царапины на проволочках многопроволочной жилы (или на монолите) ножами станка. Приводит к занижению фактического сечения и перелому провода при вибрации. Распушение жил: Потеря исходной структуры скрутки жилы при стягивании изоляции. Распушенные проволочки не позволят качественно провести лужение или опрессовку (жилы не зайдут в терминал). Вытягивание жил: Нарушение шага скрутки жилы внутри провода из-за избыточного усилия стягивания изоляции (тупые ножи или неверный диаметр врезания). 2. Дефекты изоляции: Смятие изоляции: Профиль провода деформирован, сплющен или имеет глубокие следы (прокусы) от слишком сильного прижима подающих роликов станка. Рваный край изоляции: Срез неровный, имеет бахрому или заусенцы. Остатки изоляции: Изоляционная оболочка снята не полностью, на медных жилах остались фрагменты пластика, которые помешают электрическому контакту при опрессовке. 3. Отклонения геометрии: Длина зачистки вне допуска: Слишком короткая зачистка не обеспечит нужный вылет жил при опрессовке терминала, а слишком длинная приведет к оголению меди за пределами разъема (риск короткого замыкания). | D10: ВАЖНО! ТРЕБОВАНИЕ БЕЗОПАСНОСТИ: Все механические манипуляции по настройке, замене матриц, регулировке ножей и обслуживанию оборудования проводить исключительно в полностью обесточенном состоянии. В процессе работы использовать средства индивидуальной защиты (перчатки, защитные очки при пайке).
A11: CUT_WIRE+2crimp | B11: Автомат резка + опрессовка | C11: ТИПОВЫЕ ДЕФЕКТЫ (Критерии отбраковки / NG) для резки и зачистки: Согласно IPC/WHMA-A-620F (класс 3) и КД, браком на данном этапе считаются: 1. Дефекты токопроводящей жилы (Самые критичные): Подрезка жил: Обрыв, глубокие надрезы или царапины на проволочках многопроволочной жилы (или на монолите) ножами станка. Приводит к занижению фактического сечения и перелому провода при вибрации. Распушение жил: Потеря исходной структуры скрутки жилы при стягивании изоляции. Распушенные проволочки не позволят качественно провести лужение или опрессовку (жилы не зайдут в терминал). Вытягивание жил: Нарушение шага скрутки жилы внутри провода из-за избыточного усилия стягивания изоляции (тупые ножи или неверный диаметр врезания). 2. Дефекты изоляции: Смятие изоляции: Профиль провода деформирован, сплющен или имеет глубокие следы (прокусы) от слишком сильного прижима подающих роликов станка. Рваный край изоляции: Срез неровный, имеет бахрому или заусенцы. Остатки изоляции: Изоляционная оболочка снята не полностью, на медных жилах остались фрагменты пластика, которые помешают электрическому контакту при опрессовке. 3. Отклонения геометрии: Длина зачистки вне допуска: Слишком короткая зачистка не обеспечит нужный вылет жил при опрессовке терминала, а слишком длинная приведет к оголению меди за пределами разъема (риск короткого замыкания). | D11: ВАЖНО! ТРЕБОВАНИЕ БЕЗОПАСНОСТИ: Все механические манипуляции по настройке, замене матриц, регулировке ножей и обслуживанию оборудования проводить исключительно в полностью обесточенном состоянии. В процессе работы использовать средства индивидуальной защиты (перчатки, защитные очки при пайке).
A12: CUT_WIRE+2strip | B12: Резка с разделкой | C12: ТИПОВЫЕ ДЕФЕКТЫ (Критерии отбраковки / NG) для резки и зачистки: Согласно IPC/WHMA-A-620F (класс 3) и КД, браком на данном этапе считаются: 1. Дефекты токопроводящей жилы (Самые критичные): Подрезка жил: Обрыв, глубокие надрезы или царапины на проволочках многопроволочной жилы (или на монолите) ножами станка. Приводит к занижению фактического сечения и перелому провода при вибрации. Распушение жил: Потеря исходной структуры скрутки жилы при стягивании изоляции. Распушенные проволочки не позволят качественно провести лужение или опрессовку (жилы не зайдут в терминал). Вытягивание жил: Нарушение шага скрутки жилы внутри провода из-за избыточного усилия стягивания изоляции (тупые ножи или неверный диаметр врезания). 2. Дефекты изоляции: Смятие изоляции: Профиль провода деформирован, сплющен или имеет глубокие следы (прокусы) от слишком сильного прижима подающих роликов станка. Рваный край изоляции: Срез неровный, имеет бахрому или заусенцы. Остатки изоляции: Изоляционная оболочка снята не полностью, на медных жилах остались фрагменты пластика, которые помешают электрическому контакту при опрессовке. 3. Отклонения геометрии: Длина зачистки вне допуска: Слишком короткая зачистка не обеспечит нужный вылет жил при опрессовке терминала, а слишком длинная приведет к оголению меди за пределами разъема (риск короткого замыкания). | D12: ВАЖНО! ТРЕБОВАНИЕ БЕЗОПАСНОСТИ: Все механические манипуляции по настройке, замене матриц, регулировке ножей и обслуживанию оборудования проводить исключительно в полностью обесточенном состоянии. В процессе работы использовать средства индивидуальной защиты (перчатки, защитные очки при пайке).
A13: CUT_WIRE+2strip+1mark | B13: Резка с разделкой+ маркировка | C13: ТИПОВЫЕ ДЕФЕКТЫ (Критерии отбраковки / NG) для резки и зачистки: Согласно IPC/WHMA-A-620F (класс 3) и КД, браком на данном этапе считаются: 1. Дефекты токопроводящей жилы (Самые критичные): Подрезка жил: Обрыв, глубокие надрезы или царапины на проволочках многопроволочной жилы (или на монолите) ножами станка. Приводит к занижению фактического сечения и перелому провода при вибрации. Распушение жил: Потеря исходной структуры скрутки жилы при стягивании изоляции. Распушенные проволочки не позволят качественно провести лужение или опрессовку (жилы не зайдут в терминал). Вытягивание жил: Нарушение шага скрутки жилы внутри провода из-за избыточного усилия стягивания изоляции (тупые ножи или неверный диаметр врезания). 2. Дефекты изоляции: Смятие изоляции: Профиль провода деформирован, сплющен или имеет глубокие следы (прокусы) от слишком сильного прижима подающих роликов станка. Рваный край изоляции: Срез неровный, имеет бахрому или заусенцы. Остатки изоляции: Изоляционная оболочка снята не полностью, на медных жилах остались фрагменты пластика, которые помешают электрическому контакту при опрессовке. 3. Отклонения геометрии: Длина зачистки вне допуска: Слишком короткая зачистка не обеспечит нужный вылет жил при опрессовке терминала, а слишком длинная приведет к оголению меди за пределами разъема (риск короткого замыкания). | D13: ВАЖНО! ТРЕБОВАНИЕ БЕЗОПАСНОСТИ: Все механические манипуляции по настройке, замене матриц, регулировке ножей и обслуживанию оборудования проводить исключительно в полностью обесточенном состоянии. В процессе работы использовать средства индивидуальной защиты (перчатки, защитные очки при пайке).
... A108: US_WELD | B108: УЗ сварка | C108: ТИПОВЫЕ ДЕФЕКТЫ (Критерии отбраковки / NG) со ссылками на IPC/WHMA-A-620F: 1. Дефекты структуры и монолитности металлоблока (Раздел 8.2): Недовар (Недостаточная энергия / давление): Металлоблок не сформирован до конца, под увеличением видны явные зазоры между отдельными проволочками, либо отдельные жилы отделяются от сростка при незначительном механическом усилии (Критический брак). Перевар / Пережог (Избыточная энергия): Чрезмерное сплющивание узла. Толщина металлоблока занижена, по бокам образовался сильный облой (выдавленный тонкий металл). Из-за деструкции меди в зоне сварки резко падает механическое усилие на разрыв. Трещины в сростке: Наличие сквозных или поверхностных микротрещин на теле металлоблока (следствие износа сонотрода или неверной частоты колебаний). 2. Дефекты позиционирования проводников (Раздел 8.1 / 8.2): Распушение жил: Отдельные проволочки на входе в металлоблок выбились из общего пучка, не попали под действие сонотрода и торчат в стороны. Снижает рабочее сечение узла. Неверный вылет жил: Торцы проводов не выходят за край металлоблока (утоплены внутри шва), либо длина вылета жил превышает 1,5 мм, нарушая габариты последующей изоляции узла. Перекрещивание проводников: Жилы внутри пакета были уложены крест-накрест. Приводит к перебиванию и подрезанию отдельных проволочек в процессе прессования. 3. Термические и сопутствующие дефекты: Повреждение изоляции: Штатная оболочка провода зашла под прижимной механизм или сонотрод и имеет следы оплавления, обгорания или глубоких механических надрезов. Недопустимый зазор до изоляции: Оголенный участок жил от края металлоблока до начала изоляции провода превышает 1,5 мм (если иное не оговорено в КД), что увеличивает габариты незащищенной зоны. | D108: ВАЖНО! ТРЕБОВАНИЕ БЕЗОПАСНОСТИ: Все механические манипуляции по настройке, замене матриц, регулировке ножей и обслуживанию оборудования проводить исключительно в полностью обесточенном состоянии. В процессе работы использовать средства индивидуальной защиты (перчатки, защитные очки при пайке).

Sheet БД.ШАГИ
A1: КОД ОПЕРАЦИИ | B1: № | C1: ТИП | D1: ТЕКСТ | E1: ДОПУСК
A2: CUT_COAX+1strip | B2: 1 | C2: Операция | D2: Включить станок. Произвести заправку провода через систему рихтовки (выравнивания) и подающие ролики. | E2: -
A3: CUT_COAX+1strip | B3: 2 | C3: Операция | D3: Ввести параметры многоступенчатой разделки коаксиала: общую длину реза и длины ступеней (внешняя оболочка / экран / диэлектрик) по КД, усилие прижима роликов. Контролировать целостность экрана и диэлектрика. | E3: -
A4: CUT_COAX+1strip | B4: 3 | C4: Операция | D4: Режим многоступенчатой разделки: полное/частичное снятие по ступеням (внешняя оболочка → экран → диэлектрик) для стороны А. Контролировать целостность экрана и диэлектрика. | E4: -
A5: CUT_COAX+1strip | B5: 4 | C5: Операция | D5: Произвести тестовый рез (2–3 шт.). | E5: -
A6: CUT_COAX+1strip | B6: 5 | C6: Контроль | D6: ВИЗУАЛЬНЫЙ КОНТРОЛЬ (IPC разд.13): ступени разделки по КД; центральная жила без надрезов; диэлектрик без задиров (Ø сохранён); экран без бахромы и распушения, не касается жилы. | E6: IPC/WHMA-A-620F (Раздел 3)
A7: CUT_COAX+1strip | B7: 6 | C7: Контроль | D7: ИНСТРУМЕНТАЛЬНЫЙ КОНТРОЛЬ: Измерить общую длину отрезков линейкой. Измерить длину зачистки с каждой обрабатываемой стороны штангенциркулем. | E7: IPC/WHMA-A-620F (Раздел 3)
A8: CUT_COAX+1strip | B8: 7 | C8: Операция | D8: При положительном результате запустить автоматический цикл резки партии. | E8: -
A9: CUT_COAX+1strip | B9: 8 | C9: Операция | D9: Снять готовую партию. Уложить в тару без перегибов. Если применялось полное снятие изоляции, укладывать предельно аккуратно, чтобы исключить распушение жил от трения друг о друга. | E9: -
A10: CUT_COAX+1strip | B10: 9 | C10: Контроль | D10: Проводить выборочный межоперационный контроль длины и качества зачистки. | E10: IPC/WHMA-A-620F (Раздел 3)
A11: CUT_COAX+2strip | B11: 1 | C11: Операция | D11: Включить станок. Произвести заправку провода через систему рихтовки (выравнивания) и подающие ролики. | E11: -
A12: CUT_COAX+2strip | B12: 2 | C12: Операция | D12: Ввести параметры многоступенчатой разделки коаксиала: общую длину реза и длины ступеней (внешняя оболочка / экран / диэлектрик) по КД, усилие прижима роликов. Контролировать целостность экрана и диэлектрика. | E12: -
... A715: US_WELD | B715: 9 | C715: Операция | D715: Уложить спаянные узлы в антистатическую тару с ячейками для предотвращения механических повреждений пинов. | E715: -

Sheet БД.ОП-ОБ
A1: КОД ОПЕРАЦИИ | B1: РАЗДЕЛ | C1: № | D1: НАИМЕНОВАНИЕ | E1: ИНВ. НОМЕР | F1: № ПРОГ. | G1: ПАРАМЕТРЫ | H1: НОРМА | I1: ЕД. ИЗМ.
A2: CUT_COAX+1strip | B2: Инструмент | C2: 1 | D2: Линейка металлическая ГОСТ 427-75
A3: CUT_COAX+1strip | B3: Инструмент | C3: 2 | D3: Рулетка измерительная металлическая ГОСТ 7502-98
A4: CUT_COAX+1strip | B4: Оборудование | C4: 1 | D4: BZW-886+Q2 | Станок резки провода с роторной зачисткой мал. — кабель Ø до 5,5 мм | E4: ОБ.094 | F4: -
A5: CUT_COAX+1strip | B5: Оборудование | C5: 2 | D5: BZW-50X | Станок резки провода с роторной зачисткой больш. — кабель Ø свыше 5,5 мм | E5: ОБ.095 | F5: -
A6: CUT_COAX+2strip | B6: Инструмент | C6: 1 | D6: Линейка металлическая ГОСТ 427-75
A7: CUT_COAX+2strip | B7: Инструмент | C7: 2 | D7: Рулетка измерительная металлическая ГОСТ 7502-98
A8: CUT_COAX+2strip | B8: Оборудование | C8: 1 | D8: BZW-886+Q2 | Станок резки провода с роторной зачисткой мал. — кабель Ø до 5,5 мм | E8: ОБ.094 | F8: -
A9: CUT_COAX+2strip | B9: Оборудование | C9: 2 | D9: BZW-50X | Станок резки провода с роторной зачисткой больш. — кабель Ø свыше 5,5 мм | E9: ОБ.095 | F9: -
A10: CUT_NEYLON | B10: Инструмент | C10: 1 | D10: Линейка металлическая ГОСТ 427-75
A11: CUT_NEYLON | B11: Инструмент | C11: 2 | D11: Штангенциркуль ШЦ-I (ГОСТ 166-89)
A12: CUT_NEYLON | B12: Оборудование | C12: 1 | D12: BZW-200+H | Станок резки нейлоновых оплёток | E12: ОБ.096 | F12: -
A13: CUT_TUT_long | B13: Инструмент | C13: 1 | D13: Линейка металлическая ГОСТ 427-75
A14: CUT_TUT_long | B14: Инструмент | C14: 2 | D14: Штангенциркуль ШЦ-I (ГОСТ 166-89)
A15: CUT_TUT_long | B15: Оборудование | C15: 1 | D15: Автомат мерной резки гофрированных и термоусаживаемых трубок | E15: ОБ.018 | F15: -
A16: CUT_TUT_short | B16: Инструмент | C16: 1 | D16: Линейка металлическая ГОСТ 427-75
A17: CUT_TUT_short | B17: Инструмент | C17: 2 | D17: Штангенциркуль ШЦ-I (ГОСТ 166-89)
A18: CUT_TUT_short | B18: Оборудование | C18: 1 | D18: Автомат мерной резки гофрированных и термоусаживаемых трубок | E18: ОБ.018 | F18: -
A19: CUT_WIRE+1crimp | B19: Инструмент | C19: 1 | D19: Линейка металлическая ГОСТ 427-75
A20: CUT_WIRE+1crimp | B20: Инструмент | C20: 2 | D20: Рулетка измерительная металлическая ГОСТ 7502-98
A21: CUT_WIRE+1crimp | B21: Оборудование | C21: 1 | D21: BZW-2.0 | Станок резки/ обжим+обжим | E21: ОБ.097 | F21: -
A22: CUT_WIRE+1strip | B22: Инструмент | C22: 1 | D22: Линейка металлическая ГОСТ 427-75
A23: CUT_WIRE+1strip | B23: Инструмент | C23: 2 | D23: Рулетка измерительная металлическая ГОСТ 7502-98
A24: CUT_WIRE+1strip | B24: Оборудование | C24: 1 | D24: EW-05F+M | Автомат мерной резки проводов | E24: ОБ.015 | F24: -
A25: CUT_WIRE+1strip+1mark | B25: Инструмент | C25: 1 | D25: Линейка металлическая ГОСТ 427-75
A26: CUT_WIRE+1strip+1mark | B26: Инструмент | C26: 2 | D26: Рулетка измерительная металлическая ГОСТ 7502-98
A27: CUT_WIRE+1strip+1mark | B27: Оборудование | C27: 1 | D27: EW-3185+L | Автомат мерной резки и маркировки проводов | E27: ОБ.019 | F27: -
A28: CUT_WIRE+1strip+2mark | B28: Инструмент | C28: 1 | D28: Линейка металлическая ГОСТ 427-75
A29: CUT_WIRE+1strip+2mark | B29: Инструмент | C29: 2 | D29: Рулетка измерительная металлическая ГОСТ 7502-98
A30: CUT_WIRE+1strip+2mark | B30: Оборудование | C30: 1 | D30: EW-3185+L | Автомат мерной резки и маркировки проводов | E30: ОБ.019 | F30: -
A31: CUT_WIRE+2crimp | B31: Инструмент | C31: 1 | D31: Линейка металлическая ГОСТ 427-75
A32: CUT_WIRE+2crimp | B32: Инструмент | C32: 2 | D32: Рулетка измерительная металлическая ГОСТ 7502-98
A33: CUT_WIRE+2crimp | B33: Оборудование | C33: 1 | D33: BZW-2.0 | Станок резки/ обжим+обжим | E33: ОБ.097 | F33: -
A34: CUT_WIRE+2strip | B34: Инструмент | C34: 1 | D34: Линейка металлическая ГОСТ 427-75
A35: CUT_WIRE+2strip | B35: Инструмент | C35: 2 | D35: Рулетка измерительная металлическая ГОСТ 7502-98
A36: CUT_WIRE+2strip | B36: Оборудование | C36: 1 | D36: EW-05F+M | Автомат мерной резки проводов | E36: ОБ.015 | F36: -
A37: CUT_WIRE+2strip+1mark | B37: Инструмент | C37: 1 | D37: Линейка металлическая ГОСТ 427-75
A38: CUT_WIRE+2strip+1mark | B38: Инструмент | C38: 2 | D38: Рулетка измерительная металлическая ГОСТ 7502-98
A39: CUT_WIRE+2strip+1mark | B39: Оборудование | C39: 1 | D39: EW-3185+L | Автомат мерной резки и маркировки проводов | E39: ОБ.019 | F39: -
A40: CUT_WIRE+2strip+2mark | B40: Инструмент | C40: 1 | D40: Линейка металлическая ГОСТ 427-75
A41: CUT_WIRE+2strip+2mark | B41: Инструмент | C41: 2 | D41: Рулетка измерительная металлическая ГОСТ 7502-98
A42: CUT_WIRE+2strip+2mark | B42: Оборудование | C42: 1 | D42: EW-3185+L | Автомат мерной резки и маркировки проводов | E42: ОБ.019 | F42: -
A43: CUT_WIRE_auto | B43: Инструмент | C43: 1 | D43: Линейка металлическая ГОСТ 427-75
A44: CUT_WIRE_auto | B44: Инструмент | C44: 2 | D44: Рулетка измерительная металлическая ГОСТ 7502-98
A45: CUT_WIRE_auto | B45: Оборудование | C45: 1 | D45: EW-05F+M | Автомат мерной резки проводов | E45: ОБ.015 | F45: -
A46: CUT_WIRE_hand | B46: Инструмент | C46: 1 | D46: Линейка металлическая ГОСТ 427-75
A47: CUT_WIRE_hand | B47: Инструмент | C47: 2 | D47: Рулетка измерительная металлическая ГОСТ 7502-98
A48: CUT_WIRE_hand | B48: Оборудование | C48: 1 | D48: EW-05F+M | Автомат мерной резки проводов | E48: ОБ.015 | F48: -
A49: CUT_ПМЛ | B49: Инструмент | C49: 1 | D49: Линейка металлическая ГОСТ 427-75
A50: CUT_ПМЛ | B50: Инструмент | C50: 2 | D50: Штангенциркуль ШЦ-I (ГОСТ 166-89)
A51: CUT_ПМЛ | B51: Оборудование | C51: 1 | D51: Автомат мерной резки гофрированных и термоусаживаемых трубок | E51: ОБ.018 | F51: -
A52: CUT_гофра | B52: Инструмент | C52: 1 | D52: Линейка металлическая ГОСТ 427-75
A53: CUT_гофра | B53: Инструмент | C53: 2 | D53: Штангенциркуль ШЦ-I (ГОСТ 166-89)
A54: CUT_гофра | B54: Оборудование | C54: 1 | D54: Автомат мерной резки гофрированных и термоусаживаемых трубок | E54: ОБ.018 | F54: -
A55: HEAT_TTK_long | B55: Инструмент | C55: 1 | D55: Линейка металлическая ГОСТ 427-75
A56: HEAT_TTK_long | B56: Оборудование | C56: 1 | D56: 8620DX-Pro(R) | Станция паяльная термовоздушная | E56: ОБ.070.X
A57: HEAT_TTK_short | B57: Инструмент | C57: 1 | D57: Линейка металлическая ГОСТ 427-75
A58: HEAT_TTK_short | B58: Оборудование | C58: 1 | D58: 8620DX-Pro(R) | Станция паяльная термовоздушная | E58: ОБ.070.X
A59: HEAT_TYT_long | B59: Инструмент | C59: 1 | D59: Линейка металлическая ГОСТ 427-75
A60: HEAT_TYT_long | B60: Оборудование | C60: 1 | D60: 8620DX-Pro(R) | Станция паяльная термовоздушная | E60: ОБ.070.X
A61: HEAT_TYT_short | B61: Инструмент | C61: 1 | D61: Линейка металлическая ГОСТ 427-75
A62: HEAT_TYT_short | B62: Оборудование | C62: 1 | D62: 8620DX-Pro(R) | Станция паяльная термовоздушная | E62: ОБ.070.X
A63: INS_BRAID | B63: Инструмент | C63: 1 | D63: Ножницы; линейка металлическая 300 мм; 8620DX-Pro(R) станция термовоздушная (оплавление торцов оплётки) | E63: ОБ.070.X
A64: INS_MARK_HARNESS | B64: Инструмент | C64: 1 | D64: Пинцет; линейка металлическая 300 мм
A65: INS_RJ_cat5 | B65: Инструмент | C65: 1 | D65: Пинцет монтажный антистатический
A66: INS_RJ_cat5 | B66: Инструмент | C66: 2 | D66: Обжимной инструмент (кримпер) для вилок 8P8C / RJ45
A67: INS_RJ_cat6/7 | B67: Инструмент | C67: 1 | D67: Пинцет монтажный антистатический
A68: INS_RJ_cat6/7 | B68: Инструмент | C68: 2 | D68: Обжимной инструмент (кримпер) для вилок 8P8C / RJ45
A69: INS_WRAP | B69: Инструмент | C69: 1 | D69: Ножницы; линейка металлическая 300 мм
A70: INS_housing_COAX | B70: Инструмент | C70: 1 | D70: Пинцет антистатический
A71: INS_housing_DB/DH/СНП | B71: Инструмент | C71: 1 | D71: Пинцет антистатический
A72: INS_housing_GX | B72: Инструмент | C72: 1 | D72: Пинцет антистатический
A73: INS_housing_USB | B73: Инструмент | C73: 1 | D73: Пинцет антистатический
A74: INS_terminal_1.00 | B74: Инструмент | C74: 1 | D74: Пинцет монтажный антистатический
A75: INS_terminal_1.00 | B75: Инструмент | C75: 2 | D75: Экстрактор
... A83: INS_terminal_2,54-6,3 | B83: Инструмент | C83: 2 | D83: Экстрактор
A84: PRS_CAP | B84: Оборудование | C84: 1 | D84: WL-IDC | Пресс пневматический для опрессовки разъемов | E84: ОБ.004
A85: PRS_CAP | B85: Матрицы | C85: 1 | D85: Шестигранные матрицы
A86: PRS_CAP | B86: Инструмент | C86: 1 | D86: Штангенциркуль ШЦ-I (ГОСТ 166-89)
A87: PRS_CAP_COAX | B87: Оборудование | C87: 1 | D87: WL-IDC | Пресс пневматический для опрессовки разъемов | E87: ОБ.004
A88: PRS_CAP_COAX | B88: Оснастка | C88: 1 | D88: Оснастка для центровки углового разъёма (по типоразмеру)
A89: PRS_CAP_COAX | B89: Инструмент | C89: 1 | D89: Штангенциркуль ШЦ-I (ГОСТ 166-89)
A90: PRS_COPPER | B90: Оборудование | C90: 1 | D90: ‹наименование оборудования›
A91: PRS_COPPER | B91: Матрицы | C91: 1 | D91: Шестигранные матрицы
A92: PRS_COPPER | B92: Инструмент | C92: 1 | D92: Штангенциркуль ШЦ-I (ГОСТ 166-89)
A93: PRS_HKИ/НВИ/РПИ | B93: Инструмент | C93: 1 | D93: EW-2550 | Прибор для измерения высоты опрессовки (микрометр) | E93: ОБ.034.2
A94: PRS_HKИ/НВИ/РПИ | B94: Инструмент | C94: 2 | D94: EW-2510 | Машина испытательная разрывная | E94: ОБ.033.2
A95: PRS_HKИ/НВИ/РПИ | B95: Оборудование | C95: 1 | D95: SR-16M | Пресс пневматический для опрессовки кабельных контактов и наконечников | E95: ОБ.006.1
A96: PRS_IDC | B96: Оборудование | C96: 1 | D96: WL-IDC | Пресс пневматический для опрессовки разъемов | E96: ОБ.004
A97: PRS_IDC | B97: Матрицы | C97: 1 | D97: Шестигранные матрицы
A98: PRS_IDC | B98: Инструмент | C98: 1 | D98: Штангенциркуль ШЦ-I (ГОСТ 166-89)
A99: PRS_MHF | B99: Оборудование | C99: 1 | D99: PRS-MHF1/4 | Опрессовка MHF1 | E99: по кабелю: ОБ.024.2 (MHF-4, 1.37) / ОБ.024.4 (MHF-1, 1.78) / ОБ.024.3 (MHF-1)
A100: PRS_MHF | B100: Матрицы | C100: 1 | D100: Шестигранные матрицы
A101: PRS_MHF | B101: Инструмент | C101: 1 | D101: Штангенциркуль ШЦ-I (ГОСТ 166-89)
A102: PRS_MHF_LK | B102: Оборудование | C102: 1 | D102: PRS-MHF1/4-LK | Опрессовка MHF1 LK | E102: ОБ.024.1
A103: PRS_MHF_LK | B103: Матрицы | C103: 1 | D103: Шестигранные матрицы
A104: PRS_MHF_LK | B104: Инструмент | C104: 1 | D104: Штангенциркуль ШЦ-I (ГОСТ 166-89)
A105: PRS_SLEEVE_coax | B105: Оборудование | C105: 1 | D105: SR-16M | Пресс пневматический для опрессовки кабельных контактов и наконечников | E105: ОБ.006.1
A106: PRS_SLEEVE_coax | B106: Матрицы | C106: 1 | D106: Шестигранные матрицы
A107: PRS_SLEEVE_coax | B107: Инструмент | C107: 1 | D107: Штангенциркуль ШЦ-I (ГОСТ 166-89)
...

Sheet _TC_TECHOPS_META
A1: key | B1: value
A2: sourceSpreadsheetId | B2: 1W3VK9Fw71lYdw1Klcsn_za5-2EhvLoXIAKZVYOCnKcs
A3: updatedAt | B3: 2026-09-29T08:25:10.558Z
A4: recordCount | B4: 1043
A5: countsByTabJson | B5: {"ob":192,"op":139,"ter":528,"coax":184}
A6: diagnosticsByTabJson | B6: {"ob":{"label":"БД.ОБ","sourceSheetName":"БД.ОБ","headerRowNumber":2,"foundHeaders":["№","Тип","Инв. номер","Артикул","Наменование","Производитель","Операции","Потребление,вват/ч","Ссылка на сайт производителя","Расположение","Описание","Для базы","Полное наименование","Стоимость","Коэффициент","Cрок окупаемости, мес.","Кол-во сек. работы в мес.","Желаемый срок окупаемости, сек.","Стоимость 1 сек. эксплуатации без НДС","Габариты\nШхД"],"matchedGroups":["для базы"],"missingGroups":[],"parsedRows":192,"sheetFound":true},"op":{"label":"БД.ОП","sourceSheetName":"БД.ОП","headerRowNumber":2,"foundHeaders":["Номер","Название","Апликаторы / модули","Программа","Машина","Полуфабрикат","Провод","Разъем","Инструмент","Время Операции","Время подготовки, сек","Расход на настройку м; шт;","Время Чел, сек/оп; сек/м","Время машины, сек/оп; сек/м","Уд.Цена ЧЛ, сек","Уд.Цена ЧЛ_МАГ, сек","Уд.Цена МШ, сек","Тип операции","Время ручных работ для взятия полуфабриката","Время ручных работ","Время ручных работ для снятия полуфабриката","Скорость проката, сек/м","Скорость работы инструмента","Кол-во операций инструмента","Время доп.операции","Инструкция","Отказы"],"matchedGroups":["номер","название","время операции","время подготовки, сек","время машины, сек/оп; сек/м","тип операции"],"missingGroups":[],"parsedRows":139,"sheetFound":true},"ter":{"label":"БД.ТЕР","sourceSheetName":"БД.ТЕР","headerRowNumber":1,"foundHeaders":["Тип\nразъема","Производитель","Product Name","Series","Шаг\nразьема","Тип\n контакта","Артикул\n контакта (REEL)","Артикул\n контакта (BAG)","Аппликатор","Пневма\nАвтомат","ОТР","С зачисткой","Длина зачистки, мм","L+","L-","Высота обжима проводника , мм","Высота обжима изоляции, мм","Усилие обрыва контакта, N","От AWG","До AWG","От мм2","До мм2","Диаметр изоляции от, мм","Диаметр изоляции до, мм","Материал контакта","Максисмальная сила тока, А","Ссылка на DATASHEET на сайте производителя","Источник высоты обжима"],"matchedGroups":["product name","series","производитель","тип разъёма"],"missingGroups":[],"parsedRows":528,"sheetFound":true},"coax":{"label":"БД.КОАКС","sourceSheetName":"БД.КОАКС","headerRowNumber":2,"foundHeaders":["Артикул","Тип/Серия","Провод","Производитель","Программа","D1","D2","D3","L1","L2","L3","L+","L-","Тип пина","Тип экрана"],"matchedGroups":["артикул","тип/серия","производитель","провод","программа"],"missingGroups":["поставщик"],"parsedRows":184,"sheetFound":true}}
A7: schemaVersion | B7: 14
A8: columnHeadersByTabJson | B8: {"ob":["№","Тип","Инв. номер","Артикул","Наменование","Производитель","Операции","Потребление,вват/ч","Ссылка на сайт производителя","Расположение","Описание","Для базы","Полное наименование","Стоимость","Коэффициент","Cрок окупаемости, мес.","Кол-во сек. работы в мес.","Желаемый срок окупаемости, сек.","Стоимость 1 сек. эксплуатации без НДС","Габариты\nШхД"],"op":["Номер","Название","Апликаторы / модули","Программа","Машина","Полуфабрикат","Провод","Разъем","Инструмент","Время Операции","Время подготовки, сек","Расход на настройку м; шт;","Время Чел, сек/оп; сек/м","Время машины, сек/оп; сек/м","Уд.Цена ЧЛ, сек","Уд.Цена ЧЛ_МАГ, сек","Уд.Цена МШ, сек","Тип операции","Время ручных работ для взятия полуфабриката","Время ручных работ","Время ручных работ для снятия полуфабриката","Скорость проката, сек/м","Скорость работы инструмента","Кол-во операций инструмента","Время доп.операции","Инструкция","Отказы"],"ter":["Тип\nразъема","Производитель","Product Name","Series","Шаг\nразьема","Тип\n контакта","Артикул\n контакта (REEL)","Артикул\n контакта (BAG)","Аппликатор","Пневма\nАвтомат","ОТР","С зачисткой","Длина зачистки, мм","L+","L-","Высота обжима проводника , мм","Высота обжима изоляции, мм","Усилие обрыва контакта, N","От AWG","До AWG","От мм2","До мм2","Диаметр изоляции от, мм","Диаметр изоляции до, мм","Материал контакта","Максисмальная сила тока, А","Ссылка на DATASHEET на сайте производителя","Источник высоты обжима"],"coax":["Артикул","Тип/Серия","Провод","Производитель","Программа","D1","D2","D3","L1","L2","L3","L+","L-","Тип пина","Тип экрана"]}

Sheet _TC_TECHOPS_DB
A1: tabKey | B1: displayText | C1: normalizedSearch | D1: exportJson | E1: sourceSheet | F1: sortKey | G1: extra1 | H1: extra2 | I1: extra3 | J1: extra4 | K1: extra5 | L1: extra6 | M1: extra7 | N1: extra8 | O1: extra9 | P1: extra10 | Q1: extra11 | R1: extra12 | S1: extra13
A2: ob | B2: / | C2: / | D2: ["190","","","","","","","","","","","/","","","","","","","",""] | E2: БД.ОБ | F2: /
A3: ob | B3: / | C3: / | D3: ["191","","","","","","","","","","","/","","","","","","","",""] | E3: БД.ОБ | F3: /
A4: ob | B4: / | C4: / | D4: ["192","","","","","","","","","","","/","","","","","","","",""] | E4: БД.ОБ | F4: /
A5: ob | B5: /Автомобильный набор инструментов | C5: /автомобильныйнаборинструментов | D5: ["14","Инструмент","ОБ.066","","Автомобильный набор инструментов","Jonnesway","","","","Цар","","/Автомобильный набор инструментов","","35 000,00","1,0","12","514 800","6 177 600,00","0,006",""] | E5: БД.ОБ | F5: Инструмент /Автомобильный набор инструментов | G5: Инструмент
A6: ob | B6: /Газовый паяльник | C6: /газовыйпаяльник | D6: ["11","Инструмент","ОБ.062","","Газовый паяльник","Dremel","Пайка","","","Цар","","/Газовый паяльник","","7 500,00","1,0","12","514 800","6 177 600,00","0,001",""] | E6: БД.ОБ | F6: Инструмент /Газовый паяльник | G6: Инструмент
A7: ob | B7: /Дремель | C7: /дремель | D7: ["12","Инструмент","ОБ.064","","Дремель","Dremel","","","","Цар","","/Дремель","","8 500,00","1,0","12","514 800","6 177 600,00","0,001",""] | E7: БД.ОБ | F7: Инструмент /Дремель | G7: Инструмент
A8: ob | B8: /Метчики | C8: /метчики | D8: ["16","Инструмент","ОБ.077","","Метчики","TOPEX","","500","","Цар","","/Метчики","","3 000,00","1,0","12","514 800","6 177 600,00","0,000",""] | E8: БД.ОБ | F8: Инструмент /Метчики | G8: Инструмент
A9: ob | B9: /Набор герметичных разъёмов с обжимкой | C9: /наборгерметичныхразъёмовсобжимкой | D9: ["15","Инструмент","ОБ.067","","Набор герметичных разъёмов с обжимкой","--------------------------","","","","Цар","","/Набор герметичных разъёмов с обжимкой","","","1,0","12","514 800","6 177 600,00","0,000",""] | E9: БД.ОБ | F9: Инструмент /Набор герметичных разъёмов с обжимкой | G9: Инструмент
A10: ob | B10: /Набор метчиков | C10: /наборметчиков | D10: ["21","Инструмент","ОБ.085","","Набор метчиков","","","","","Цар","","/Набор метчиков","","2 000,00","1,0","12","514 800","6 177 600,00","0,000",""] | E10: БД.ОБ | F10: Инструмент /Набор метчиков | G10: Инструмент
A11: ob | B11: /Ударная отвёртка | C11: /ударнаяотвёртка | D11: ["13","Инструмент","ОБ.065","","Ударная отвёртка","Kraftool","","","","Цар","","/Ударная отвёртка","","550,00","1,0","12","514 800","6 177 600,00","0,000",""] | E11: БД.ОБ | F11: Инструмент /Ударная отвёртка | G11: Инструмент
A12: ob | B12: ATBN052/Динамометрический ключ 1/4 2-20Нм | C12: atbn052/динамометрическийключ1/42-20нм | D12: ["3","Инструмент","ОБ.050","ATBN052","Динамометрический ключ 1/4 2-20Нм","Airline","","","","Цар","","ATBN052/Динамометрический ключ 1/4 2-20Нм","","3 000,00","1,0","12","514 800","6 177 600,00","0,000",""] | E12: БД.ОБ | F12: Инструмент ATBN052/Динамометрический ключ 1/4 2-20Нм | G12: Инструмент
A13: ob | B13: B25H064/Пистолет для заливки пластика | C13: b25h064/пистолетдлязаливкипластика | D13: ["10","Инструмент","ОБ.059","B25H064","Пистолет для заливки пластика","Robatech","Литье пластика","600","","Цар","","B25H064/Пистолет для заливки пластика","","250 000,00","1,0","12","514 800","6 177 600,00","0,040",""] | E13: БД.ОБ | F13: Инструмент B25H064/Пистолет для заливки пластика | G13: Инструмент
A14: ob | B14: DT-8920/Дифманометр-Термоанемометр | C14: dt-8920/дифманометр-термоанемометр | D14: ["1","Инструмент","ОБ.048","DT-8920","Дифманометр-Термоанемометр","--------------------------","","","","Цар","","DT-8920/Дифманометр-Термоанемометр","","35 000,00","1,0","12","514 800","6 177 600,00","0,006",""] | E14: БД.ОБ | F14: Инструмент DT-8920/Дифманометр-Термоанемометр | G14: Инструмент
A15: ob | B15: HC-70/Ножницы секторные | C15: hc-70/ножницысекторные | D15: ["4","Инструмент","ОБ.051","HC-70","Ножницы секторные","КВТ","","","","Цар","","HC-70/Ножницы секторные","","14 000,00","1,0","12","514 800","6 177 600,00","0,002",""] | E15: БД.ОБ | F15: Инструмент HC-70/Ножницы секторные | G15: Инструмент
A16: ob | B16: L-107/Пром. Термоклеевой пистолет | C16: l-107/пром.термоклеевойпистолет | D16: ["6","Инструмент","ОБ.053","L-107","Пром. Термоклеевой пистолет","Lead pack","","","","Цар","","L-107/Пром. Термоклеевой пистолет","","15 000,00","1,0","12","514 800","6 177 600,00","0,002",""] | E16: БД.ОБ | F16: Инструмент L-107/Пром. Термоклеевой пистолет | G16: Инструмент
... A193: ob | B193: КМ-22-8ПВ/Компрессор воздушный | C193: км-22-8пв/компрессорвоздушный | D193: ["102","Оборудование","ОБ.037","КМ-22-8ПВ","Компрессор воздушный","Kraftmachine","","22000","","Цар","","КМ-22-8ПВ/Компрессор воздушный","","600 000,00","1,0","12","514 800","6 177 600,00","0,097","120x80"] | E193: БД.ОБ | F193: Оборудование КМ-22-8ПВ/Компрессор воздушный | G193: Оборудование
A194: op | B194: Автомат резка + опрессовка | CUT_WIRE+1crimp | C194: cut_wire+1crimpавтоматрезка+опрессовка | D194: ["CUT_WIRE+1crimp","Автомат резка + опрессовка","","","BZW-2.0/Станок резки/ обжим+обжим","","","","","4,00","3600","2","0,00","4,00","0,42","0,42","0,24","Погонный","","","","3","0,2","5","","word","word"] | E194: БД.ОП | F194: Автомат резка + опрессовка | G194: CUT_WIRE+1crimp | H194: Автомат резка + опрессовка | I194: 4 | J194: 3600 | K194: 4
A195: op | B195: Автомат резка + опрессовка | CUT_WIRE+2crimp | C195: cut_wire+2crimpавтоматрезка+опрессовка | D195: ["CUT_WIRE+2crimp","Автомат резка + опрессовка","","","BZW-2.0/Станок резки/ обжим+обжим","","","","","4,80","3600","2","0,00","4,80","0,42","0,42","0,24","Погонный","","","","3","0,2","9","","word","word"] | E195: БД.ОП | F195: Автомат резка + опрессовка | G195: CUT_WIRE+2crimp | H195: Автомат резка + опрессовка | I195: 4.8 | J195: 3600 | K195: 4.8
A196: op | B196: Автомат резка + опрессовка + лужение | CUT_WIRE+1crimp+tin | C196: cut_wire+1crimp+tinавтоматрезка+опрессовка+лужение | D196: ["CUT_WIRE+1crimp+tin","Автомат резка + опрессовка + лужение","","","BZW-5.0+Z/Станок резки/ обжим+лужение","","","","","4,00","3600","2","0,00","4,00","0,42","0,42","0,29","Погонный","","","","3","0,2","5","","word","word"] | E196: БД.ОП | F196: Автомат резка + опрессовка + лужение | G196: CUT_WIRE+1crimp+tin | H196: Автомат резка + опрессовка + лужение | I196: 4 | J196: 3600 | K196: 4
A197: op | B197: Герметизация | SEAL | C197: sealгерметизация | D197: ["SEAL","Герметизация","","","","Жгут загерметизирован","","","","40,00","180","0","40,00","0,00","0,42","0,42","","Статичный","3","34","3","","","","","word","word"] | E197: БД.ОП | F197: Герметизация | G197: SEAL | H197: Герметизация | I197: 40 | J197: 180 | K197: 0
A198: op | B198: Заделка свободных концов | INS_END_CAP | C198: ins_end_capзаделкасвободныхконцов | D198: ["INS_END_CAP","Заделка свободных концов","","","","Жгут со свободными концами заделанными","","","","20,00","120","0","20,00","0,00","0,42","0,42","","Статичный","2","16","2","","","","","word","word"] | E198: БД.ОП | F198: Заделка свободных концов | G198: INS_END_CAP | H198: Заделка свободных концов | I198: 20 | J198: 120 | K198: 0
A199: op | B199: Закупки | BUY | C199: buyзакупки | D199: ["BUY","Закупки","","","","","","","","0,00","","","0,00","0,00","0,42","0,42","","Статичный","","","","","","","","word","word"] | E199: БД.ОП | F199: Закупки | G199: BUY | H199: Закупки | I199: 0 | K199: 0
A200: op | B200: Коаксиальная сборка | R/A-R/A short | C200: r/a-r/ashortкоаксиальнаясборка | D200: ["R/A-R/A short","Коаксиальная сборка","","","","","","","","193,50","6060","","193,50","69,50","0,42","0,42","","Статичный","","193,5","","","69,5","1","","word","word"] | E200: БД.ОП | F200: Коаксиальная сборка | G200: R/A-R/A short | H200: Коаксиальная сборка | I200: 193.5 | J200: 6060 | K200: 69.5
A201: op | B201: Коаксиальная сборка | R/A-R/A long | C201: r/a-r/alongкоаксиальнаясборка | D201: ["R/A-R/A long","Коаксиальная сборка","","","","","","","","223,50","6180","","223,50","69,50","0,42","0,42","","Статичный","","223,5","","","69,5","1","","word","word"] | E201: БД.ОП | F201: Коаксиальная сборка | G201: R/A-R/A long | H201: Коаксиальная сборка | I201: 223.5 | J201: 6180 | K201: 69.5
A202: op | B202: Коаксиальная сборка | R/A-Str short | C202: r/a-strshortкоаксиальнаясборка | D202: ["R/A-Str short","Коаксиальная сборка","","","","","","","","178,50","6060","","178,50","63,50","0,42","0,42","","Статичный","","178,5","","","63,5","1","","word","word"] | E202: БД.ОП | F202: Коаксиальная сборка | G202: R/A-Str short | H202: Коаксиальная сборка | I202: 178.5 | J202: 6060 | K202: 63.5
A203: op | B203: Коаксиальная сборка | R/A-Str long | C203: r/a-strlongкоаксиальнаясборка | D203: ["R/A-Str long","Коаксиальная сборка","","","","","","","","208,50","6180","","208,50","63,50","0,42","0,42","","Статичный","","208,5","","","63,5","1","","word","word"] | E203: БД.ОП | F203: Коаксиальная сборка | G203: R/A-Str long | H203: Коаксиальная сборка | I203: 208.5 | J203: 6180 | K203: 63.5
A204: op | B204: Коаксиальная сборка | Str-Str short | C204: str-strshortкоаксиальнаясборка | D204: ["Str-Str short","Коаксиальная сборка","","","","","","","","163,50","6060","","163,50","57,50","0,42","0,42","","Статичный","","163,5","","","57,5","1","","word","word"] | E204: БД.ОП | F204: Коаксиальная сборка | G204: Str-Str short | H204: Коаксиальная сборка | I204: 163.5 | J204: 6060 | K204: 57.5
A205: op | B205: Коаксиальная сборка | Str-Str long | C205: str-strlongкоаксиальнаясборка | D205: ["Str-Str long","Коаксиальная сборка","","","","","","","","193,50","6180","","193,50","57,50","0,42","0,42","","Статичный","","193,5","","","57,5","1","","word","word"] | E205: БД.ОП | F205: Коаксиальная сборка | G205: Str-Str long | H205: Коаксиальная сборка | I205: 193.5 | J205: 6180 | K205: 57.5
A206: op | B206: Коаксиальная сборка | R/A-MHF1 | C206: r/a-mhf1коаксиальнаясборка | D206: ["R/A-MHF1","Коаксиальная сборка","","","","","","","","131,50","5940","","131,50","45,50","0,42","0,42","","Статичный","","131,5","","","45,5","1","","word","word"] | E206: БД.ОП | F206: Коаксиальная сборка | G206: R/A-MHF1 | H206: Коаксиальная сборка | I206: 131.5 | J206: 5940 | K206: 45.5
A207: op | B207: Коаксиальная сборка | Str-MHF1 | C207: str-mhf1коаксиальнаясборка | D207: ["Str-MHF1","Коаксиальная сборка","","","","","","","","116,50","5940","","116,50","39,50","0,42","0,42","","Статичный","","116,5","","","39,5","1","","word","word"] | E207: БД.ОП | F207: Коаксиальная сборка | G207: Str-MHF1 | H207: Коаксиальная сборка | I207: 116.5 | J207: 5940 | K207: 39.5
A208: op | B208: Коаксиальная сборка | MHF1-MHF1 | C208: mhf1-mhf1коаксиальнаясборка | D208: ["MHF1-MHF1","Коаксиальная сборка","","","","","","","","44,50","5280","","44,50","12,50","0,42","0,42","","Статичный","","44,5","","","12,5","1","","word","word"] | E208: БД.ОП | F208: Коаксиальная сборка | G208: MHF1-MHF1 | H208: Коаксиальная сборка | I208: 44.5 | J208: 5280 | K208: 12.5
A209: op | B209: Коаксиальная сборка | R/A-R/A RG402(5) | C209: r/a-r/arg402(5)коаксиальнаясборка | D209: ["R/A-R/A RG402(5)","Коаксиальная сборка","","","","","","","","291,50","6180","","291,50","115,50","0,42","0,42","","Статичный","","291,5","","","115,5","1","","word","word"] | E209: БД.ОП | F209: Коаксиальная сборка | G209: R/A-R/A RG402(5) | H209: Коаксиальная сборка | I209: 291.5 | J209: 6180 | K209: 115.5
A210: op | B210: Коаксиальная сборка | Str-R/A RG402(5) | C210: str-r/arg402(5)коаксиальнаясборка | D210: ["Str-R/A RG402(5)","Коаксиальная сборка","","","","","","","","281,50","6180","","281,50","110,50","0,42","0,42","","Статичный","","281,5","","","110,5","1","","word","word"] | E210: БД.ОП | F210: Коаксиальная сборка | G210: Str-R/A RG402(5) | H210: Коаксиальная сборка | I210: 281.5 | J210: 6180 | K210: 110.5
A211: op | B211: Коаксиальная сборка | Str-Str RG402(5) | C211: str-strrg402(5)коаксиальнаясборка | D211: ["Str-Str RG402(5)","Коаксиальная сборка","","","","","","","","241,50","5940","","241,50","103,50","0,42","0,42","","Статичный","","241,5","","","103,5","1","","word","word"] | E211: БД.ОП | F211: Коаксиальная сборка | G211: Str-Str RG402(5) | H211: Коаксиальная сборка | I211: 241.5 | J211: 5940 | K211: 103.5
... A245: op | B245: Монтаж терминалов | INS_terminal_2,54-6,3 | C245: ins_terminal_2,54-6,3монтажтерминалов | D245: ["INS_terminal_2,54-6,3","Монтаж терминалов","","","","","","","","8,00","120","0","8,00","0,00","0,42","0,42","","Переменный","2","4","2","","","","","word","word"] | E245: БД.ОП | F245: Монтаж терминалов | G245: INS_terminal_2,54-6,3 | H245: Монтаж терминалов | I245: 8 | J245: 120 | K245: 0
A246: op | B246: Набор комплектующих | PREP2 | C246: prep2наборкомплектующих | D246: ["PREP2","Набор комплектующих","","","","","","","","0,00","","","0,00","0,00","0,42","0,42","","Статичный","","","","","","","","word","word"] | E246: БД.ОП | F246: Набор комплектующих | G246: PREP2 | H246: Набор комплектующих | I246: 0 | K246: 0
A247: op | B247: Опрессовка | PRS_SLEEVE_coax | C247: prs_sleeve_coaxопрессовка | D247: ["PRS_SLEEVE_coax","Опрессовка","","","SR-16M/Пресс пневматический для опрессовки кабельных контактов и наконечников","Обжатая гильза","","","","8,00","120","5","8,00","2,00","0,42","0,42","0,06","Статичный","6","","2","","2,0","1","","word","word"] | E247: БД.ОП | F247: Опрессовка | G247: PRS_SLEEVE_coax | H247: Опрессовка | I247: 8 | J247: 120 | K247: 2
A248: op | B248: Опрессовка | PRS_MHF | C248: prs_mhfопрессовка | D248: ["PRS_MHF","Опрессовка","","","SR-IPEX/Пресс пневматический для опрессовки радиочастотных разъемов MHF-1 (1.78)","","","","","6,00","120","20","6,00","1,00","0,42","0,42","0,06","Статичный","4","","2","","1,0","1","","word","word"] | E248: БД.ОП | F248: Опрессовка | G248: PRS_MHF | H248: Опрессовка | I248: 6 | J248: 120 | K248: 1
A249: op | B249: Опрессовка | PRS_MHF_LK | C249: prs_mhf_lkопрессовка | D249: ["PRS_MHF_LK","Опрессовка","","","SR-IPEX-L/Пресс пневматический для опрессовки радиочастотных разъемов MHF (замки)","","","","","6,00","120","20","6,00","1,00","0,42","0,42","0,06","Статичный","2","2","2","","1,0","1","","word","word"] | E249: БД.ОП | F249: Опрессовка | G249: PRS_MHF_LK | H249: Опрессовка | I249: 6 | J249: 120 | K249: 1
A250: op | B250: Опрессовка | PRS_IDC | C250: prs_idcопрессовка | D250: ["PRS_IDC","Опрессовка","","","WL-IDC/Пресс пневматический для опрессовки разъемов","","","","","6,00","120","20","6,00","1,00","0,42","0,42","0,01","Статичный","2","2","2","","1,0","1","","word","word"] | E250: БД.ОП | F250: Опрессовка | G250: PRS_IDC | H250: Опрессовка | I250: 6 | J250: 120 | K250: 1
A251: op | B251: Опрессовка | PRS_CAP | C251: prs_capопрессовка | D251: ["PRS_CAP","Опрессовка","","","WL-IDC/Пресс пневматический для опрессовки разъемов","","","","","14,00","120","20","14,00","1,00","0,42","0,42","0,01","Статичный","2","10","2","","1,0","1","","word","word"] | E251: БД.ОП | F251: Опрессовка | G251: PRS_CAP | H251: Опрессовка | I251: 14 | J251: 120 | K251: 1
A252: op | B252: Опрессовка | PRS_CAP_COAX | C252: prs_cap_coaxопрессовка | D252: ["PRS_CAP_COAX","Опрессовка","","","WL-IDC/Пресс пневматический для опрессовки разъемов","Коакс. разъём с запрессованной крышкой","","","","12,00","120","2","12,00","1,00","0,42","0,42","0,01","Статичный","2","8","2","","1,0","1","","word","word"] | E252: БД.ОП | F252: Опрессовка | G252: PRS_CAP_COAX | H252: Опрессовка | I252: 12 | J252: 120 | K252: 1
A253: op | B253: Опрессовка наконечников | PRS_HKИ/НВИ/РПИ | C253: prs_hkи/нви/рпиопрессовканаконечников | D253: ["PRS_HKИ/НВИ/РПИ","Опрессовка наконечников","","","SR-16M/Пресс пневматический для опрессовки кабельных контактов и наконечников","","","","","8,00","120","5","8,00","2,00","0,42","0,42","0,06","Переменный","6","","2","","2,0","1","","word","word"] | E253: БД.ОП | F253: Опрессовка наконечников | G253: PRS_HKИ/НВИ/РПИ | H253: Опрессовка наконечников | I253: 8 | J253: 120 | K253: 2
A254: op | B254: Опрессовка наконечников | PRS_НШВИ | C254: prs_ншвиопрессовканаконечников | D254: ["PRS_НШВИ","Опрессовка наконечников","","","SR-16M/Пресс пневматический для опрессовки кабельных контактов и наконечников","","","","","8,00","120","5","8,00","2,00","0,42","0,42","0,06","Переменный","6","","2","","2,0","1","","word","word"] | E254: БД.ОП | F254: Опрессовка наконечников | G254: PRS_НШВИ | H254: Опрессовка наконечников | I254: 8 | J254: 120 | K254: 2
A255: op | B255: Опрессовка наконечников | PRS_ТМЛ | C255: prs_тмлопрессовканаконечников | D255: ["PRS_ТМЛ","Опрессовка наконечников","","","BZW-20TS/Большой прес наконечников","","","","","28,00","120","5","28,00","2,00","0,42","0,42","0,05","Переменный","6","20","2","","2,0","1","","word","word"] | E255: БД.ОП | F255: Опрессовка наконечников | G255: PRS_ТМЛ | H255: Опрессовка наконечников | I255: 28 | J255: 120 | K255: 2
A256: op | B256: Опрессовка терминалов | PRS_TERMINAL_auto | C256: prs_terminal_autoопрессовкатерминалов | D256: ["PRS_TERMINAL_auto","Опрессовка терминалов","","","EW-50A(R)/Автомат для снятия изоляции и опрессовки контактов","","","","","6,00","1800","100","6,00","3,00","0,42","0,42","0,03","Переменный","4","","2","","3,0","1","","word","word"] | E256: БД.ОП | F256: Опрессовка терминалов | G256: PRS_TERMINAL_auto | H256: Опрессовка терминалов | I256: 6 | J256: 1800 | K256: 3
A257: op | B257: Опрессовка терминалов | PRS_TERMINAL_press | C257: prs_terminal_pressопрессовкатерминалов | D257: ["PRS_TERMINAL_press","Опрессовка терминалов","","","BZW-SF4040T(R)/Станок для обжима терминалов без зачистки","","","","","6,00","1800","100","6,00","3,00","0,42","0,42","0,02","Переменный","4","","2","","3,0","1","","word","word"] | E257: БД.ОП | F257: Опрессовка терминалов | G257: PRS_TERMINAL_press | H257: Опрессовка терминалов | I257: 6 | J257: 1800 | K257: 3
A258: op | B258: Опрессовка терминалов | PRS_TERMINAL_hand | C258: prs_terminal_handопрессовкатерминалов | D258: ["PRS_TERMINAL_hand","Опрессовка терминалов","","","","","","","","35,00","600","100","35,00","0,00","0,42","0,42","","Переменный","20","10","5","","","","","word","word"] | E258: БД.ОП | F258: Опрессовка терминалов | G258: PRS_TERMINAL_hand | H258: Опрессовка терминалов | I258: 35 | J258: 600 | K258: 0
... A288: op | B288: Печать маркировок | PRINT_MARK | C288: print_markпечатьмаркировок | D288: ["PRINT_MARK","Печать маркировок","","","SPP-L410/Принтер маркировочный портативный","Термоусадка на трубке","","","","2,00","600","5","1,00","2,00","0,42","0,42","0,01","Статичный","0","0","1","2","2,0","1","","word","word"] | E288: БД.ОП | F288: Печать маркировок | G288: PRINT_MARK | H288: Печать маркировок | I288: 2 | J288: 600 | K288: 2
A289: op | B289: Подготовительные работы | PREP1 | C289: prep1подготовительныеработы | D289: ["PREP1","Подготовительные работы","","","","","","","","0,00","","","0,00","0,00","0,42","0,42","","Статичный","","","","","","","","word","word"] | E289: БД.ОП | F289: Подготовительные работы | G289: PREP1 | H289: Подготовительные работы | I289: 0 | K289: 0
A290: op | B290: Разделка | STRIP_COAX_auto | C290: strip_coax_autoразделка | D290: ["STRIP_COAX_auto","Разделка","","","EW-1165/Машина для снятия изоляции с коаксиальных кабелей","","","","","10,00","600","3","10,00","4,00","0,42","0,42","0,04","Переменный","4","4","2","","4,0","1","","word","word"] | E290: БД.ОП | F290: Разделка | G290: STRIP_COAX_auto | H290: Разделка | I290: 10 | J290: 600 | K290: 4
A291: op | B291: Разделка | STRIP_COAX_hand | C291: strip_coax_handразделка | D291: ["STRIP_COAX_hand","Разделка","","","","","","","","100,00","1800","3","100,00","0,00","0,42","0,42","","Переменный","5","90","5","","","","","word","word"] | E291: БД.ОП | F291: Разделка | G291: STRIP_COAX_hand | H291: Разделка | I291: 100 | J291: 1800 | K291: 0
A292: op | B292: Разделка | STRIP_U/UTP_ethernet | C292: strip_u/utp_ethernetразделка | D292: ["STRIP_U/UTP_ethernet","Разделка","","","","","","","","15,00","120","3","15,00","0,00","0,42","0,42","","Переменный","3","10","2","","","","","word","word"] | E292: БД.ОП | F292: Разделка | G292: STRIP_U/UTP_ethernet | H292: Разделка | I292: 15 | J292: 120 | K292: 0
A293: op | B293: Разделка | STRIP_F/UTP_ethernet | C293: strip_f/utp_ethernetразделка | D293: ["STRIP_F/UTP_ethernet","Разделка","","","","","","","","20,00","120","3","20,00","0,00","0,42","0,42","","Переменный","3","15","2","","","","","word","word"] | E293: БД.ОП | F293: Разделка | G293: STRIP_F/UTP_ethernet | H293: Разделка | I293: 20 | J293: 120 | K293: 0
A294: op | B294: Разделка | STRIP_S/UTP_ethernet | C294: strip_s/utp_ethernetразделка | D294: ["STRIP_S/UTP_ethernet","Разделка","","","","","","","","25,00","120","3","25,00","0,00","0,42","0,42","","Переменный","3","20","2","","","","","word","word"] | E294: БД.ОП | F294: Разделка | G294: STRIP_S/UTP_ethernet | H294: Разделка | I294: 25 | J294: 120 | K294: 0
A295: op | B295: Разделка | STRIP_SF/UTP_ethernet | C295: strip_sf/utp_ethernetразделка | D295: ["STRIP_SF/UTP_ethernet","Разделка","","","","","","","","30,00","120","3","30,00","0,00","0,42","0,42","","Переменный","3","25","2","","","","","word","word"] | E295: БД.ОП | F295: Разделка | G295: STRIP_SF/UTP_ethernet | H295: Разделка | I295: 30 | J295: 120 | K295: 0
A296: op | B296: Разделка | STRIP_U/FTP_ethernet | C296: strip_u/ftp_ethernetразделка | D296: ["STRIP_U/FTP_ethernet","Разделка","","","","","","","","35,00","120","3","35,00","0,00","0,42","0,42","","Переменный","3","30","2","","","","","word","word"] | E296: БД.ОП | F296: Разделка | G296: STRIP_U/FTP_ethernet | H296: Разделка | I296: 35 | J296: 120 | K296: 0
A297: op | B297: Разделка | STRIP_F/FTP_ethernet | C297: strip_f/ftp_ethernetразделка | D297: ["STRIP_F/FTP_ethernet","Разделка","","","","","","","","40,00","120","3","40,00","0,00","0,42","0,42","","Переменный","3","35","2","","","","","word","word"] | E297: БД.ОП | F297: Разделка | G297: STRIP_F/FTP_ethernet | H297: Разделка | I297: 40 | J297: 120 | K297: 0
A298: op | B298: Разделка | STRIP_S/FTP_ethernet | C298: strip_s/ftp_ethernetразделка | D298: ["STRIP_S/FTP_ethernet","Разделка","","","","","","","","45,00","120","3","45,00","0,00","0,42","0,42","","Переменный","3","40","2","","","","","word","word"] | E298: БД.ОП | F298: Разделка | G298: STRIP_S/FTP_ethernet | H298: Разделка | I298: 45 | J298: 120 | K298: 0
A299: op | B299: Разделка | STRIP_SF/FTP_ethernet | C299: strip_sf/ftp_ethernetразделка | D299: ["STRIP_SF/FTP_ethernet","Разделка","","","","","","","","50,00","120","3","50,00","0,00","0,42","0,42","","Переменный","3","45","2","","","","","word","word"] | E299: БД.ОП | F299: Разделка | G299: STRIP_SF/FTP_ethernet | H299: Разделка | I299: 50 | J299: 120 | K299: 0
A300: op | B300: Разделка | STRIP_WIRE | C300: strip_wireразделка | D300: ["STRIP_WIRE","Разделка","","","BZW-D2.0S(R)/Большой стрипер","","","","","5,00","120","3","5,00","2,00","0,42","0,42","0,02","Переменный","3","","2","","2,0","1","","word","word"] | E300: БД.ОП | F300: Разделка | G300: STRIP_WIRE | H300: Разделка | I300: 5 | J300: 120 | K300: 2
A301: op | B301: Разделка | STRIP_CABLE_usb_2.0 | C301: strip_cable_usb_2.0разделка | D301: ["STRIP_CABLE_usb_2.0","Разделка","","","","Поготовленный кабель под пайку","","","","50,00","120","3","50,00","0,00","0,42","0,42","","Переменный","","50","","","","","","word","word"] | E301: БД.ОП | F301: Разделка | G301: STRIP_CABLE_usb_2.0 | H301: Разделка | I301: 50 | J301: 120 | K301: 0
... A332: op | B332: Усадка | HEAT_TTK_long | C332: heat_ttk_longусадка | D332: ["HEAT_TTK_long","Усадка","","","8620DX-Pro(R)/Станция паяльная термовоздушная","","","","","27,00","600","0","27,00","20,00","0,42","0,42","0,00","Статичный","2","24","1","","20,0","1","","word","word"] | E332: БД.ОП | F332: Усадка | G332: HEAT_TTK_long | H332: Усадка | I332: 27 | J332: 600 | K332: 20
A333: ter | B333: Connfly | DS1066 | C333: connflyds1066обжимнойконтактfemale | D333: ["Обжимной контакт","Connfly","","DS1066","2","Female","T-DS1066-SC600","","совмест. S2","FALSE","FALSE","TRUE","","5","","","","","30","24","0,05","0,2","","","Copper Alloy, покрытие Tin (код «6»)","2","https://en.connfly.com/static/upload/file//DS1066.pdf","нет данных производителя — замер в цехе (у Connfly в чертежах нет высоты обжима)"] | E333: БД.ТЕР | G333: Connfly | H333: DS1066 | J333: Female | K333: T-DS1066-SC600 | L333: 5 | N333: совмест. S2 | R333: 2
A334: ter | B334: Connfly | DS1069 | C334: connflyds1069 | D334: ["","Connfly","","DS1069","2,5","","T-DS1069-SC600","","","","","","","5","","","","","28","22","0,05","0,3","","","","","","нет данных производителя: чертежи Connfly без высоты обжима"] | E334: БД.ТЕР | G334: Connfly | H334: DS1069 | K334: T-DS1069-SC600 | L334: 5 | R334: 2.5
A335: ter | B335: Connfly | DS1072 | DS1072 | C335: connflyds1072ds1072обжимнойконтактfemale | D335: ["Обжимной контакт","Connfly","DS1072","DS1072","3,96","Female","T-DS1072-SC600","","","","","","","","","","","","24","18","0,2","0,75","1,3","2,8","-","7","https://www.connfly.com/static/upload/file/pdf/DS1072.pdf","чертёж Connfly C-DS1072-XXXXX-D содержит только габариты, высоты обжима нет (аналогично T-DS1069-SC600, уже в базе); ток 7А при 18AWG, напряжение 250В — из чертежа"] | E335: БД.ТЕР | G335: Connfly | H335: DS1072 | I335: DS1072 | J335: Female | K335: T-DS1072-SC600 | R335: 3.96
A336: ter | B336: Connfly | DS1072 | DS1072 | C336: connflyds1072ds1072обжимнойконтактfemale | D336: ["Обжимной контакт","Connfly","DS1072","DS1072","3,96","Female","T-DS1072-SC800","","","","","","","","","","","","24","18","0,2","0,75","1,3","2,8","Full gold flash","7","https://www.connfly.com/static/upload/file/pdf/DS1072.pdf","Официальный чертёж Connfly C-DS1072-XXXXX-D (тот же PDF, что и для T-DS1072-SC600): «PRODUCT NUMBER CODE» для Female Terminal T-DS1072-SC600, единственная переменная — Contact Plating (6: Tin — уже в БД, 8: Full gold flash — добавлено); высоты обжима чертёж не даёт (см. заметку у T-DS1072-SC600)."] | E336: БД.ТЕР | G336: Connfly | H336: DS1072 | I336: DS1072 | J336: Female | K336: T-DS1072-SC800 | R336: 3.96
A337: ter | B337: Connfly | DS1073 | DS1073 (MF series) | C337: connflyds1073ds1073(mfseries)обжимнойконтактfemale | D337: ["Обжимной контакт","Connfly","DS1073 (MF series)","DS1073","4,2","Female","","T-DS1073-02-SC600","","","","","","","","","","","24","18","0,2","0,75","","","Copper Alloy / Tin, изолятор Nylon 66","","https://www.elmatrix.ru/catalog/73437/","Connfly T-DS1073-02-SC600 — контакт-гнездо (Female) серии DS1073 для разъёмов MF (Mini-Fit-совместимых), 4,20мм шаг, 18-24AWG, 600V, медный сплав/олово, изолятор Nylon66. Как и другие контакты Connfly в базе (T-DS1071...), фирменных таблиц высоты обжима нет (см. crimp-height-sources) — не заполнено."] | E337: БД.ТЕР | G337: Connfly | H337: DS1073 | I337: DS1073 (MF series) | J337: Female | R337: 4.2
A338: ter | B338: Connfly | DS1073 | DS1073 (MF series) | C338: connflyds1073ds1073(mfseries)обжимнойконтактfemale | D338: ["Обжимной контакт","Connfly","DS1073 (MF series)","DS1073","4,2","Female","","T-DS1073-02-SC800","","","","","","","","","","","24","18","0,2","0,75","","","Copper Alloy / Full gold flash, изолятор Nylon 66","","https://en.connfly.com/static/upload/file//DS1073-02.pdf","Официальный datasheet Connfly DS1073-02 SERIES (en.connfly.com/static/upload/file//DS1073-02.pdf), «Product Number Code: Contact T-DS1073-02-XCX00»: Contact Plating (6 Tin / 8 Full gold flash) x Contact type (S Female — уже в БД T-DS1073-02-SC600, P Male); PDF не даёт отдельной таблицы высоты обжима. T-DS1073-02-PC600 подтверждён также на дистрибьюторской странице (uatronica.com) — https://en.connfly.com/static/upload/file//DS1073-02.pdf"] | E338: БД.ТЕР | G338: Connfly | H338: DS1073 | I338: DS1073 (MF series) | J338: Female | R338: 4.2
